Workbook

Sheet Daily Planner
A1: Daily Planner
A2: Fill in Subject / Topic / Subtopic / Hours each day. Day, Date and Streak are formula-driven — do not overtype them.
A3: Day | B3: Date | C3: Today's Goal | D3: Subject | E3: Topic | F3: Subtopic | G3: Estimated Hours | H3: Completed | I3: Revision Due | J3: Notes | K3: Streak (auto)
A4: =IF(B4="","",TEXT(B4,"dddd")) -> Wednesday | B4: 46239 | D4: Python Advanced | E4: CPython Internals | F4: PyObject struct & object layout | G4: 1 | H4: TRUE | I4: =FALSE() -> FALSE | K4: =IF(H4=TRUE(),1,0) -> 1
A5: =IF(B5="","",TEXT(B5,"dddd")) -> Thursday | B5: 46240 | H5: =FALSE() -> FALSE | I5: =FALSE() -> FALSE | K5: =IF(H5=TRUE(),K4+1,0) -> 0
A6: =IF(B6="","",TEXT(B6,"dddd")) -> Friday | B6: 46241 | H6: =FALSE() -> FALSE | I6: =FALSE() -> FALSE | K6: =IF(H6=TRUE(),K5+1,0) -> 0
A7: =IF(B7="","",TEXT(B7,"dddd")) -> Saturday | B7: 46242 | H7: =FALSE() -> FALSE | I7: =FALSE() -> FALSE | K7: =IF(H7=TRUE(),K6+1,0) -> 0
A8: =IF(B8="","",TEXT(B8,"dddd")) -> Sunday | B8: 46243 | H8: =FALSE() -> FALSE | I8: =FALSE() -> FALSE | K8: =IF(H8=TRUE(),K7+1,0) -> 0
A9: =IF(B9="","",TEXT(B9,"dddd")) -> Monday | B9: 46244 | H9: =FALSE() -> FALSE | I9: =FALSE() -> FALSE | K9: =IF(H9=TRUE(),K8+1,0) -> 0
A10: =IF(B10="","",TEXT(B10,"dddd")) -> Tuesday | B10: 46245 | H10: =FALSE() -> FALSE | I10: =FALSE() -> FALSE | K10: =IF(H10=TRUE(),K9+1,0) -> 0
A11: =IF(B11="","",TEXT(B11,"dddd")) -> Wednesday | B11: 46246 | H11: =FALSE() -> FALSE | I11: =FALSE() -> FALSE | K11: =IF(H11=TRUE(),K10+1,0) -> 0
A12: =IF(B12="","",TEXT(B12,"dddd")) -> Thursday | B12: 46247 | H12: =FALSE() -> FALSE | I12: =FALSE() -> FALSE | K12: =IF(H12=TRUE(),K11+1,0) -> 0
A13: =IF(B13="","",TEXT(B13,"dddd")) -> Friday | B13: 46248 | H13: =FALSE() -> FALSE | I13: =FALSE() -> FALSE | K13: =IF(H13=TRUE(),K12+1,0) -> 0
A14: =IF(B14="","",TEXT(B14,"dddd")) -> Saturday | B14: 46249 | H14: =FALSE() -> FALSE | I14: =FALSE() -> FALSE | K14: =IF(H14=TRUE(),K13+1,0) -> 0
A15: =IF(B15="","",TEXT(B15,"dddd")) -> Sunday | B15: 46250 | H15: =FALSE() -> FALSE | I15: =FALSE() -> FALSE | K15: =IF(H15=TRUE(),K14+1,0) -> 0
A16: =IF(B16="","",TEXT(B16,"dddd")) -> Monday | B16: 46251 | H16: =FALSE() -> FALSE | I16: =FALSE() -> FALSE | K16: =IF(H16=TRUE(),K15+1,0) -> 0
... A123: =IF(B123="","",TEXT(B123,"dddd")) -> Wednesday | B123: 46358 | H123: =FALSE() -> FALSE | I123: =FALSE() -> FALSE | K123: =IF(H123=TRUE(),K122+1,0) -> 0

Sheet Weekly Review
A1: Weekly Review
A2: Hours Studied pulls automatically from Daily Planner. Fill in the reflection columns every Sunday.
A3: Week # | B3: Week Starting | C3: Week Ending | D3: Hours Studied (auto) | E3: Concepts Learned | F3: Problems Solved | G3: Research Papers | H3: Projects | I3: Weak Areas | J3: Action Items
A4: 1 | B4: 46239 | C4: =B4+6 -> 46245 | D4: =SUMIFS('Daily Planner'!$G$4:$G$123,'Daily Planner'!$B$4:$B$123,">="&B4,'Daily Planner'!$B$4:$B$123,"<="&C4,'Daily Planner'!$H$4:$H$123,TRUE()) -> 1
A5: 2 | B5: 46246 | C5: =B5+6 -> 46252 | D5: =SUMIFS('Daily Planner'!$G$4:$G$123,'Daily Planner'!$B$4:$B$123,">="&B5,'Daily Planner'!$B$4:$B$123,"<="&C5,'Daily Planner'!$H$4:$H$123,TRUE()) -> 0
A6: 3 | B6: 46253 | C6: =B6+6 -> 46259 | D6: =SUMIFS('Daily Planner'!$G$4:$G$123,'Daily Planner'!$B$4:$B$123,">="&B6,'Daily Planner'!$B$4:$B$123,"<="&C6,'Daily Planner'!$H$4:$H$123,TRUE()) -> 0
A7: 4 | B7: 46260 | C7: =B7+6 -> 46266 | D7: =SUMIFS('Daily Planner'!$G$4:$G$123,'Daily Planner'!$B$4:$B$123,">="&B7,'Daily Planner'!$B$4:$B$123,"<="&C7,'Daily Planner'!$H$4:$H$123,TRUE()) -> 0
A8: 5 | B8: 46267 | C8: =B8+6 -> 46273 | D8: =SUMIFS('Daily Planner'!$G$4:$G$123,'Daily Planner'!$B$4:$B$123,">="&B8,'Daily Planner'!$B$4:$B$123,"<="&C8,'Daily Planner'!$H$4:$H$123,TRUE()) -> 0
A9: 6 | B9: 46274 | C9: =B9+6 -> 46280 | D9: =SUMIFS('Daily Planner'!$G$4:$G$123,'Daily Planner'!$B$4:$B$123,">="&B9,'Daily Planner'!$B$4:$B$123,"<="&C9,'Daily Planner'!$H$4:$H$123,TRUE()) -> 0
A10: 7 | B10: 46281 | C10: =B10+6 -> 46287 | D10: =SUMIFS('Daily Planner'!$G$4:$G$123,'Daily Planner'!$B$4:$B$123,">="&B10,'Daily Planner'!$B$4:$B$123,"<="&C10,'Daily Planner'!$H$4:$H$123,TRUE()) -> 0
A11: 8 | B11: 46288 | C11: =B11+6 -> 46294 | D11: =SUMIFS('Daily Planner'!$G$4:$G$123,'Daily Planner'!$B$4:$B$123,">="&B11,'Daily Planner'!$B$4:$B$123,"<="&C11,'Daily Planner'!$H$4:$H$123,TRUE()) -> 0
A12: 9 | B12: 46295 | C12: =B12+6 -> 46301 | D12: =SUMIFS('Daily Planner'!$G$4:$G$123,'Daily Planner'!$B$4:$B$123,">="&B12,'Daily Planner'!$B$4:$B$123,"<="&C12,'Daily Planner'!$H$4:$H$123,TRUE()) -> 0
A13: 10 | B13: 46302 | C13: =B13+6 -> 46308 | D13: =SUMIFS('Daily Planner'!$G$4:$G$123,'Daily Planner'!$B$4:$B$123,">="&B13,'Daily Planner'!$B$4:$B$123,"<="&C13,'Daily Planner'!$H$4:$H$123,TRUE()) -> 0
A14: 11 | B14: 46309 | C14: =B14+6 -> 46315 | D14: =SUMIFS('Daily Planner'!$G$4:$G$123,'Daily Planner'!$B$4:$B$123,">="&B14,'Daily Planner'!$B$4:$B$123,"<="&C14,'Daily Planner'!$H$4:$H$123,TRUE()) -> 0
A15: 12 | B15: 46316 | C15: =B15+6 -> 46322 | D15: =SUMIFS('Daily Planner'!$G$4:$G$123,'Daily Planner'!$B$4:$B$123,">="&B15,'Daily Planner'!$B$4:$B$123,"<="&C15,'Daily Planner'!$H$4:$H$123,TRUE()) -> 0
... A21: 18 | B21: 46358 | C21: =B21+6 -> 46364 | D21: =SUMIFS('Daily Planner'!$G$4:$G$123,'Daily Planner'!$B$4:$B$123,">="&B21,'Daily Planner'!$B$4:$B$123,"<="&C21,'Daily Planner'!$H$4:$H$123,TRUE()) -> 0

Sheet Monthly Review
A1: Monthly Review
A2: Topics Completed now pulls automatically from every curriculum sheet's Date Completed column. Projects/Research/Interview Progress stay manual since those sheets don't track a completion date per spec.
A3: Month | B3: Topics Completed (auto) | C3: Projects | D3: Research | E3: Interview Progress | F3: Skills Improved | G3: Goals Next Month
A4: August 2026 | B4: =COUNTIFS('Python Advanced'!O5:O34,">="&DATE(2026,8,1),'Python Advanced'!O5:O34,"<="&DATE(2026,8,31))+COUNTIFS('Data Structures & Algorithms'!O5:O38,">="&DATE(2026,8,1),'Data Structures & Algorithms'!O5:O38,"<="&DATE(2026,8,31))+COUNTIFS('Operating Systems'!O5:O33,">="&DATE(2026,8,1),'Operating Systems'!O5:O33,"<="&DATE(2026,8,31))+COUNTIFS('Computer Networking'!O5:O29,">="&DATE(2026,8,1),'Computer Networking'!O5:O29,"<="&DATE(2026,8,31))+COUNTIFS(Databases!O5:O24,">="&DATE(2026,8,1),Databases!O5:O24,"<="&DATE(2026,8,31))+COUNTIFS(Mathematics!O5:O28,">="&DATE(2026,8,1),Mathematics!O5:O28,"<="&DATE(2026,8,31))+COUNTIFS('Machine Learning'!O5:O23,">="&DATE(2026,8,1),'Machine Learning'!O5:O23,"<="&DATE(2026,8,31))+COUNTIFS('Deep Learning'!O5:O23,">="&DATE(2026,8,1),'Deep Learning'!O5:O23,"<="&DATE(2026,8,31))+COUNTIFS('LLM Engineering'!O5:O37,">="&DATE(2026,8,1),'LLM Engineering'!O5:O37,"<="&DATE(2026,8,31))+COUNTIFS('CUDA & GPU Programming'!O5:O22,">="&DATE(2026,8,1),'CUDA & GPU Programming'!O5:O22,"<="&DATE(2026,8,31))+COUNTIFS('Distributed Systems'!O5:O29,">="&DATE(2026,8,1),'Distributed Systems'!O5:O29,"<="&DATE(2026,8,31)) -> 1
A5: September 2026 | B5: =COUNTIFS('Python Advanced'!O5:O34,">="&DATE(2026,9,1),'Python Advanced'!O5:O34,"<="&DATE(2026,9,30))+COUNTIFS('Data Structures & Algorithms'!O5:O38,">="&DATE(2026,9,1),'Data Structures & Algorithms'!O5:O38,"<="&DATE(2026,9,30))+COUNTIFS('Operating Systems'!O5:O33,">="&DATE(2026,9,1),'Operating Systems'!O5:O33,"<="&DATE(2026,9,30))+COUNTIFS('Computer Networking'!O5:O29,">="&DATE(2026,9,1),'Computer Networking'!O5:O29,"<="&DATE(2026,9,30))+COUNTIFS(Databases!O5:O24,">="&DATE(2026,9,1),Databases!O5:O24,"<="&DATE(2026,9,30))+COUNTIFS(Mathematics!O5:O28,">="&DATE(2026,9,1),Mathematics!O5:O28,"<="&DATE(2026,9,30))+COUNTIFS('Machine Learning'!O5:O23,">="&DATE(2026,9,1),'Machine Learning'!O5:O23,"<="&DATE(2026,9,30))+COUNTIFS('Deep Learning'!O5:O23,">="&DATE(2026,9,1),'Deep Learning'!O5:O23,"<="&DATE(2026,9,30))+COUNTIFS('LLM Engineering'!O5:O37,">="&DATE(2026,9,1),'LLM Engineering'!O5:O37,"<="&DATE(2026,9,30))+COUNTIFS('CUDA & GPU Programming'!O5:O22,">="&DATE(2026,9,1),'CUDA & GPU Programming'!O5:O22,"<="&DATE(2026,9,30))+COUNTIFS('Distributed Systems'!O5:O29,">="&DATE(2026,9,1),'Distributed Systems'!O5:O29,"<="&DATE(2026,9,30)) -> 0
A6: October 2026 | B6: =COUNTIFS('Python Advanced'!O5:O34,">="&DATE(2026,10,1),'Python Advanced'!O5:O34,"<="&DATE(2026,10,31))+COUNTIFS('Data Structures & Algorithms'!O5:O38,">="&DATE(2026,10,1),'Data Structures & Algorithms'!O5:O38,"<="&DATE(2026,10,31))+COUNTIFS('Operating Systems'!O5:O33,">="&DATE(2026,10,1),'Operating Systems'!O5:O33,"<="&DATE(2026,10,31))+COUNTIFS('Computer Networking'!O5:O29,">="&DATE(2026,10,1),'Computer Networking'!O5:O29,"<="&DATE(2026,10,31))+COUNTIFS(Databases!O5:O24,">="&DATE(2026,10,1),Databases!O5:O24,"<="&DATE(2026,10,31))+COUNTIFS(Mathematics!O5:O28,">="&DATE(2026,10,1),Mathematics!O5:O28,"<="&DATE(2026,10,31))+COUNTIFS('Machine Learning'!O5:O23,">="&DATE(2026,10,1),'Machine Learning'!O5:O23,"<="&DATE(2026,10,31))+COUNTIFS('Deep Learning'!O5:O23,">="&DATE(2026,10,1),'Deep Learning'!O5:O23,"<="&DATE(2026,10,31))+COUNTIFS('LLM Engineering'!O5:O37,">="&DATE(2026,10,1),'LLM Engineering'!O5:O37,"<="&DATE(2026,10,31))+COUNTIFS('CUDA & GPU Programming'!O5:O22,">="&DATE(2026,10,1),'CUDA & GPU Programming'!O5:O22,"<="&DATE(2026,10,31))+COUNTIFS('Distributed Systems'!O5:O29,">="&DATE(2026,10,1),'Distributed Systems'!O5:O29,"<="&DATE(2026,10,31)) -> 0
A7: November 2026 | B7: =COUNTIFS('Python Advanced'!O5:O34,">="&DATE(2026,11,1),'Python Advanced'!O5:O34,"<="&DATE(2026,11,30))+COUNTIFS('Data Structures & Algorithms'!O5:O38,">="&DATE(2026,11,1),'Data Structures & Algorithms'!O5:O38,"<="&DATE(2026,11,30))+COUNTIFS('Operating Systems'!O5:O33,">="&DATE(2026,11,1),'Operating Systems'!O5:O33,"<="&DATE(2026,11,30))+COUNTIFS('Computer Networking'!O5:O29,">="&DATE(2026,11,1),'Computer Networking'!O5:O29,"<="&DATE(2026,11,30))+COUNTIFS(Databases!O5:O24,">="&DATE(2026,11,1),Databases!O5:O24,"<="&DATE(2026,11,30))+COUNTIFS(Mathematics!O5:O28,">="&DATE(2026,11,1),Mathematics!O5:O28,"<="&DATE(2026,11,30))+COUNTIFS('Machine Learning'!O5:O23,">="&DATE(2026,11,1),'Machine Learning'!O5:O23,"<="&DATE(2026,11,30))+COUNTIFS('Deep Learning'!O5:O23,">="&DATE(2026,11,1),'Deep Learning'!O5:O23,"<="&DATE(2026,11,30))+COUNTIFS('LLM Engineering'!O5:O37,">="&DATE(2026,11,1),'LLM Engineering'!O5:O37,"<="&DATE(2026,11,30))+COUNTIFS('CUDA & GPU Programming'!O5:O22,">="&DATE(2026,11,1),'CUDA & GPU Programming'!O5:O22,"<="&DATE(2026,11,30))+COUNTIFS('Distributed Systems'!O5:O29,">="&DATE(2026,11,1),'Distributed Systems'!O5:O29,"<="&DATE(2026,11,30)) -> 0
A8: December 2026 | B8: =COUNTIFS('Python Advanced'!O5:O34,">="&DATE(2026,12,1),'Python Advanced'!O5:O34,"<="&DATE(2026,12,31))+COUNTIFS('Data Structures & Algorithms'!O5:O38,">="&DATE(2026,12,1),'Data Structures & Algorithms'!O5:O38,"<="&DATE(2026,12,31))+COUNTIFS('Operating Systems'!O5:O33,">="&DATE(2026,12,1),'Operating Systems'!O5:O33,"<="&DATE(2026,12,31))+COUNTIFS('Computer Networking'!O5:O29,">="&DATE(2026,12,1),'Computer Networking'!O5:O29,"<="&DATE(2026,12,31))+COUNTIFS(Databases!O5:O24,">="&DATE(2026,12,1),Databases!O5:O24,"<="&DATE(2026,12,31))+COUNTIFS(Mathematics!O5:O28,">="&DATE(2026,12,1),Mathematics!O5:O28,"<="&DATE(2026,12,31))+COUNTIFS('Machine Learning'!O5:O23,">="&DATE(2026,12,1),'Machine Learning'!O5:O23,"<="&DATE(2026,12,31))+COUNTIFS('Deep Learning'!O5:O23,">="&DATE(2026,12,1),'Deep Learning'!O5:O23,"<="&DATE(2026,12,31))+COUNTIFS('LLM Engineering'!O5:O37,">="&DATE(2026,12,1),'LLM Engineering'!O5:O37,"<="&DATE(2026,12,31))+COUNTIFS('CUDA & GPU Programming'!O5:O22,">="&DATE(2026,12,1),'CUDA & GPU Programming'!O5:O22,"<="&DATE(2026,12,31))+COUNTIFS('Distributed Systems'!O5:O29,">="&DATE(2026,12,1),'Distributed Systems'!O5:O29,"<="&DATE(2026,12,31)) -> 0

Sheet Revision Planner
A1: Revision Planner
A2: Spaced-repetition schedule: 1 -> 3 -> 7 -> 14 -> 30 -> 90 -> 365 days. Each curriculum sheet computes its own Revision Date from Date Completed + Revision Stage; this sheet rolls those up and flags overdue items.
A3: Subject | B3: Total Topics | C3: Completed | D3: % Complete | E3: Overdue Revisions | F3: Due Within 3 Days
A4: Python Advanced | B4: =SUMPRODUCT(COUNTIF('Python Advanced'!A5:A34,{"Completed","In Progress","Not Started","Research","Project","Optional"})) -> 26 | C4: =COUNTIF('Python Advanced'!A5:A34,"Completed") -> 2 | D4: =IF(B4=0,0,ROUND(C4/B4*100,0)) -> 8 | E4: =COUNTIFS('Python Advanced'!Q5:Q34,"<"&TODAY(),'Python Advanced'!Q5:Q34,"<>") -> 0 | F4: =COUNTIFS('Python Advanced'!Q5:Q34,">="&TODAY(),'Python Advanced'!Q5:Q34,"<="&TODAY()+3) -> 0
A5: Data Structures & Algorithms | B5: =SUMPRODUCT(COUNTIF('Data Structures & Algorithms'!A5:A38,{"Completed","In Progress","Not Started","Research","Project","Optional"})) -> 29 | C5: =COUNTIF('Data Structures & Algorithms'!A5:A38,"Completed") -> 0 | D5: =IF(B5=0,0,ROUND(C5/B5*100,0)) -> 0 | E5: =COUNTIFS('Data Structures & Algorithms'!Q5:Q38,"<"&TODAY(),'Data Structures & Algorithms'!Q5:Q38,"<>") -> 0 | F5: =COUNTIFS('Data Structures & Algorithms'!Q5:Q38,">="&TODAY(),'Data Structures & Algorithms'!Q5:Q38,"<="&TODAY()+3) -> 0
A6: Operating Systems | B6: =SUMPRODUCT(COUNTIF('Operating Systems'!A5:A33,{"Completed","In Progress","Not Started","Research","Project","Optional"})) -> 25 | C6: =COUNTIF('Operating Systems'!A5:A33,"Completed") -> 0 | D6: =IF(B6=0,0,ROUND(C6/B6*100,0)) -> 0 | E6: =COUNTIFS('Operating Systems'!Q5:Q33,"<"&TODAY(),'Operating Systems'!Q5:Q33,"<>") -> 0 | F6: =COUNTIFS('Operating Systems'!Q5:Q33,">="&TODAY(),'Operating Systems'!Q5:Q33,"<="&TODAY()+3) -> 0
A7: Computer Networking | B7: =SUMPRODUCT(COUNTIF('Computer Networking'!A5:A29,{"Completed","In Progress","Not Started","Research","Project","Optional"})) -> 21 | C7: =COUNTIF('Computer Networking'!A5:A29,"Completed") -> 0 | D7: =IF(B7=0,0,ROUND(C7/B7*100,0)) -> 0 | E7: =COUNTIFS('Computer Networking'!Q5:Q29,"<"&TODAY(),'Computer Networking'!Q5:Q29,"<>") -> 0 | F7: =COUNTIFS('Computer Networking'!Q5:Q29,">="&TODAY(),'Computer Networking'!Q5:Q29,"<="&TODAY()+3) -> 0
A8: Databases | B8: =SUMPRODUCT(COUNTIF(Databases!A5:A24,{"Completed","In Progress","Not Started","Research","Project","Optional"})) -> 17 | C8: =COUNTIF(Databases!A5:A24,"Completed") -> 0 | D8: =IF(B8=0,0,ROUND(C8/B8*100,0)) -> 0 | E8: =COUNTIFS(Databases!Q5:Q24,"<"&TODAY(),Databases!Q5:Q24,"<>") -> 0 | F8: =COUNTIFS(Databases!Q5:Q24,">="&TODAY(),Databases!Q5:Q24,"<="&TODAY()+3) -> 0
A9: Mathematics | B9: =SUMPRODUCT(COUNTIF(Mathematics!A5:A28,{"Completed","In Progress","Not Started","Research","Project","Optional"})) -> 21 | C9: =COUNTIF(Mathematics!A5:A28,"Completed") -> 0 | D9: =IF(B9=0,0,ROUND(C9/B9*100,0)) -> 0 | E9: =COUNTIFS(Mathematics!Q5:Q28,"<"&TODAY(),Mathematics!Q5:Q28,"<>") -> 0 | F9: =COUNTIFS(Mathematics!Q5:Q28,">="&TODAY(),Mathematics!Q5:Q28,"<="&TODAY()+3) -> 0
A10: Machine Learning | B10: =SUMPRODUCT(COUNTIF('Machine Learning'!A5:A23,{"Completed","In Progress","Not Started","Research","Project","Optional"})) -> 16 | C10: =COUNTIF('Machine Learning'!A5:A23,"Completed") -> 0 | D10: =IF(B10=0,0,ROUND(C10/B10*100,0)) -> 0 | E10: =COUNTIFS('Machine Learning'!Q5:Q23,"<"&TODAY(),'Machine Learning'!Q5:Q23,"<>") -> 0 | F10: =COUNTIFS('Machine Learning'!Q5:Q23,">="&TODAY(),'Machine Learning'!Q5:Q23,"<="&TODAY()+3) -> 0
A11: Deep Learning | B11: =SUMPRODUCT(COUNTIF('Deep Learning'!A5:A23,{"Completed","In Progress","Not Started","Research","Project","Optional"})) -> 16 | C11: =COUNTIF('Deep Learning'!A5:A23,"Completed") -> 0 | D11: =IF(B11=0,0,ROUND(C11/B11*100,0)) -> 0 | E11: =COUNTIFS('Deep Learning'!Q5:Q23,"<"&TODAY(),'Deep Learning'!Q5:Q23,"<>") -> 0 | F11: =COUNTIFS('Deep Learning'!Q5:Q23,">="&TODAY(),'Deep Learning'!Q5:Q23,"<="&TODAY()+3) -> 0
A12: LLM Engineering | B12: =SUMPRODUCT(COUNTIF('LLM Engineering'!A5:A37,{"Completed","In Progress","Not Started","Research","Project","Optional"})) -> 29 | C12: =COUNTIF('LLM Engineering'!A5:A37,"Completed") -> 0 | D12: =IF(B12=0,0,ROUND(C12/B12*100,0)) -> 0 | E12: =COUNTIFS('LLM Engineering'!Q5:Q37,"<"&TODAY(),'LLM Engineering'!Q5:Q37,"<>") -> 0 | F12: =COUNTIFS('LLM Engineering'!Q5:Q37,">="&TODAY(),'LLM Engineering'!Q5:Q37,"<="&TODAY()+3) -> 0
A13: CUDA & GPU Programming | B13: =SUMPRODUCT(COUNTIF('CUDA & GPU Programming'!A5:A22,{"Completed","In Progress","Not Started","Research","Project","Optional"})) -> 15 | C13: =COUNTIF('CUDA & GPU Programming'!A5:A22,"Completed") -> 0 | D13: =IF(B13=0,0,ROUND(C13/B13*100,0)) -> 0 | E13: =COUNTIFS('CUDA & GPU Programming'!Q5:Q22,"<"&TODAY(),'CUDA & GPU Programming'!Q5:Q22,"<>") -> 0 | F13: =COUNTIFS('CUDA & GPU Programming'!Q5:Q22,">="&TODAY(),'CUDA & GPU Programming'!Q5:Q22,"<="&TODAY()+3) -> 0
A14: Distributed Systems | B14: =SUMPRODUCT(COUNTIF('Distributed Systems'!A5:A29,{"Completed","In Progress","Not Started","Research","Project","Optional"})) -> 22 | C14: =COUNTIF('Distributed Systems'!A5:A29,"Completed") -> 0 | D14: =IF(B14=0,0,ROUND(C14/B14*100,0)) -> 0 | E14: =COUNTIFS('Distributed Systems'!Q5:Q29,"<"&TODAY(),'Distributed Systems'!Q5:Q29,"<>") -> 0 | F14: =COUNTIFS('Distributed Systems'!Q5:Q29,">="&TODAY(),'Distributed Systems'!Q5:Q29,"<="&TODAY()+3) -> 0
A15: TOTAL | B15: =SUM(B4:B14) -> 237 | C15: =SUM(C4:C14) -> 2 | D15: =IF(B15=0,0,ROUND(C15/B15*100,0)) -> 1 | E15: =SUM(E4:E14) -> 0 | F15: =SUM(F4:F14) -> 0

Sheet Python Advanced
A1: Python Advanced
A2: Intermediate->expert CPython internals, concurrency, and native performance. No beginner syntax topics.
A3: Sheet Progress — 26 topics total | Q3: =ROUND(COUNTIF(A5:A34,"Completed")/SUMPRODUCT(COUNTIF(A5:A34,{"Completed","In Progress","Not Started","Research","Project","Optional"}))*100,0) -> 8
A4: Status | B4: Topic | C4: Subtopic | D4: Difficulty | E4: Prerequisites | F4: Learning Goal | G4: Est. Hours | H4: Best YouTube Resource | I4: Best Reading | J4: Official Documentation | K4: Coding Exercise | L4: Mini Project | M4: Interview Questions | N4: Notes | O4: Date Completed | P4: Revision Stage | Q4: Revision Date
A5: CPython Internals & Memory Model
A6: Completed | B6: CPython Internals | C6: PyObject struct & object layout | D6: Advanced | E6: C basics, Python fluency | F6: Understand how every Python object is represented in memory via PyObject/PyVarObject. | G6: 3 | H6: CPython Internals - James Powell (PyData) | I6: 'CPython Internals' book by Anthony Shaw (Ch.1-3) | J6: docs.python.org/3/c-api/structures.html | K6: Write a C extension that inspects an object's ob_refcnt and ob_type | L6: Build a memory-layout visualizer using ctypes | M6: What is the difference between PyObject and PyVarObject? | Why does every Python object carry a refcount? | N6: Foundation for everything else in this section. | O6: 46239 | P6: 0 | Q6: =IF(OR(O6="",P6=0),"",O6+CHOOSE(P6,1,3,7,14,30,90,365))
A7: Not Started | B7: Python Memory Model | C7: Private heap & pymalloc arenas | D7: Advanced | E7: CPython Internals basics | F7: Understand pymalloc's arena/pool/block allocator design for small objects. | G7: 3 | H7: Real Python - Memory Management in Python | I7: docs.python.org/3/c-api/memory.html | J7: docs.python.org/3/c-api/memory.html | K7: Use tracemalloc to profile allocations of a small script | L7: Build a script that visualizes allocation size distributions | M7: Why does CPython use its own allocator instead of malloc directly? | What is a pymalloc arena? | N7: tracemalloc is the practical entry point. | P7: 0 | Q7: =IF(OR(O7="",P7=0),"",O7+CHOOSE(P7,1,3,7,14,30,90,365))
A8: Not Started | B8: Reference Counting | C8: Refcounting mechanics & INCREF/DECREF | D8: Advanced | E8: CPython Internals | F8: Trace how Py_INCREF/Py_DECREF drive object lifetime. | G8: 2 | H8: CPython Internals - Refcounting explained (Anthony Shaw talk) | I8: 'CPython Internals' book Ch.4 | J8: docs.python.org/3/c-api/refcounting.html | K8: Use sys.getrefcount to trace an object across scopes | L8: N/A | M8: Why can sys.getrefcount overcount by one? | What happens on refcount reaching zero? | N8: Classic gotcha: getrefcount's own argument passing adds a reference. | P8: 0 | Q8: =IF(OR(O8="",P8=0),"",O8+CHOOSE(P8,1,3,7,14,30,90,365))
A9: Not Started | B9: Garbage Collection | C9: Generational GC & cycle detection | D9: Advanced | E9: Reference Counting | F9: Understand the 3-generation cyclic GC that supplements refcounting. | G9: 3 | H9: Real Python - Garbage Collection in Python | I9: docs.python.org/3/library/gc.html | J9: docs.python.org/3/library/gc.html | K9: Create and detect a reference cycle with gc.get_objects() | L9: Build a tool that flags reference cycles in a codebase | M9: Why is cyclic GC needed if refcounting exists? | What are generations 0/1/2 for? | N9: __del__ and cycles historically interacted badly pre-3.4. | P9: 0 | Q9: =IF(OR(O9="",P9=0),"",O9+CHOOSE(P9,1,3,7,14,30,90,365))
A10: Not Started | B10: Descriptors | C10: Data vs non-data descriptors, __get__/__set__ | D10: Advanced | E10: OOP fundamentals | F10: Master the descriptor protocol that underlies properties, methods, and slots. | G10: 3 | H10: Real Python - Descriptors | I10: docs.python.org/3/howto/descriptor.html | J10: docs.python.org/3/reference/datamodel.html#descriptors | K10: Implement a validated-attribute descriptor from scratch | L10: Build a typed-field ORM-style mini library using descriptors | M10: What's the precedence order between instance __dict__ and a data descriptor? | How does @property use descriptors? | N10: Understanding this unlocks how Django/SQLAlchemy fields work. | P10: 0 | Q10: =IF(OR(O10="",P10=0),"",O10+CHOOSE(P10,1,3,7,14,30,90,365))
A11: Not Started | B11: Decorators Internals | C11: Closures, functools.wraps, decorator factories | D11: Advanced | E11: Descriptors | F11: Go beyond syntax to understand closures and metadata preservation in decorators. | G11: 2 | H11: mCoding - Python Decorators | I11: Real Python - Primer on Python Decorators | J11: docs.python.org/3/library/functools.html#functools.wraps | K11: Write a parametrized retry decorator with backoff | L11: Build a timing/profiling decorator library | M11: Why does functools.wraps matter? | How do class-based decorators differ from function-based? | N11: Watch for late-binding closures in loops. | P11: 0 | Q11: =IF(OR(O11="",P11=0),"",O11+CHOOSE(P11,1,3,7,14,30,90,365))
A12: Not Started | B12: Metaclasses | C12: type(), __new__ vs __init__, metaclass conflicts | D12: Expert | E12: Descriptors, OOP | F12: Understand how classes themselves are instances of metaclasses. | G12: 4 | H12: mCoding - Metaclasses Explained | I12: Real Python - Python Metaclasses | J12: docs.python.org/3/reference/datamodel.html#metaclasses | K12: Build a metaclass that auto-registers subclasses | L12: Implement a simple ORM base using a metaclass | M12: When would you use __init_subclass__ instead of a metaclass? | What problem do ABCMeta and metaclasses solve? | N12: Prefer __init_subclass__ / __set_name__ when possible; metaclasses are a last resort. | P12: 0 | Q12: =IF(OR(O12="",P12=0),"",O12+CHOOSE(P12,1,3,7,14,30,90,365))
A13: Not Started | B13: Slots | C13: __slots__ memory savings & limitations | D13: Advanced | E13: Descriptors | F13: Understand how __slots__ removes per-instance __dict__ to save memory. | G13: 1 | H13: mCoding - __slots__ Explained | I13: Real Python - Python __slots__ | J13: docs.python.org/3/reference/datamodel.html#slots | K13: Benchmark memory usage of a class with vs without __slots__ | L13: N/A | M13: Why can't you use __slots__ with multiple inheritance easily? | What breaks when you add __slots__? | N13: Big win for millions of small objects (e.g. graph nodes). | P13: 0 | Q13: =IF(OR(O13="",P13=0),"",O13+CHOOSE(P13,1,3,7,14,30,90,365))
A14: Concurrency & Parallelism
A15: Completed | B15: GIL | C15: Global Interpreter Lock mechanics & 3.13 free-threading | D15: Expert | E15: CPython Internals | F15: Understand why the GIL exists and what the no-GIL (PEP 703) build changes. | G15: 4 | H15: David Beazley - Understanding the GIL | I15: Real Python - What is the GIL | J15: docs.python.org/3/glossary.html#term-global-interpreter-lock | K15: Benchmark CPU-bound threading vs multiprocessing | L15: N/A | M15: Why doesn't the GIL block I/O-bound concurrency? | What does PEP 703 change? | N15: Directly relevant to inference-server throughput design. | P15: 2 | Q15: =IF(OR(O15="",P15=0),"",O15+CHOOSE(P15,1,3,7,14,30,90,365))
A16: Not Started | B16: Multiprocessing Internals | C16: Process pools, pickling, shared memory | D16: Advanced | E16: GIL | F16: Understand fork/spawn start methods and IPC costs in multiprocessing. | G16: 3 | H16: Real Python - Multiprocessing in Python | I16: docs.python.org/3/library/multiprocessing.html | J16: docs.python.org/3/library/multiprocessing.shared_memory.html | K16: Build a producer-consumer pipeline using multiprocessing.Queue | L16: Parallelize a CPU-bound data preprocessing pipeline | M16: Why is spawn safer than fork on macOS/Windows? | When would you use shared_memory over a Queue? | N16: Pickling overhead is the usual bottleneck for large tensors. | P16: 0 | Q16: =IF(OR(O16="",P16=0),"",O16+CHOOSE(P16,1,3,7,14,30,90,365))
A17: Not Started | B17: Threading | C17: Thread pools, locks, condition variables | D17: Advanced | E17: GIL | F17: Master thread synchronization primitives beyond basic locks. | G17: 3 | H17: Corey Schafer - Threading Tutorial | I17: Real Python - Intro to Threading | J17: docs.python.org/3/library/threading.html | K17: Implement a bounded worker pool with a Condition variable | L17: N/A | M17: When is a RLock needed instead of a Lock? | What's a thundering herd and how do Conditions avoid it? | N17: Best for I/O-bound work given the GIL. | P17: 0 | Q17: =IF(OR(O17="",P17=0),"",O17+CHOOSE(P17,1,3,7,14,30,90,365))
A18: Not Started | B18: Asyncio Internals | C18: Event loop, tasks, futures | D18: Expert | E18: Threading | F18: Understand how the asyncio event loop schedules coroutines via a select/epoll loop. | G18: 4 | H18: David Beazley - Build Your Own Async | I18: Real Python - Async IO in Python | J18: docs.python.org/3/library/asyncio-eventloop.html | K18: Implement a minimal event loop from scratch with generators | L18: Build an async rate-limited API client | M18: What's the difference between a Task and a Future? | How does await suspend/resume a coroutine? | N18: Core to understanding FastAPI's request handling model. | P18: 0 | Q18: =IF(OR(O18="",P18=0),"",O18+CHOOSE(P18,1,3,7,14,30,90,365))
A19: Not Started | B19: Selectors | C19: selectors module & epoll/kqueue abstraction | D19: Advanced | E19: Asyncio Internals | F19: Understand the OS-level readiness notification asyncio is built on. | G19: 2 | H19: Real Python - Selectors module walkthrough | I19: docs.python.org/3/library/selectors.html | J19: docs.python.org/3/library/selectors.html | K19: Build a simple echo server using selectors directly (no asyncio) | L19: N/A | M19: Why is epoll preferred over select() at scale? | What is level-triggered vs edge-triggered readiness? | N19: This is the layer directly beneath asyncio's event loop. | P19: 0 | Q19: =IF(OR(O19="",P19=0),"",O19+CHOOSE(P19,1,3,7,14,30,90,365))
A20: Not Started | B20: Concurrency Models | C20: Choosing threads vs processes vs asyncio | D20: Advanced | E20: GIL, Asyncio Internals | F20: Build intuition for choosing the right concurrency model for a workload. | G20: 2 | H20: Anthony Explains - Concurrency in Python | I20: Real Python - Speed Up Python with Concurrency | J20: docs.python.org/3/library/concurrency.html | K20: Benchmark the same workload under threading/multiprocessing/asyncio | L20: N/A | M20: How do you choose between threads, processes, and asyncio for an ML inference server? | N20: Common system-design interview follow-up. | P20: 0 | Q20: =IF(OR(O20="",P20=0),"",O20+CHOOSE(P20,1,3,7,14,30,90,365))
A21: Language Internals & Bytecode
A22: Not Started | B22: Bytecode | C22: dis module, stack-based VM execution | D22: Advanced | E22: CPython Internals | F22: Read and interpret CPython bytecode to understand execution cost. | G22: 3 | H22: mCoding - Reading Python Bytecode | I22: Real Python - Bytecode intro | J22: docs.python.org/3/library/dis.html | K22: Use dis.dis to compare bytecode for a for-loop vs a list comprehension | L22: N/A | M22: Why are list comprehensions often faster than equivalent for-loops? | What is a stack-based VM? | N22: Useful for micro-optimization interview questions. | P22: 0 | Q22: =IF(OR(O22="",P22=0),"",O22+CHOOSE(P22,1,3,7,14,30,90,365))
A23: Not Started | B23: Python Compiler | C23: AST, compile phases, peephole optimizer | D23: Expert | E23: Bytecode | F23: Trace source code from AST to bytecode through the compiler pipeline. | G23: 3 | H23: CPython compiler pipeline talk - James Powell | I23: 'CPython Internals' Ch.8-9 | J23: docs.python.org/3/library/ast.html | K23: Write an AST transformer that rewrites a simple expression | L23: N/A | M23: What are the compilation stages from source to bytecode? | What does the peephole optimizer do? | N23: Powers tools like Bandit, and custom linters. | P23: 0 | Q23: =IF(OR(O23="",P23=0),"",O23+CHOOSE(P23,1,3,7,14,30,90,365))
A24: Not Started | B24: Context Managers | C24: __enter__/__exit__, contextlib, ExitStack | D24: Advanced | E24: Descriptors | F24: Master resource-management patterns beyond basic 'with' usage. | G24: 2 | H24: mCoding - Context Managers | I24: Real Python - Context Managers and Python's with Statement | J24: docs.python.org/3/library/contextlib.html | K24: Build a nested-resource manager using contextlib.ExitStack | L24: Build a DB transaction context manager with rollback on exception | M24: How does __exit__'s return value suppress exceptions? | What problem does ExitStack solve? | N24: ExitStack is underused and great for dynamic resource counts. | P24: 0 | Q24: =IF(OR(O24="",P24=0),"",O24+CHOOSE(P24,1,3,7,14,30,90,365))
A25: Not Started | B25: Type Hints | C25: Structural typing, Protocol, overload | D25: Advanced | E25: Python fluency | F25: Use the typing module for structural (duck) typing contracts. | G25: 2 | H25: mCoding - Python Type Hints | I25: Real Python - Type Checking in Python | J25: docs.python.org/3/library/typing.html | K25: Define a Protocol for a 'Trainable' interface and type-check with mypy | L25: N/A | M25: What's the difference between nominal and structural typing? | When would you use @overload? | N25: Protocols are close to Go/TS-style interfaces. | P25: 0 | Q25: =IF(OR(O25="",P25=0),"",O25+CHOOSE(P25,1,3,7,14,30,90,365))
A26: Not Started | B26: Generics | C26: TypeVar, Generic classes, PEP 695 syntax | D26: Advanced | E26: Type Hints | F26: Write reusable generic classes and functions with proper variance. | G26: 2 | H26: mCoding - Generics in Python | I26: Real Python - Generics | J26: docs.python.org/3/library/typing.html#generics | K26: Implement a generic Repository[T] class with mypy strict mode | L26: N/A | M26: What is covariance vs contravariance in generics? | How does PEP 695 simplify generic syntax (3.12+)? | N26: PEP 695 (3.12) meaningfully cleans up old TypeVar boilerplate. | P26: 0 | Q26: =IF(OR(O26="",P26=0),"",O26+CHOOSE(P26,1,3,7,14,30,90,365))
A27: Not Started | B27: Profiling | C27: cProfile, py-spy, line_profiler | D27: Advanced | E27: Python fluency | F27: Profile CPU-bound Python code and read flamegraphs. | G27: 3 | H27: Real Python - Profiling Python Code | I27: 'High Performance Python' Ch.2 (Gorelick & Ozsvath) | J27: docs.python.org/3/library/profile.html | K27: Profile a slow data-pipeline script and produce a flamegraph with py-spy | L27: Optimize a real script from 10x profiling findings | M27: What's the overhead difference between cProfile and py-spy? | When would you reach for line_profiler? | N27: py-spy can attach to a running production process with no code changes. | P27: 0 | Q27: =IF(OR(O27="",P27=0),"",O27+CHOOSE(P27,1,3,7,14,30,90,365))
A28: Not Started | B28: Optimization | C28: Algorithmic vs micro-optimization, caching | D28: Advanced | E28: Profiling | F28: Prioritize optimization effort using profiling data, not intuition. | G28: 2 | H28: Real Python - Python Performance Optimization | I28: 'High Performance Python' Ch.1 | J28: docs.python.org/3/library/functools.html#functools.lru_cache | K28: Apply lru_cache and measure the speedup on a recursive function | L28: N/A | M28: Why should you always profile before optimizing? | What's the tradeoff of lru_cache's memory use? | N28: Premature optimization is still the classic interview trap. | P28: 0 | Q28: =IF(OR(O28="",P28=0),"",O28+CHOOSE(P28,1,3,7,14,30,90,365))
A29: C Extensions & Native Performance
A30: Not Started | B30: C Extensions | C30: Writing a CPython C extension module | D30: Expert | E30: CPython Internals, C | F30: Write a native extension exposing a C function to Python. | G30: 5 | H30: Real Python - Building a C Extension | I30: 'CPython Internals' Ch.15 | J30: docs.python.org/3/extending/extending.html | K30: Write and build a C extension that speeds up a hot loop | L30: Port a slow pure-Python function to a C extension and benchmark | M30: What's the GIL's role when calling into a C extension? | How do you release the GIL in C code (Py_BEGIN_ALLOW_THREADS)? | N30: Releasing the GIL in C extensions is key for true parallelism. | P30: 0 | Q30: =IF(OR(O30="",P30=0),"",O30+CHOOSE(P30,1,3,7,14,30,90,365))
A31: Not Started | B31: Cython | C31: Typed Cython, cdef, memoryviews | D31: Advanced | E31: C Extensions basics | F31: Use Cython to compile typed Python-like code to C for speed. | G31: 4 | H31: Cython official tutorial (conference talks) | I31: 'Cython: A Guide for Python Programmers' (Smith) | J31: cython.readthedocs.io | K31: Cythonize a numeric hot loop and benchmark against pure Python/NumPy | L31: Speed up a data-preprocessing step with typed Cython | M31: What does 'cdef' buy you over a plain Python function? | How do memoryviews avoid copy overhead? | N31: Cython is the pragmatic middle ground before dropping to raw C. | P31: 0 | Q31: =IF(OR(O31="",P31=0),"",O31+CHOOSE(P31,1,3,7,14,30,90,365))
A32: Not Started | B32: PyBind11 | C32: Exposing C++ to Python, type casting | D32: Advanced | E32: C++ basics, C Extensions | F32: Bind C++ classes/functions into Python using pybind11. | G32: 4 | H32: pybind11 official walkthrough (conference talks) | I32: pybind11 documentation - First Steps | J32: pybind11.readthedocs.io | K32: Bind a small C++ class (e.g. a KV cache) to Python with pybind11 | L32: Wrap a C++ inference kernel and call it from Python | M32: How does pybind11 handle Python/C++ object lifetime? | Why is pybind11 preferred over raw CPython C-API for C++? | N32: This is exactly how PyTorch exposes its C++ core to Python. | P32: 0 | Q32: =IF(OR(O32="",P32=0),"",O32+CHOOSE(P32,1,3,7,14,30,90,365))
A33: Not Started | B33: NumPy Internals | C33: ndarray memory layout, strides, broadcasting | D33: Advanced | E33: C Extensions | F33: Understand strided memory layout and how broadcasting avoids copies. | G33: 3 | H33: Enthought - NumPy Internals | I33: 'From Python to NumPy' (Rougier, free online book) | J33: numpy.org/doc/stable/reference/internals.html | K33: Write a broadcasting rule checker from scratch and compare to NumPy's | L33: N/A | M33: What are strides and why do they make transpose free? | How does broadcasting decide compatible shapes? | N33: Foundational for reasoning about tensor ops performance. | P33: 0 | Q33: =IF(OR(O33="",P33=0),"",O33+CHOOSE(P33,1,3,7,14,30,90,365))
A34: Not Started | B34: PyTorch Internals | C34: Tensor storage, autograd graph, dispatcher | D34: Expert | E34: NumPy Internals | F34: Understand how PyTorch tensors, storage, and autograd tape fit together. | G34: 5 | H34: Edward Yang - PyTorch Internals talk | I34: 'PyTorch Internals' blog series - Edward Yang | J34: pytorch.org/docs/stable/notes/extending.html | K34: Trace a tensor operation through the dispatcher using torch's debug logging | L34: Implement a custom autograd.Function with backward pass | M34: What is the difference between a Tensor and its Storage? | How does the dispatcher route an op to a CPU/CUDA kernel? | N34: Directly relevant to writing custom CUDA-backed PyTorch ops. | P34: 0 | Q34: =IF(OR(O34="",P34=0),"",O34+CHOOSE(P34,1,3,7,14,30,90,365))

Sheet Data Structures & Algorithms
A1: Data Structures & Algorithms
A2: Advanced patterns and structures for coding interviews and systems-adjacent problem solving.
A3: Sheet Progress — 29 topics total | Q3: =ROUND(COUNTIF(A5:A38,"Completed")/SUMPRODUCT(COUNTIF(A5:A38,{"Completed","In Progress","Not Started","Research","Project","Optional"}))*100,0) -> 0
A4: Status | B4: Topic | C4: Subtopic | D4: Difficulty | E4: Prerequisites | F4: Learning Goal | G4: Est. Hours | H4: Best YouTube Resource | I4: Best Reading | J4: Official Documentation | K4: Coding Exercise | L4: Mini Project | M4: Interview Questions | N4: Notes | O4: Date Completed | P4: Revision Stage | Q4: Revision Date
A5: Arrays, Bit Manipulation & Searching
A6: Not Started | B6: Advanced Arrays | C6: In-place rotation, Dutch National Flag, cyclic sort | D6: Advanced | E6: Arrays basics | F6: Master in-place array manipulation patterns that avoid O(n) extra space. | G6: 2 | H6: NeetCode - Array patterns playlist | I6: 'Elements of Programming Interviews' Ch.5 | J6: N/A (pattern-based, no single doc) | K6: LeetCode 75 - Sort Colors (Dutch flag) | L6: N/A | M6: How does cyclic sort find missing numbers in O(1) space? | Why does the Dutch flag algorithm need 3 pointers? | N6: Pattern: LeetCode 41, 442, 448 all reuse cyclic sort. | P6: 0 | Q6: =IF(OR(O6="",P6=0),"",O6+CHOOSE(P6,1,3,7,14,30,90,365))
A7: Not Started | B7: Bit Manipulation | C7: XOR tricks, bitmasking, popcount | D7: Advanced | E7: Binary basics | F7: Use bitwise operators for O(1) space state tracking and fast arithmetic. | G7: 3 | H7: NeetCode - Bit Manipulation playlist | I7: 'Hacker's Delight' Ch.2 (Warren) | J7: docs.python.org/3/library/stdtypes.html#bitwise-operations-on-integer-types | K7: LeetCode 136 - Single Number, LeetCode 78 - Subsets via bitmask | L7: Build a bitmask-based DP solver for a small TSP instance | M7: Why does XOR-ing all elements find the unique one? | How do you enumerate all subsets using bitmasks? | N7: Bitmask DP shows up constantly in 'assign N items to K groups' problems. | P7: 0 | Q7: =IF(OR(O7="",P7=0),"",O7+CHOOSE(P7,1,3,7,14,30,90,365))
A8: Not Started | B8: Binary Search | C8: Search space reduction, binary search on answer | D8: Advanced | E8: Sorted arrays | F8: Recognize when a problem's answer space (not just an array) is monotonic and binary-searchable. | G8: 3 | H8: NeetCode - Binary Search playlist | I8: 'Elements of Programming Interviews' Ch.7 | J8: N/A | K8: LeetCode 875 - Koko Eating Bananas (binary search on answer) | L8: N/A | M8: How do you binary search on a monotonic answer function instead of an array? | What causes infinite loops in binary search implementations? | N8: 'Binary search the answer' is one of the highest-leverage patterns for mediums/hards. | P8: 0 | Q8: =IF(OR(O8="",P8=0),"",O8+CHOOSE(P8,1,3,7,14,30,90,365))
A9: Not Started | B9: Prefix Sum | C9: 1D/2D prefix sums, difference arrays | D9: Advanced | E9: Arrays | F9: Precompute range sums in O(1) query time after O(n) preprocessing. | G9: 2 | H9: NeetCode - Prefix Sum explained | I9: 'Competitive Programmer's Handbook' Ch.9 (Laaksonen, free PDF) | J9: N/A | K9: LeetCode 560 - Subarray Sum Equals K | L9: Build a range-update range-query tool with a difference array | M9: How does a difference array support O(1) range updates? | Why combine prefix sum with a hashmap for subarray-sum problems? | N9: Difference arrays are the DP-adjacent trick interviewers love to probe. | P9: 0 | Q9: =IF(OR(O9="",P9=0),"",O9+CHOOSE(P9,1,3,7,14,30,90,365))
A10: Not Started | B10: Sliding Window | C10: Fixed & variable window, two pointers | D10: Advanced | E10: Arrays | F10: Reduce O(n^2) brute force scans to O(n) using a shrinking/growing window. | G10: 3 | H10: NeetCode - Sliding Window playlist | I10: 'Elements of Programming Interviews' Ch.5 | J10: N/A | K10: LeetCode 3 - Longest Substring Without Repeating Characters | L10: N/A | M10: How do you decide window growth vs shrink conditions? | When is a fixed-size window preferable to variable? | N10: One of the top-3 highest-frequency FAANG/AI-lab patterns. | P10: 0 | Q10: =IF(OR(O10="",P10=0),"",O10+CHOOSE(P10,1,3,7,14,30,90,365))
A11: Not Started | B11: Monotonic Stack | C11: Next greater/smaller element patterns | D11: Advanced | E11: Stacks | F11: Use a monotonic stack to answer 'next greater element' style queries in O(n). | G11: 3 | H11: NeetCode - Monotonic Stack playlist | I11: 'Elements of Programming Interviews' Ch.8 | J11: N/A | K11: LeetCode 739 - Daily Temperatures | L11: N/A | M11: Why is each element pushed/popped at most once (amortized O(n))? | How does a monotonic stack solve histogram-area problems? | N11: LeetCode 84 (Largest Rectangle in Histogram) is the canonical hard version. | P11: 0 | Q11: =IF(OR(O11="",P11=0),"",O11+CHOOSE(P11,1,3,7,14,30,90,365))
A12: Not Started | B12: Monotonic Queue | C12: Sliding window maximum via deque | D12: Advanced | E12: Monotonic Stack, Sliding Window | F12: Maintain a running window max/min in O(1) amortized using a deque. | G12: 2 | H12: NeetCode - Sliding Window Maximum walkthrough | I12: 'Competitive Programmer's Handbook' Ch.9 | J12: N/A | K12: LeetCode 239 - Sliding Window Maximum | L12: N/A | M12: Why does a deque beat a heap for sliding-window max? | What invariant does the deque maintain? | N12: Common follow-up to the sliding window pattern above. | P12: 0 | Q12: =IF(OR(O12="",P12=0),"",O12+CHOOSE(P12,1,3,7,14,30,90,365))
A13: Trees, Tries & Advanced Structures
A14: Not Started | B14: Trie | C14: Prefix tree construction & search | D14: Advanced | E14: Trees | F14: Build a trie for fast prefix search, autocomplete, and word-break problems. | G14: 3 | H14: NeetCode - Implement Trie | I14: 'Competitive Programmer's Handbook' Ch.10 | J14: N/A | K14: LeetCode 208 - Implement Trie (Prefix Tree) | L14: Build an autocomplete engine backed by a trie | M14: What's the time complexity of trie insert/search vs a hashset? | How do you compress a trie (radix tree)? | N14: Directly relevant to tokenizer vocabulary lookups. | P14: 0 | Q14: =IF(OR(O14="",P14=0),"",O14+CHOOSE(P14,1,3,7,14,30,90,365))
A15: Not Started | B15: Fenwick Tree | C15: Binary Indexed Tree for range sum/update | D15: Expert | E15: Prefix Sum, Bit Manipulation | F15: Support O(log n) point-update and prefix-sum queries. | G15: 4 | H15: Errichto - Fenwick Tree tutorial | I15: 'Competitive Programmer's Handbook' Ch.9.2 | J15: N/A | K15: LeetCode 307 - Range Sum Query - Mutable | L15: Build a live-updating leaderboard using a Fenwick tree | M15: How does the lowbit trick (i & -i) navigate the tree? | When is a Fenwick tree preferable to a segment tree? | N15: Fenwick trees are the 'fast enough, much simpler' alternative to segment trees. | P15: 0 | Q15: =IF(OR(O15="",P15=0),"",O15+CHOOSE(P15,1,3,7,14,30,90,365))
A16: Not Started | B16: Segment Tree | C16: Range queries with lazy propagation | D16: Expert | E16: Fenwick Tree | F16: Build a segment tree supporting range updates and range queries in O(log n). | G16: 5 | H16: Errichto - Segment Tree tutorial | I16: 'Competitive Programmer's Handbook' Ch.9.3 | J16: N/A | K16: LeetCode 218 - The Skyline Problem (segment tree variant) | L16: Build a range-min-query engine with lazy propagation | M16: How does lazy propagation defer updates efficiently? | What's the space complexity of a segment tree? | N16: Segment trees are the go-to when a Fenwick tree can't express the query (e.g. range min). | P16: 0 | Q16: =IF(OR(O16="",P16=0),"",O16+CHOOSE(P16,1,3,7,14,30,90,365))
A17: Not Started | B17: Suffix Array | C17: Suffix sorting & LCP array | D17: Expert | E17: Strings, Sorting | F17: Build a suffix array for fast substring queries on large texts. | G17: 4 | H17: William Fiset - Suffix Array tutorial | I17: 'Algorithms on Strings' (Crochemore) selected chapters | J17: N/A | K17: LeetCode 1044 - Longest Duplicate Substring | L17: N/A | M17: How does the LCP array speed up substring comparisons? | What is the SA-IS construction algorithm's complexity? | N17: Rare in interviews but common in bioinformatics/search-index systems. | P17: 0 | Q17: =IF(OR(O17="",P17=0),"",O17+CHOOSE(P17,1,3,7,14,30,90,365))
A18: Not Started | B18: Suffix Automaton | C18: Minimal DFA for all substrings | D18: Expert | E18: Suffix Array, Automata basics | F18: Understand the suffix automaton as a compact structure for substring existence/counting. | G18: 4 | H18: William Fiset - Suffix Automaton overview | I18: cp-algorithms.com/string/suffix-automaton.html | J18: N/A | K18: Count distinct substrings of a string using a suffix automaton | L18: N/A | M18: Why does a suffix automaton have at most 2n-1 states? | How does it differ from a suffix tree? | N18: Advanced/competitive-programming territory; good for research-engineer breadth. | P18: 0 | Q18: =IF(OR(O18="",P18=0),"",O18+CHOOSE(P18,1,3,7,14,30,90,365))
A19: Not Started | B19: Union Find | C19: Path compression & union by rank | D19: Advanced | E19: Arrays | F19: Implement disjoint set union with near-O(1) amortized operations. | G19: 3 | H19: NeetCode - Union Find explained | I19: 'Elements of Programming Interviews' Ch.9 | J19: N/A | K19: LeetCode 200 - Number of Islands (Union-Find variant) | L19: Build a dynamic connectivity checker for a graph stream | M19: Why does union-by-rank + path compression give near-O(1) amortized time (inverse Ackermann)? | When is Union-Find preferable to BFS/DFS for connectivity? | N19: Kruskal's MST algorithm is built directly on Union-Find. | P19: 0 | Q19: =IF(OR(O19="",P19=0),"",O19+CHOOSE(P19,1,3,7,14,30,90,365))
A20: Graph Theory & Shortest Paths
A21: Not Started | B21: Graph Theory | C21: BFS/DFS traversal, topological sort | D21: Advanced | E21: Trees, Recursion | F21: Master the two foundational graph traversal strategies and their applications. | G21: 3 | H21: NeetCode - Graph Theory playlist | I21: 'Elements of Programming Interviews' Ch.10 | J21: N/A | K21: LeetCode 207 - Course Schedule (topological sort) | L21: N/A | M21: When would you use BFS over DFS for shortest path in unweighted graphs? | How does Kahn's algorithm detect a cycle? | N21: Foundation for almost everything else in this section. | P21: 0 | Q21: =IF(OR(O21="",P21=0),"",O21+CHOOSE(P21,1,3,7,14,30,90,365))
A22: Not Started | B22: Shortest Path | C22: Dijkstra, Bellman-Ford, Floyd-Warshall | D22: Advanced | E22: Graph Theory, Heaps | F22: Compare shortest-path algorithms and know when each applies (negative weights, all-pairs, etc). | G22: 4 | H22: William Fiset - Shortest Path Algorithms playlist | I22: 'Introduction to Algorithms' (CLRS) Ch.24-25 | J22: N/A | K22: LeetCode 743 - Network Delay Time (Dijkstra) | L22: Build a route-finder over a weighted graph with negative edges | M22: Why does Dijkstra fail with negative edge weights? | What's the time complexity of Floyd-Warshall and when is it worth it? | N22: Bellman-Ford's relaxation idea reappears in distributed consensus discussions. | P22: 0 | Q22: =IF(OR(O22="",P22=0),"",O22+CHOOSE(P22,1,3,7,14,30,90,365))
A23: Not Started | B23: Topological Sort | C23: Kahn's algorithm & DFS-based ordering | D23: Advanced | E23: Graph Theory | F23: Order a DAG's nodes such that all edges point forward. | G23: 2 | H23: NeetCode - Topological Sort | I23: 'Elements of Programming Interviews' Ch.10 | J23: N/A | K23: LeetCode 210 - Course Schedule II | L23: N/A | M23: How do you detect a cycle using DFS-based topological sort? | Why does Kahn's algorithm use in-degree counting? | N23: Directly analogous to task/DAG scheduling in Airflow. | P23: 0 | Q23: =IF(OR(O23="",P23=0),"",O23+CHOOSE(P23,1,3,7,14,30,90,365))
A24: Not Started | B24: Maximum Flow | C24: Ford-Fulkerson, Edmonds-Karp, BFS augmenting paths | D24: Expert | E24: Graph Theory, BFS | F24: Compute max flow / min cut on a flow network. | G24: 5 | H24: William Fiset - Max Flow Ford-Fulkerson | I24: 'Introduction to Algorithms' (CLRS) Ch.26 | J24: N/A | K24: LeetCode 1584 (adapted) - build a bipartite matching solver via max flow | L24: N/A | M24: Why does Edmonds-Karp guarantee polynomial time over naive Ford-Fulkerson? | How does max-flow relate to min-cut (max-flow min-cut theorem)? | N24: Rare in interviews but foundational for network/resource-allocation system design. | P24: 0 | Q24: =IF(OR(O24="",P24=0),"",O24+CHOOSE(P24,1,3,7,14,30,90,365))
A25: Not Started | B25: Minimum Cut | C25: Max-flow min-cut theorem applications | D25: Expert | E25: Maximum Flow | F25: Apply the max-flow min-cut duality to partitioning problems. | G25: 3 | H25: William Fiset - Min Cut explained | I25: 'Introduction to Algorithms' (CLRS) Ch.26.2 | J25: N/A | K25: Model a bipartite matching problem as a min-cut problem and solve it | L25: N/A | M25: How would you frame a resource-bottleneck problem as a min-cut problem? | N25: Good for research-engineer-level 'reduce to a known problem' interview questions. | P25: 0 | Q25: =IF(OR(O25="",P25=0),"",O25+CHOOSE(P25,1,3,7,14,30,90,365))
A26: Dynamic Programming, Greedy & Backtracking
A27: Not Started | B27: Dynamic Programming | C27: 1D/2D DP, state design, memoization vs tabulation | D27: Advanced | E27: Recursion | F27: Systematically design DP states and transitions instead of pattern-matching. | G27: 5 | H27: NeetCode - Dynamic Programming playlist | I27: 'Elements of Programming Interviews' Ch.16 | J27: N/A | K27: LeetCode 322 - Coin Change | L27: N/A | M27: How do you identify overlapping subproblems vs optimal substructure? | When does bottom-up beat top-down memoization? | N27: The single highest-leverage topic for FAANG/AI-lab onsites. | P27: 0 | Q27: =IF(OR(O27="",P27=0),"",O27+CHOOSE(P27,1,3,7,14,30,90,365))
A28: Not Started | B28: Advanced DP | C28: Digit DP, bitmask DP, DP on trees | D28: Expert | E28: Dynamic Programming, Bit Manipulation | F28: Extend DP to non-obvious state spaces: digits, subsets, and tree structures. | G28: 5 | H28: Errichto - Advanced DP techniques | I28: 'Competitive Programmer's Handbook' Ch.7 | J28: N/A | K28: LeetCode 1125 - Smallest Sufficient Team (bitmask DP) | L28: N/A | M28: How does DP on trees combine child subtree results at each node? | What's the state space of a bitmask-DP TSP solution? | N28: Research-engineer level; less common but signals real algorithmic depth. | P28: 0 | Q28: =IF(OR(O28="",P28=0),"",O28+CHOOSE(P28,1,3,7,14,30,90,365))
A29: Not Started | B29: Greedy | C29: Exchange argument & interval scheduling | D29: Advanced | E29: Sorting | F29: Prove greedy correctness using exchange arguments rather than intuition alone. | G29: 3 | H29: NeetCode - Greedy playlist | I29: 'Introduction to Algorithms' (CLRS) Ch.16 | J29: N/A | K29: LeetCode 435 - Non-overlapping Intervals | L29: N/A | M29: How do you prove a greedy choice is safe (exchange argument)? | When does greedy fail where DP succeeds? | N29: Interviewers often ask you to justify why greedy works here. | P29: 0 | Q29: =IF(OR(O29="",P29=0),"",O29+CHOOSE(P29,1,3,7,14,30,90,365))
A30: Not Started | B30: Backtracking | C30: Constraint satisfaction & pruning | D30: Advanced | E30: Recursion | F30: Systematically explore solution spaces with pruning for combinatorial problems. | G30: 3 | H30: NeetCode - Backtracking playlist | I30: 'Elements of Programming Interviews' Ch.15 | J30: N/A | K30: LeetCode 51 - N-Queens | L30: N/A | M30: How does backtracking differ from brute-force DFS? | What pruning strategies cut the search space fastest? | N30: N-Queens and Sudoku solvers are the canonical practice set. | P30: 0 | Q30: =IF(OR(O30="",P30=0),"",O30+CHOOSE(P30,1,3,7,14,30,90,365))
A31: Not Started | B31: Computational Geometry | C31: Convex hull, line sweep | D31: Expert | E31: Sorting, Vectors | F31: Apply geometric primitives (cross product, sweep line) to spatial problems. | G31: 3 | H31: William Fiset - Computational Geometry intro | I31: 'Competitive Programmer's Handbook' Ch.29 | J31: N/A | K31: LeetCode 587 - Erect the Fence (convex hull) | L31: N/A | M31: How does the cross product determine turn direction (CCW/CW)? | What's the time complexity of Graham scan? | N31: Rarely asked directly but shows up in spatial-indexing system design. | P31: 0 | Q31: =IF(OR(O31="",P31=0),"",O31+CHOOSE(P31,1,3,7,14,30,90,365))
A32: String Algorithms & Probabilistic Structures
A33: Not Started | B33: String Algorithms | C33: KMP, Z-function, Rabin-Karp | D33: Advanced | E33: Strings | F33: Match patterns in text in linear time instead of naive O(nm). | G33: 4 | H33: NeetCode / Errichto - String Matching Algorithms | I33: 'Competitive Programmer's Handbook' Ch.26 | J33: N/A | K33: LeetCode 28 - Find the Index of the First Occurrence (implement KMP) | L33: N/A | M33: How does the KMP failure function avoid re-scanning characters? | Why is Rabin-Karp's rolling hash O(1) per shift? | N33: KMP's failure function idea reappears in tokenizer/BPE merge logic. | P33: 0 | Q33: =IF(OR(O33="",P33=0),"",O33+CHOOSE(P33,1,3,7,14,30,90,365))
A34: Not Started | B34: Bloom Filter | C34: Probabilistic set membership | D34: Advanced | E34: Hashing basics | F34: Trade a small false-positive rate for O(1) space-efficient membership tests. | G34: 2 | H34: William Fiset - Bloom Filters explained | I34: 'Mining of Massive Datasets' Ch.4 (free Stanford book) | J34: redis.io/docs/data-types/probabilistic/bloom-filter | K34: Implement a Bloom filter from scratch and measure its false-positive rate | L34: Add a Bloom filter in front of a cache to avoid cache-miss storms | M34: How do you choose the number of hash functions to minimize false positives? | Why can't a Bloom filter support deletion? | N34: Directly usable in your Redis-based systems work. | P34: 0 | Q34: =IF(OR(O34="",P34=0),"",O34+CHOOSE(P34,1,3,7,14,30,90,365))
A35: Not Started | B35: HyperLogLog | C35: Cardinality estimation | D35: Expert | E35: Probability basics, Hashing | F35: Estimate distinct-element counts in a stream using sublinear memory. | G35: 3 | H35: Google - HyperLogLog explained (conference talk) | I35: 'Mining of Massive Datasets' Ch.4.4 | J35: redis.io/docs/data-types/probabilistic/hyperloglogs | K35: Implement a simplified HLL and compare its estimate to a true distinct count | L35: N/A | M35: How does HLL use the position of the leftmost 1-bit to estimate cardinality? | What's the typical error rate of HLL? | N35: Redis ships PFADD/PFCOUNT built on this exact structure. | P35: 0 | Q35: =IF(OR(O35="",P35=0),"",O35+CHOOSE(P35,1,3,7,14,30,90,365))
A36: Not Started | B36: Count-Min Sketch | C36: Approximate frequency counting | D36: Advanced | E36: Hashing, Probability | F36: Estimate item frequencies in a stream with bounded error using sublinear space. | G36: 2 | H36: Mining Massive Datasets - Count-Min Sketch lecture (Stanford CS246) | I36: 'Mining of Massive Datasets' Ch.4.5 | J36: N/A | K36: Implement a count-min sketch and measure its overestimation error | L36: N/A | M36: Why does count-min sketch only ever overestimate, never underestimate? | How do width and depth trade off accuracy vs memory? | N36: Useful for rate-limiting and top-k frequency estimation at scale. | P36: 0 | Q36: =IF(OR(O36="",P36=0),"",O36+CHOOSE(P36,1,3,7,14,30,90,365))
A37: Not Started | B37: LRU Cache | C37: Doubly linked list + hashmap design | D37: Advanced | E37: Hashing, Linked Lists | F37: Implement O(1) get/put cache eviction from scratch. | G37: 2 | H37: NeetCode - LRU Cache walkthrough | I37: 'Elements of Programming Interviews' Ch.13 | J37: N/A | K37: LeetCode 146 - LRU Cache | L37: N/A | M37: Why do you need both a hashmap and a doubly linked list? | How would you make an LRU cache thread-safe? | N37: One of the most frequently asked 'design a data structure' interview questions. | P37: 0 | Q37: =IF(OR(O37="",P37=0),"",O37+CHOOSE(P37,1,3,7,14,30,90,365))
A38: Not Started | B38: LFU Cache | C38: Frequency-bucketed eviction design | D38: Expert | E38: LRU Cache | F38: Implement O(1) get/put with least-frequently-used eviction. | G38: 3 | H38: NeetCode - LFU Cache walkthrough | I38: 'Elements of Programming Interviews' Ch.13 (extension) | J38: N/A | K38: LeetCode 460 - LFU Cache | L38: N/A | M38: How do frequency buckets keep LFU operations O(1)? | How do you break ties between equally-frequent items? | N38: A step up in difficulty from LRU; a strong signal question for senior roles. | P38: 0 | Q38: =IF(OR(O38="",P38=0),"",O38+CHOOSE(P38,1,3,7,14,30,90,365))

Sheet Operating Systems
A1: Operating Systems
A2: Kernel, memory, scheduling, and modern I/O interfaces (eBPF, io_uring) relevant to systems-level ML engineering.
A3: Sheet Progress — 25 topics total | Q3: =ROUND(COUNTIF(A5:A33,"Completed")/SUMPRODUCT(COUNTIF(A5:A33,{"Completed","In Progress","Not Started","Research","Project","Optional"}))*100,0) -> 0
A4: Status | B4: Topic | C4: Subtopic | D4: Difficulty | E4: Prerequisites | F4: Learning Goal | G4: Est. Hours | H4: Best YouTube Resource | I4: Best Reading | J4: Official Documentation | K4: Coding Exercise | L4: Mini Project | M4: Interview Questions | N4: Notes | O4: Date Completed | P4: Revision Stage | Q4: Revision Date
A5: Kernel, System Calls & Memory Management
A6: Not Started | B6: Kernel | C6: Monolithic vs microkernel, kernel/user space boundary | D6: Advanced | E6: OS fundamentals | F6: Understand how the kernel mediates all hardware access and enforces isolation. | G6: 3 | H6: Neso Academy - OS Kernel basics | I6: 'Operating Systems: Three Easy Pieces' (OSTEP) Ch.2 (free online) | J6: kernel.org/doc/html/latest/ | K6: Trace a syscall from user space to kernel space with strace | L6: N/A | M6: Why is a syscall slower than a function call? | What's the tradeoff between monolithic and microkernel designs? | N6: OSTEP is the best free resource for this entire sheet. | P6: 0 | Q6: =IF(OR(O6="",P6=0),"",O6+CHOOSE(P6,1,3,7,14,30,90,365))
A7: Not Started | B7: System Calls | C7: syscall mechanism, vDSO, syscall table | D7: Advanced | E7: Kernel | F7: Understand how the syscall instruction transitions privilege levels. | G7: 3 | H7: CS 162 Berkeley - Syscalls lecture | I7: OSTEP Ch.2-3 | J7: man7.org/linux/man-pages/man2/syscalls.2.html | K7: Use strace to profile syscall overhead of a Python script | L7: N/A | M7: What does vDSO optimize (e.g. gettimeofday)? | Why is a context switch required for a syscall? | N7: vDSO avoids a full kernel trap for cheap, frequently-called syscalls. | P7: 0 | Q7: =IF(OR(O7="",P7=0),"",O7+CHOOSE(P7,1,3,7,14,30,90,365))
A8: Not Started | B8: Memory Management | C8: Address spaces, heap/stack layout | D8: Advanced | E8: Kernel | F8: Understand how a process's virtual address space is organized. | G8: 3 | H8: CS 162 Berkeley - Memory Management lecture | I8: OSTEP Ch.13-15 | J8: N/A | K8: Inspect /proc/[pid]/maps for a running process | L8: N/A | M8: Why does every process see its own full address space? | What lives in the heap vs the stack? | N8: Directly useful when debugging container OOM kills. | P8: 0 | Q8: =IF(OR(O8="",P8=0),"",O8+CHOOSE(P8,1,3,7,14,30,90,365))
A9: Not Started | B9: Virtual Memory | C9: Address translation & demand paging | D9: Advanced | E9: Memory Management | F9: Understand how virtual addresses are translated to physical ones on demand. | G9: 4 | H9: CS 162 Berkeley - Virtual Memory lecture | I9: OSTEP Ch.18-19 | J9: N/A | K9: Simulate a simple page table lookup in Python | L9: N/A | M9: What triggers a page fault and how is it handled? | Why is demand paging more efficient than eager loading? | N9: Foundation for understanding container memory limits and OOM behavior. | P9: 0 | Q9: =IF(OR(O9="",P9=0),"",O9+CHOOSE(P9,1,3,7,14,30,90,365))
A10: Not Started | B10: Paging | C10: Multi-level page tables, page replacement (LRU, clock) | D10: Advanced | E10: Virtual Memory | F10: Understand how multi-level page tables scale to large address spaces. | G10: 4 | H10: CS 162 Berkeley - Paging lecture | I10: OSTEP Ch.20-22 | J10: N/A | K10: Implement a clock-algorithm page replacement simulator | L10: N/A | M10: Why use multi-level page tables instead of a flat table? | How does the clock algorithm approximate LRU cheaply? | N10: Clock algorithm is a recurring 'approximate LRU' interview theme (also see caching). | P10: 0 | Q10: =IF(OR(O10="",P10=0),"",O10+CHOOSE(P10,1,3,7,14,30,90,365))
A11: Not Started | B11: Segmentation | C11: Segments vs paging, external fragmentation | D11: Advanced | E11: Memory Management | F11: Compare segmentation to paging and understand why modern OSes favor paging. | G11: 2 | H11: CS 162 Berkeley - Segmentation lecture | I11: OSTEP Ch.16 | J11: N/A | K11: N/A | L11: N/A | M11: Why does segmentation cause external fragmentation but paging doesn't? | Where does segmentation still survive today (x86 legacy)? | N11: Mostly historical context now, but a common conceptual-comparison question. | P11: 0 | Q11: =IF(OR(O11="",P11=0),"",O11+CHOOSE(P11,1,3,7,14,30,90,365))
A12: Not Started | B12: TLB | C12: Translation Lookaside Buffer & TLB misses | D12: Advanced | E12: Paging | F12: Understand how the TLB caches address translations and why TLB misses are costly. | G12: 2 | H12: CS 162 Berkeley - TLB lecture | I12: OSTEP Ch.19 | J12: N/A | K12: Measure TLB-miss-sensitive vs friendly memory access patterns with perf | L12: N/A | M12: Why does a TLB miss require a full page-table walk? | How does a TLB shootdown work on multi-core systems? | N12: TLB shootdowns are a real source of tail latency in multi-threaded servers. | P12: 0 | Q12: =IF(OR(O12="",P12=0),"",O12+CHOOSE(P12,1,3,7,14,30,90,365))
A13: Not Started | B13: Huge Pages | C13: Transparent huge pages & reducing TLB pressure | D13: Advanced | E13: TLB | F13: Understand how huge pages reduce TLB miss rate for large-memory workloads. | G13: 2 | H13: Brendan Gregg - Huge Pages performance talk | I13: Linux kernel docs - Transparent Hugepage Support | J13: kernel.org/doc/html/latest/admin-guide/mm/transhuge.html | K13: Enable/disable THP and benchmark a memory-bound workload | L13: N/A | M13: Why do huge pages help GPU-adjacent memory-bound workloads? | What's a downside of transparent huge pages? | N13: Relevant to tuning large ML training/inference hosts. | P13: 0 | Q13: =IF(OR(O13="",P13=0),"",O13+CHOOSE(P13,1,3,7,14,30,90,365))
A14: Not Started | B14: NUMA | C14: Non-Uniform Memory Access & node affinity | D14: Expert | E14: Memory Management | F14: Understand how memory locality to a CPU socket affects latency at scale. | G14: 3 | H14: Brendan Gregg - NUMA performance talk | I14: OSTEP supplementary notes on NUMA | J14: kernel.org/doc/html/latest/vm/numa.html | K14: Use numactl to pin a process and measure latency difference | L14: N/A | M14: Why does cross-NUMA-node memory access cost more? | How would you tune a multi-GPU training job for NUMA affinity? | N14: Directly relevant to multi-GPU server performance tuning. | P14: 0 | Q14: =IF(OR(O14="",P14=0),"",O14+CHOOSE(P14,1,3,7,14,30,90,365))
A15: Scheduling & Synchronization
A16: Not Started | B16: Context Switching | C16: Save/restore state, cost of a context switch | D16: Advanced | E16: Kernel, Memory Management | F16: Understand what actually happens during a context switch and why it's expensive. | G16: 2 | H16: CS 162 Berkeley - Context Switching lecture | I16: OSTEP Ch.6 | J16: N/A | K16: Measure context-switch latency with a benchmark like lat_ctx | L16: N/A | M16: Why is a context switch more expensive than a function call? | What state must be saved/restored? | N16: Ties directly into why thread-pool sizing matters for throughput. | P16: 0 | Q16: =IF(OR(O16="",P16=0),"",O16+CHOOSE(P16,1,3,7,14,30,90,365))
A17: Not Started | B17: CPU Scheduling | C17: CFS, priority scheduling, real-time scheduling | D17: Advanced | E17: Context Switching | F17: Understand how Linux's Completely Fair Scheduler allocates CPU time. | G17: 3 | H17: CS 162 Berkeley - Scheduling lecture | I17: OSTEP Ch.7-9 | J17: kernel.org/doc/html/latest/scheduler/sched-design-CFS.html | K17: Inspect scheduling behavior with chrt and nice priorities | L17: N/A | M17: How does CFS use a red-black tree keyed on vruntime? | When would you use SCHED_FIFO over the default scheduler? | N17: CFS internals are a strong senior-level systems interview topic. | P17: 0 | Q17: =IF(OR(O17="",P17=0),"",O17+CHOOSE(P17,1,3,7,14,30,90,365))
A18: Not Started | B18: Synchronization | C18: Race conditions, critical sections | D18: Advanced | E18: Threading concepts | F18: Understand why shared mutable state requires coordinated access. | G18: 2 | H18: CS 162 Berkeley - Synchronization lecture | I18: OSTEP Ch.28 | J18: N/A | K18: Reproduce a race condition with threads and fix it with a lock | L18: N/A | M18: What makes an operation 'atomic'? | Why can even x += 1 be unsafe across threads? | N18: Foundation before Mutex/Semaphore/Lock-Free below. | P18: 0 | Q18: =IF(OR(O18="",P18=0),"",O18+CHOOSE(P18,1,3,7,14,30,90,365))
A19: Not Started | B19: Mutex | C19: Mutual exclusion implementation & spinlocks | D19: Advanced | E19: Synchronization | F19: Understand mutex implementation strategies from spinlocks to futexes. | G19: 2 | H19: CS 162 Berkeley - Locks lecture | I19: OSTEP Ch.28 | J19: man7.org/linux/man-pages/man2/futex.2.html | K19: Implement a spinlock using compare-and-swap | L19: N/A | M19: Why does Linux use futexes instead of always spinning or always sleeping? | What is priority inversion? | N19: Futex is the real mechanism under Python's threading.Lock on Linux. | P19: 0 | Q19: =IF(OR(O19="",P19=0),"",O19+CHOOSE(P19,1,3,7,14,30,90,365))
A20: Not Started | B20: Semaphore | C20: Counting semaphores & producer-consumer | D20: Advanced | E20: Mutex | F20: Use semaphores to coordinate access to a bounded number of resources. | G20: 2 | H20: CS 162 Berkeley - Semaphores lecture | I20: OSTEP Ch.31 | J20: N/A | K20: Implement a bounded buffer producer-consumer with semaphores | L20: N/A | M20: How does a semaphore differ from a mutex conceptually? | How would you implement a mutex using a semaphore? | N20: Classic producer-consumer questions test this directly. | P20: 0 | Q20: =IF(OR(O20="",P20=0),"",O20+CHOOSE(P20,1,3,7,14,30,90,365))
A21: Not Started | B21: Lock-Free Programming | C21: CAS, ABA problem, lock-free queues | D21: Expert | E21: Mutex, Memory ordering | F21: Understand how atomic compare-and-swap enables synchronization without blocking. | G21: 4 | H21: CppCon - Lock-Free Programming (concepts transfer across languages) | I21: 'The Art of Multiprocessor Programming' Ch.10 (Herlihy & Shavit) | J21: N/A | K21: Implement a lock-free stack using compare-and-swap | L21: N/A | M21: What is the ABA problem and how do you avoid it? | Why is lock-free code still hard even without deadlocks? | N21: Comes up in high-throughput inference-server queue design. | P21: 0 | Q21: =IF(OR(O21="",P21=0),"",O21+CHOOSE(P21,1,3,7,14,30,90,365))
A22: Modern Kernel Interfaces & I/O
A23: Not Started | B23: eBPF | C23: Sandboxed kernel programs for tracing/networking | D23: Expert | E23: Kernel, System Calls | F23: Understand how eBPF lets you run safe custom code inside the kernel for observability. | G23: 4 | H23: Brendan Gregg - BPF Performance Tools talk | I23: 'BPF Performance Tools' book (Gregg) - free sample chapters | J23: ebpf.io/what-is-ebpf | K23: Write a simple bpftrace one-liner to trace syscall latency | L23: N/A | M23: Why is eBPF verified/sandboxed before it runs in-kernel? | What problems does eBPF solve that used to require kernel modules? | N23: Increasingly a required skill for production infra/observability roles. | P23: 0 | Q23: =IF(OR(O23="",P23=0),"",O23+CHOOSE(P23,1,3,7,14,30,90,365))
A24: Not Started | B24: io_uring | C24: Async I/O without syscall-per-operation overhead | D24: Expert | E24: System Calls, Async IO | F24: Understand how io_uring's shared ring buffers eliminate per-I/O syscall cost. | G24: 4 | H24: Jens Axboe - io_uring introduction talk | I24: kernel.org io_uring documentation | J24: kernel.org/doc/html/latest/networking/io_uring.html | K24: Benchmark io_uring vs epoll for a simple I/O-bound workload (via a wrapper library) | L24: N/A | M24: How does io_uring avoid a syscall per I/O operation? | Why is it a major win for high-throughput servers? | N24: Cutting-edge topic; strong signal for systems-depth interviews. | P24: 0 | Q24: =IF(OR(O24="",P24=0),"",O24+CHOOSE(P24,1,3,7,14,30,90,365))
A25: Not Started | B25: epoll | C25: Readiness-based I/O multiplexing | D25: Advanced | E25: Selectors, System Calls | F25: Understand how epoll scales to tens of thousands of connections. | G25: 3 | H25: CS 162 Berkeley adjacent - epoll deep dive (conference talks) | I25: man7.org/linux/man-pages/man7/epoll.7.html | J25: man7.org/linux/man-pages/man7/epoll.7.html | K25: Build a minimal epoll-based echo server in C or via Python's selectors | L25: N/A | M25: Why does epoll scale better than select/poll (O(1) vs O(n))? | What's the difference between edge- and level-triggered epoll? | N25: This is literally what asyncio's event loop uses on Linux. | P25: 0 | Q25: =IF(OR(O25="",P25=0),"",O25+CHOOSE(P25,1,3,7,14,30,90,365))
A26: Not Started | B26: Signals | C26: Signal delivery, handlers, async-signal-safety | D26: Advanced | E26: Kernel | F26: Understand how the kernel delivers asynchronous notifications to processes. | G26: 2 | H26: CS 162 Berkeley - Signals lecture | I26: OSTEP supplementary notes | J26: man7.org/linux/man-pages/man7/signal.7.html | K26: Write a SIGTERM handler that gracefully shuts down a server | L26: N/A | M26: Why must signal handlers only call async-signal-safe functions? | How do you handle SIGTERM gracefully in a long-running service? | N26: Directly relevant to graceful shutdown in containerized services. | P26: 0 | Q26: =IF(OR(O26="",P26=0),"",O26+CHOOSE(P26,1,3,7,14,30,90,365))
A27: Not Started | B27: Interrupts | C27: Hardware interrupts vs software interrupts | D27: Advanced | E27: Kernel | F27: Understand how hardware interrupts trigger kernel execution outside normal syscalls. | G27: 2 | H27: CS 162 Berkeley - Interrupts lecture | I27: OSTEP Ch.6 (interrupt-related sections) | J27: N/A | K27: N/A | L27: N/A | M27: What's the difference between a hardware interrupt and a trap/exception? | Why do interrupt handlers run with interrupts disabled? | N27: Foundational, mostly conceptual for an application/systems engineer. | P27: 0 | Q27: =IF(OR(O27="",P27=0),"",O27+CHOOSE(P27,1,3,7,14,30,90,365))
A28: Not Started | B28: DMA | C28: Direct Memory Access & CPU offload | D28: Advanced | E28: Interrupts | F28: Understand how DMA lets devices transfer data without CPU involvement. | G28: 2 | H28: Brendan Gregg adjacent - DMA & I/O performance talk | I28: OSTEP supplementary I/O chapter | J28: N/A | K28: N/A | L28: N/A | M28: Why does DMA reduce CPU overhead for large transfers? | How does DMA relate to GPU-to-host memory transfers? | N28: Directly relevant to understanding cudaMemcpy performance. | P28: 0 | Q28: =IF(OR(O28="",P28=0),"",O28+CHOOSE(P28,1,3,7,14,30,90,365))
A29: Not Started | B29: Zero Copy Networking | C29: sendfile, mmap, avoiding buffer copies | D29: Expert | E29: DMA, epoll | F29: Understand how zero-copy techniques avoid redundant kernel/user buffer copies. | G29: 3 | H29: Brendan Gregg - Zero Copy talk | I29: 'Systems Performance' (Gregg) Ch.10 (selected) | J29: man7.org/linux/man-pages/man2/sendfile.2.html | K29: Benchmark sendfile() vs read+write for a file-serving workload | L29: N/A | M29: How does sendfile() avoid a userspace copy? | Where does zero-copy matter for high-throughput model-serving? | N29: Relevant to serving large model weight files efficiently. | P29: 0 | Q29: =IF(OR(O29="",P29=0),"",O29+CHOOSE(P29,1,3,7,14,30,90,365))
A30: Linux Performance Tools
A31: Not Started | B31: Linux Performance Tools | C31: perf, top, vmstat, iostat | D31: Advanced | E31: Linux fundamentals | F31: Use the standard Linux toolbox to diagnose CPU/memory/IO bottlenecks. | G31: 3 | H31: Brendan Gregg - Linux Performance Tools talk (USE Method) | I31: 'Systems Performance' (Gregg) Ch.4, free sample | J31: brendangregg.com/linuxperf.html | K31: Diagnose a synthetic CPU-bound vs IO-bound bottleneck using perf/vmstat/iostat | L31: N/A | M31: What is the USE method (Utilization, Saturation, Errors)? | How do you tell CPU-bound from IO-bound from vmstat output? | N31: Brendan Gregg's performance-tools poster is the single best free reference here. | P31: 0 | Q31: =IF(OR(O31="",P31=0),"",O31+CHOOSE(P31,1,3,7,14,30,90,365))
A32: Not Started | B32: Linux Performance Tools | C32: Flame graphs & perf record/report | D32: Advanced | E32: perf basics | F32: Generate and read flame graphs to find hot code paths system-wide. | G32: 2 | H32: Brendan Gregg - Flame Graphs talk | I32: brendangregg.com/flamegraphs.html | J32: github.com/brendangregg/FlameGraph | K32: Generate a flame graph for a CPU-bound Python or C workload | L32: N/A | M32: How do you read width vs depth in a flame graph? | What's the difference between an on-CPU and off-CPU flame graph? | N32: A must-have skill for any systems-level performance-debugging interview. | P32: 0 | Q32: =IF(OR(O32="",P32=0),"",O32+CHOOSE(P32,1,3,7,14,30,90,365))
A33: Not Started | B33: Linux Performance Tools | C33: strace, ltrace, and syscall-level debugging | D33: Advanced | E33: System Calls | F33: Trace syscalls and library calls to debug unexpected latency or behavior. | G33: 2 | H33: Julia Evans - strace zine/talk | I33: 'Systems Performance' (Gregg) Ch.4.4 | J33: man7.org/linux/man-pages/man1/strace.1.html | K33: Use strace -c to find which syscalls dominate a script's runtime | L33: N/A | M33: Why does strace slow down the traced process significantly? | When would you reach for ltrace instead of strace? | N33: Great first move when debugging 'why is this container slow'. | P33: 0 | Q33: =IF(OR(O33="",P33=0),"",O33+CHOOSE(P33,1,3,7,14,30,90,365))

Sheet Computer Networking
A1: Computer Networking
A2: Transport/application-layer protocols, load balancing, and RPC relevant to serving infrastructure.
A3: Sheet Progress — 21 topics total | Q3: =ROUND(COUNTIF(A5:A29,"Completed")/SUMPRODUCT(COUNTIF(A5:A29,{"Completed","In Progress","Not Started","Research","Project","Optional"}))*100,0) -> 0
A4: Status | B4: Topic | C4: Subtopic | D4: Difficulty | E4: Prerequisites | F4: Learning Goal | G4: Est. Hours | H4: Best YouTube Resource | I4: Best Reading | J4: Official Documentation | K4: Coding Exercise | L4: Mini Project | M4: Interview Questions | N4: Notes | O4: Date Completed | P4: Revision Stage | Q4: Revision Date
A5: Transport Layer
A6: Not Started | B6: TCP | C6: Three-way handshake, flow control, retransmission | D6: Advanced | E6: Networking fundamentals | F6: Understand TCP's reliability guarantees and how they're implemented. | G6: 4 | H6: CS 168 Berkeley - TCP lecture | I6: 'Computer Networking: A Top-Down Approach' Ch.3 (Kurose & Ross) | J6: datatracker.ietf.org/doc/html/rfc9293 | K6: Capture a TCP handshake with tcpdump and annotate each packet | L6: N/A | M6: Why does TCP use a 3-way handshake instead of 2? | How does the sliding window enable flow control? | N6: RFC 9293 is the current TCP spec (obsoletes RFC 793). | P6: 0 | Q6: =IF(OR(O6="",P6=0),"",O6+CHOOSE(P6,1,3,7,14,30,90,365))
A7: Not Started | B7: UDP | C7: Connectionless delivery & use cases | D7: Advanced | E7: Networking fundamentals | F7: Understand when UDP's lack of guarantees is a feature, not a bug. | G7: 1 | H7: CS 168 Berkeley - UDP lecture | I7: 'Computer Networking: A Top-Down Approach' Ch.3.3 | J7: datatracker.ietf.org/doc/html/rfc768 | K7: Build a simple UDP echo client/server | L7: N/A | M7: Why is UDP preferred for real-time streaming/gaming? | What has to be built on top of UDP to make it reliable (see QUIC)? | N7: UDP's simplicity is exactly why QUIC was built on top of it instead of TCP. | P7: 0 | Q7: =IF(OR(O7="",P7=0),"",O7+CHOOSE(P7,1,3,7,14,30,90,365))
A8: Not Started | B8: QUIC | C8: Stream multiplexing over UDP, 0-RTT | D8: Expert | E8: TCP, UDP, TLS | F8: Understand how QUIC solves TCP head-of-line blocking and speeds up connection setup. | G8: 4 | H8: Google/Cloudflare - QUIC explained talks | I8: 'HTTP/3 Explained' (free online book by Daniel Stenberg) | J8: datatracker.ietf.org/doc/html/rfc9000 | K8: Compare a QUIC vs TCP connection handshake with a packet capture | L8: N/A | M8: How does QUIC avoid head-of-line blocking across streams? | Why can QUIC achieve 0-RTT reconnection? | N8: QUIC is the transport underneath HTTP/3. | P8: 0 | Q8: =IF(OR(O8="",P8=0),"",O8+CHOOSE(P8,1,3,7,14,30,90,365))
A9: Not Started | B9: Congestion Control | C9: Slow start, AIMD, Reno vs Cubic | D9: Advanced | E9: TCP | F9: Understand how TCP infers and reacts to network congestion. | G9: 3 | H9: CS 168 Berkeley - Congestion Control lecture | I9: 'Computer Networking: A Top-Down Approach' Ch.3.7 | J9: datatracker.ietf.org/doc/html/rfc5681 | K9: Plot TCP's congestion window growth using a packet capture | L9: N/A | M9: Why does AIMD favor gradual increase and sharp decrease? | What's the practical difference between Reno and Cubic? | N9: Directly relevant to understanding throughput on high-bandwidth training clusters. | P9: 0 | Q9: =IF(OR(O9="",P9=0),"",O9+CHOOSE(P9,1,3,7,14,30,90,365))
A10: Not Started | B10: BBR | C10: Bottleneck Bandwidth and RTT congestion control | D10: Expert | E10: Congestion Control | F10: Understand how BBR models the network path instead of reacting to packet loss. | G10: 3 | H10: Google - BBR congestion control talk | I10: Google's BBR paper (ACM Queue, free) | J10: github.com/google/bbr | K10: Compare throughput of Cubic vs BBR on a lossy simulated link (e.g. with tc netem) | L10: N/A | M10: Why does BBR outperform loss-based algorithms on lossy but not congested links? | What two signals does BBR estimate? | N10: BBR is what many hyperscalers use for high-throughput data transfer. | P10: 0 | Q10: =IF(OR(O10="",P10=0),"",O10+CHOOSE(P10,1,3,7,14,30,90,365))
A11: Application Layer & Security
A12: Not Started | B12: HTTP/2 | C12: Multiplexing, header compression (HPACK) | D12: Advanced | E12: HTTP/1.1 basics | F12: Understand how HTTP/2 solves HTTP/1.1's connection-per-request inefficiency. | G12: 3 | H12: Cloudflare - HTTP/2 explained talk | I12: 'HTTP/2 in Action' selected chapters (free excerpts) | J12: datatracker.ietf.org/doc/html/rfc9113 | K12: Compare page-load waterfall for HTTP/1.1 vs HTTP/2 | L12: N/A | M12: How does HPACK reduce header overhead across requests? | What is stream multiplexing solving (head-of-line blocking at the app layer)? | N12: Still has TCP-level head-of-line blocking, which is what HTTP/3 fixes. | P12: 0 | Q12: =IF(OR(O12="",P12=0),"",O12+CHOOSE(P12,1,3,7,14,30,90,365))
A13: Not Started | B13: HTTP/3 | C13: QUIC-based HTTP, no TCP head-of-line blocking | D13: Expert | E13: HTTP/2, QUIC | F13: Understand how HTTP/3 fully removes head-of-line blocking by running over QUIC. | G13: 3 | H13: Cloudflare - HTTP/3 explained talk | I13: 'HTTP/3 Explained' (free online book) | J13: datatracker.ietf.org/doc/html/rfc9114 | K13: Test a site's HTTP/3 support and compare latency to HTTP/2 | L13: N/A | M13: Why does HTTP/3 avoid TCP-level head-of-line blocking while HTTP/2 doesn't? | What's the adoption tradeoff of HTTP/3 (UDP blocking by some networks)? | N13: Relevant to designing low-latency APIs for global inference endpoints. | P13: 0 | Q13: =IF(OR(O13="",P13=0),"",O13+CHOOSE(P13,1,3,7,14,30,90,365))
A14: Not Started | B14: TLS | C14: TLS 1.3 handshake, certificates, forward secrecy | D14: Advanced | E14: Cryptography basics | F14: Understand how TLS establishes a secure channel and what changed in 1.3. | G14: 4 | H14: Computerphile - TLS handshake explained | I14: 'Bulletproof TLS and PKI' selected chapters (Ivan Ristic, free samples) | J14: datatracker.ietf.org/doc/html/rfc8446 | K14: Capture and annotate a TLS 1.3 handshake with Wireshark | L14: N/A | M14: Why is TLS 1.3's handshake faster (1-RTT vs 2-RTT)? | What does forward secrecy protect against? | N14: TLS 1.3 removed several legacy/insecure cipher options entirely. | P14: 0 | Q14: =IF(OR(O14="",P14=0),"",O14+CHOOSE(P14,1,3,7,14,30,90,365))
A15: Not Started | B15: DNS | C15: Resolution hierarchy, caching, DNS-over-HTTPS | D15: Advanced | E15: Networking fundamentals | F15: Understand how domain names resolve through the recursive/authoritative hierarchy. | G15: 3 | H15: CS 168 Berkeley - DNS lecture | I15: 'Computer Networking: A Top-Down Approach' Ch.2.4 | J15: datatracker.ietf.org/doc/html/rfc1035 | K15: Trace a DNS resolution path with dig +trace | L15: N/A | M15: Why does DNS use a hierarchical, cached design? | What privacy problem does DoH (DNS over HTTPS) address? | N15: DNS misconfig is one of the most common real-world outage causes. | P15: 0 | Q15: =IF(OR(O15="",P15=0),"",O15+CHOOSE(P15,1,3,7,14,30,90,365))
A16: Routing, Load Balancing & Proxies
A17: Not Started | B17: Routing | C17: BGP basics, route propagation | D17: Advanced | E17: Networking fundamentals | F17: Understand how autonomous systems exchange routes across the internet. | G17: 3 | H17: CS 168 Berkeley - Routing/BGP lecture | I17: 'Computer Networking: A Top-Down Approach' Ch.5.4 | J17: datatracker.ietf.org/doc/html/rfc4271 | K17: N/A | L17: N/A | M17: Why is BGP a path-vector rather than distance-vector protocol? | What causes a BGP route leak/hijack? | N17: Mostly conceptual for an application/ML engineer, but a common systems-breadth question. | P17: 0 | Q17: =IF(OR(O17="",P17=0),"",O17+CHOOSE(P17,1,3,7,14,30,90,365))
A18: Not Started | B18: Load Balancers | C18: L4 vs L7 load balancing, health checks | D18: Advanced | E18: TCP, HTTP | F18: Understand the tradeoffs between transport-level and application-level load balancing. | G18: 3 | H18: NGINX - Load Balancing explained (official talk) | I18: NGINX docs - load balancing guide | J18: nginx.org/en/docs/http/load_balancing.html | K18: Configure NGINX as an L7 load balancer with round-robin and least-conn | L18: N/A | M18: When would you choose L4 over L7 load balancing? | How do health checks avoid routing to a dead backend? | N18: Directly relevant to designing multi-replica inference-serving deployments. | P18: 0 | Q18: =IF(OR(O18="",P18=0),"",O18+CHOOSE(P18,1,3,7,14,30,90,365))
A19: Not Started | B19: NGINX | C19: Reverse proxy config, upstream blocks | D19: Advanced | E19: Load Balancers, HTTP | F19: Configure NGINX as a production-grade reverse proxy in front of an API. | G19: 2 | H19: NGINX official crash course | I19: NGINX official documentation - beginner's guide | J19: nginx.org/en/docs/beginners_guide.html | K19: Set up NGINX in front of a FastAPI app with TLS termination | L19: Add rate limiting and caching to an NGINX reverse-proxy config | M19: What's the difference between proxy_pass and an upstream block? | How does NGINX handle connection keep-alive to backends? | N19: Given your FastAPI background, this connects directly to your existing stack. | P19: 0 | Q19: =IF(OR(O19="",P19=0),"",O19+CHOOSE(P19,1,3,7,14,30,90,365))
A20: Not Started | B20: Envoy | C20: Sidecar proxy, service mesh data plane | D20: Expert | E20: Load Balancers, gRPC | F20: Understand how Envoy provides observability, retries, and traffic shaping as a sidecar. | G20: 3 | H20: Envoy Proxy - official intro talk | I20: envoyproxy.io official docs - intro | J20: envoyproxy.io/docs/envoy/latest/intro/intro | K20: Run Envoy as a sidecar in front of a local service and inspect its stats endpoint | L20: N/A | M20: Why do service meshes use a sidecar proxy pattern? | What does Envoy's xDS API configure dynamically? | N20: Directly relevant to Kubernetes-based ML-serving infrastructure. | P20: 0 | Q20: =IF(OR(O20="",P20=0),"",O20+CHOOSE(P20,1,3,7,14,30,90,365))
A21: Not Started | B21: Reverse Proxy | C21: Caching, TLS termination, request routing | D21: Advanced | E21: NGINX/Envoy | F21: Understand the general responsibilities a reverse proxy takes off application servers. | G21: 2 | H21: NGINX - Reverse Proxy explained | I21: 'Computer Networking: A Top-Down Approach' Ch.2.2 (proxy/cache section) | J21: N/A | K21: N/A | L21: N/A | M21: What responsibilities should live in the proxy vs the application? | How does reverse-proxy caching reduce backend load? | N21: General pattern underlying NGINX/Envoy/HAProxy. | P21: 0 | Q21: =IF(OR(O21="",P21=0),"",O21+CHOOSE(P21,1,3,7,14,30,90,365))
A22: Not Started | B22: Anycast | C22: Same IP, multiple locations, BGP-based routing | D22: Expert | E22: Routing, CDNs | F22: Understand how anycast routes users to their nearest instance of a service. | G22: 2 | H22: Cloudflare - How Anycast works (blog-adjacent talk) | I22: Cloudflare Learning Center - What Is Anycast | J22: cloudflare.com/learning/cdn/glossary/anycast-network/ | K22: N/A | L22: N/A | M22: How does anycast use BGP to route to the 'nearest' server? | What happens during anycast failover? | N22: This is how most global CDNs and DNS resolvers (e.g. 1.1.1.1) work. | P22: 0 | Q22: =IF(OR(O22="",P22=0),"",O22+CHOOSE(P22,1,3,7,14,30,90,365))
A23: RPC, gRPC & CDNs
A24: Not Started | B24: gRPC | C24: Protobuf, HTTP/2 transport, streaming RPC | D24: Advanced | E24: HTTP/2, RPC concepts | F24: Build and reason about gRPC's four call types (unary, server/client/bidi streaming). | G24: 4 | H24: gRPC official crash course (YouTube) | I24: grpc.io official documentation - core concepts | J24: grpc.io/docs/what-is-grpc/core-concepts/ | K24: Build a bidirectional-streaming gRPC service for token streaming | L24: Convert a FastAPI REST endpoint to an equivalent gRPC service | M24: Why is gRPC often faster than REST/JSON for internal services? | When would bidirectional streaming beat a unary call for LLM token streaming? | N24: Directly relevant to low-latency internal microservice communication. | P24: 0 | Q24: =IF(OR(O24="",P24=0),"",O24+CHOOSE(P24,1,3,7,14,30,90,365))
A25: Not Started | B25: RPC | C25: Remote procedure call semantics, idempotency | D25: Advanced | E25: Networking fundamentals | F25: Understand the guarantees (or lack thereof) RPC frameworks provide on failure. | G25: 2 | H25: MIT 6.824 - RPC lecture | I25: 'Distributed Systems' (van Steen & Tanenbaum) Ch.4, free PDF | J25: N/A | K25: N/A | L25: N/A | M25: What does 'at-most-once' vs 'at-least-once' RPC semantics mean? | Why must RPC handlers often be designed idempotent? | N25: This exact idempotency question resurfaces in distributed systems / Kafka contexts. | P25: 0 | Q25: =IF(OR(O25="",P25=0),"",O25+CHOOSE(P25,1,3,7,14,30,90,365))
A26: Not Started | B26: CDNs | C26: Edge caching, cache invalidation, origin shielding | D26: Advanced | E26: Anycast, Reverse Proxy | F26: Understand how CDNs reduce latency and origin load via edge caching. | G26: 3 | H26: Cloudflare - How a CDN works (official explainer) | I26: Cloudflare Learning Center - What is a CDN | J26: cloudflare.com/learning/cdn/what-is-a-cdn/ | K26: N/A | L26: N/A | M26: How does cache invalidation work across thousands of edge nodes? | What is origin shielding protecting against? | N26: Relevant if you ever serve model weights or static assets globally. | P26: 0 | Q26: =IF(OR(O26="",P26=0),"",O26+CHOOSE(P26,1,3,7,14,30,90,365))
A27: Not Started | B27: Packet Capture | C27: tcpdump filters & capture strategy | D27: Advanced | E27: TCP/UDP | F27: Capture and filter live network traffic for debugging. | G27: 2 | H27: Chris Greer - tcpdump crash course | I27: man7.org/linux/man-pages/man8/tcpdump.8.html | J27: tcpdump.org | K27: Capture and filter only SYN packets on a given port with tcpdump | L27: N/A | M27: How do you filter tcpdump captures to a specific host/port? | Why capture at multiple points (client, LB, server) when debugging? | N27: First tool to reach for on 'why is this connection slow/dropping'. | P27: 0 | Q27: =IF(OR(O27="",P27=0),"",O27+CHOOSE(P27,1,3,7,14,30,90,365))
A28: Not Started | B28: Wireshark | C28: Protocol dissection & following TCP streams | D28: Advanced | E28: Packet Capture | F28: Use Wireshark's GUI to dissect protocols and follow full conversations. | G28: 2 | H28: Chris Greer - Wireshark tutorials | I28: Wireshark official user guide | J28: wireshark.org/docs/wsug_html_chunked/ | K28: Capture and 'Follow TCP Stream' on an HTTP request in Wireshark | L28: N/A | M28: How do you use Wireshark's 'Follow Stream' to reconstruct an HTTP conversation? | What's the difference between a display filter and a capture filter? | N28: Great for visually debugging the same captures tcpdump takes. | P28: 0 | Q28: =IF(OR(O28="",P28=0),"",O28+CHOOSE(P28,1,3,7,14,30,90,365))
A29: Not Started | B29: WireGuard | C29: Modern VPN protocol design | D29: Advanced | E29: TLS, Cryptography basics | F29: Understand why WireGuard's minimal design outperforms IPsec/OpenVPN. | G29: 2 | H29: WireGuard official technical whitepaper talk | I29: wireguard.com/papers/wireguard.pdf (official whitepaper) | J29: wireguard.com | K29: Set up a WireGuard tunnel between two hosts | L29: N/A | M29: Why is WireGuard's codebase so much smaller than IPsec's? | What cryptographic primitives does WireGuard use (Noise protocol)? | N29: Good to know for securing internal cluster/service-to-service traffic. | P29: 0 | Q29: =IF(OR(O29="",P29=0),"",O29+CHOOSE(P29,1,3,7,14,30,90,365))

Sheet Databases
A1: Databases
A2: PostgreSQL internals, analytical/vector stores, and distributed data concerns.
A3: Sheet Progress — 17 topics total | Q3: =ROUND(COUNTIF(A5:A24,"Completed")/SUMPRODUCT(COUNTIF(A5:A24,{"Completed","In Progress","Not Started","Research","Project","Optional"}))*100,0) -> 0
A4: Status | B4: Topic | C4: Subtopic | D4: Difficulty | E4: Prerequisites | F4: Learning Goal | G4: Est. Hours | H4: Best YouTube Resource | I4: Best Reading | J4: Official Documentation | K4: Coding Exercise | L4: Mini Project | M4: Interview Questions | N4: Notes | O4: Date Completed | P4: Revision Stage | Q4: Revision Date
A5: PostgreSQL Internals
A6: Not Started | B6: PostgreSQL Internals | C6: Process model & shared buffers | D6: Advanced | E6: SQL fluency | F6: Understand PostgreSQL's process-per-connection architecture and shared memory. | G6: 3 | H6: CMU Database Group - Postgres Internals lecture (15-445) | I6: 'The Internals of PostgreSQL' (free online book by Hironobu Suzuki) | J6: postgresql.org/docs/current/overview.html | K6: Inspect pg_stat_activity while running concurrent queries | L6: N/A | M6: Why does Postgres use one process per connection instead of threads? | What lives in shared_buffers vs the OS page cache? | N6: 'The Internals of PostgreSQL' is the single best free deep-dive resource. | P6: 0 | Q6: =IF(OR(O6="",P6=0),"",O6+CHOOSE(P6,1,3,7,14,30,90,365))
A7: Not Started | B7: MVCC | C7: Multi-Version Concurrency Control & tuple versions | D7: Advanced | E7: PostgreSQL Internals | F7: Understand how Postgres allows readers and writers to avoid blocking each other. | G7: 4 | H7: CMU 15-445 - MVCC lecture | I7: 'The Internals of PostgreSQL' Ch.5 | J7: postgresql.org/docs/current/mvcc-intro.html | K7: Observe xmin/xmax tuple versioning with a manual transaction experiment | L7: N/A | M7: How does MVCC avoid read locks blocking writers? | What causes table bloat and how does VACUUM address it? | N7: MVCC is one of the most-asked 'explain how your database works' interview topics. | P7: 0 | Q7: =IF(OR(O7="",P7=0),"",O7+CHOOSE(P7,1,3,7,14,30,90,365))
A8: Not Started | B8: WAL | C8: Write-Ahead Log & crash recovery | D8: Advanced | E8: MVCC | F8: Understand how the WAL guarantees durability and enables replication. | G8: 3 | H8: CMU 15-445 - Logging & Recovery lecture | I8: 'The Internals of PostgreSQL' Ch.9 | J8: postgresql.org/docs/current/wal-intro.html | K8: Inspect WAL file growth while running write-heavy transactions | L8: N/A | M8: Why must the log be written before the data page (write-ahead)? | How does WAL enable streaming replication? | N8: WAL shipping is literally how Postgres replicas stay in sync. | P8: 0 | Q8: =IF(OR(O8="",P8=0),"",O8+CHOOSE(P8,1,3,7,14,30,90,365))
A9: Not Started | B9: Indexes | C9: B-Tree, Hash, GiST, GIN index types | D9: Advanced | E9: SQL fluency | F9: Choose the right Postgres index type for a given query pattern. | G9: 3 | H9: CMU 15-445 - Indexes lecture | I9: 'The Internals of PostgreSQL' Ch.7 | J9: postgresql.org/docs/current/indexes-types.html | K9: Compare query plans with and without an index using EXPLAIN ANALYZE | L9: N/A | M9: When would GIN beat a B-Tree index? | Why can an index sometimes make a query slower? | N9: EXPLAIN ANALYZE literacy is a hard requirement for this whole sheet. | P9: 0 | Q9: =IF(OR(O9="",P9=0),"",O9+CHOOSE(P9,1,3,7,14,30,90,365))
A10: Not Started | B10: B Trees | C10: Balanced tree structure & disk-page fit | D10: Advanced | E10: Indexes | F10: Understand why B-Trees (not binary trees) are the standard for disk-based indexes. | G10: 3 | H10: CMU 15-445 - Tree Indexes lecture | I10: 'Database Internals' Ch.2-4 (Petrov) selected chapters | J10: N/A | K10: Simulate a B-Tree split-on-insert in Python | L10: N/A | M10: Why do B-Trees use high fan-out instead of binary branching? | How does a B-Tree minimize disk seeks? | N10: The 'why not a binary tree' question is a classic filter question. | P10: 0 | Q10: =IF(OR(O10="",P10=0),"",O10+CHOOSE(P10,1,3,7,14,30,90,365))
A11: Not Started | B11: B+ Trees | C11: Leaf-linked B+Trees for range scans | D11: Advanced | E11: B Trees | F11: Understand how B+Trees optimize range queries via linked leaf nodes. | G11: 2 | H11: CMU 15-445 - B+Tree lecture | I11: 'Database Internals' Ch.4 | J11: N/A | K11: N/A | L11: N/A | M11: Why do B+Trees keep all data in leaves with linked pointers? | How does this specifically speed up range scans (BETWEEN queries)? | N11: This is the index structure Postgres actually uses by default. | P11: 0 | Q11: =IF(OR(O11="",P11=0),"",O11+CHOOSE(P11,1,3,7,14,30,90,365))
A12: Not Started | B12: LSM Trees | C12: Log-Structured Merge trees & compaction | D12: Advanced | E12: B Trees | F12: Understand the write-optimized alternative to B-Trees used by many modern stores. | G12: 4 | H12: CMU 15-445 - LSM Trees lecture | I12: 'Database Internals' Ch.7 | J12: N/A | K12: Compare write throughput of an LSM-based store vs Postgres for a write-heavy workload | L12: N/A | M12: Why do LSM trees favor writes while B-Trees favor reads? | What is compaction and why does it matter for read amplification? | N12: LSM trees underlie RocksDB, Cassandra, and ClickHouse's MergeTree. | P12: 0 | Q12: =IF(OR(O12="",P12=0),"",O12+CHOOSE(P12,1,3,7,14,30,90,365))
A13: Analytical & Vector Stores
A14: Not Started | B14: ClickHouse | C14: Columnar storage & vectorized query execution | D14: Advanced | E14: LSM Trees, SQL | F14: Understand how column-oriented storage accelerates analytical (OLAP) queries. | G14: 3 | H14: ClickHouse official - Columnar storage explained | I14: ClickHouse official documentation - architecture overview | J14: clickhouse.com/docs/en/development/architecture | K14: Load a dataset into ClickHouse and compare an aggregate query's speed vs Postgres | L14: N/A | M14: Why is column storage faster for aggregate queries but slower for row lookups? | What is vectorized query execution? | N14: Directly relevant to logging/analytics for ML training pipelines. | P14: 0 | Q14: =IF(OR(O14="",P14=0),"",O14+CHOOSE(P14,1,3,7,14,30,90,365))
A15: Not Started | B15: DuckDB | C15: In-process OLAP engine, columnar & vectorized | D15: Advanced | E15: ClickHouse concepts | F15: Understand DuckDB's 'SQLite for analytics' embedded-OLAP model. | G15: 2 | H15: DuckDB official - Why DuckDB talk (CIDR/VLDB) | I15: duckdb.org official documentation | J15: duckdb.org/docs/ | K15: Query a large local Parquet file directly with DuckDB, no server needed | L15: Build a local analytics notebook using DuckDB over your training logs | M15: Why is DuckDB well-suited to ad-hoc analysis of large local Parquet/CSV files? | How does DuckDB compare to Pandas for large datasets? | N15: Great, low-friction tool for exploring large experiment-log datasets. | P15: 0 | Q15: =IF(OR(O15="",P15=0),"",O15+CHOOSE(P15,1,3,7,14,30,90,365))
A16: Not Started | B16: Vector Databases | C16: ANN indexes: HNSW, IVF, product quantization | D16: Advanced | E16: Linear Algebra, Embeddings | F16: Understand the approximate-nearest-neighbor algorithms vector DBs are built on. | G16: 4 | H16: Pinecone - Vector Database 101 (official learning series) | I16: Pinecone Learning Center - HNSW explained | J16: pinecone.io/learn/series/faiss/hnsw/ | K16: Build an HNSW index with faiss and benchmark recall vs brute-force search | L16: Build a small RAG retrieval layer comparing HNSW vs IVF-PQ tradeoffs | M16: Why does HNSW trade some recall for massive speedups over brute force? | What does product quantization compress and at what cost? | N16: Directly relevant to your existing RAG work. | P16: 0 | Q16: =IF(OR(O16="",P16=0),"",O16+CHOOSE(P16,1,3,7,14,30,90,365))
A17: Not Started | B17: Query Optimizer | C17: Cost-based optimization & query plans | D17: Expert | E17: Indexes, B+ Trees | F17: Understand how a query planner chooses among possible execution strategies. | G17: 4 | H17: CMU 15-445 - Query Optimization lecture | I17: 'Database Internals' Ch.9 (Petrov) | J17: postgresql.org/docs/current/planner-optimizer.html | K17: Force different query plans with pg hints and compare EXPLAIN ANALYZE costs | L17: N/A | M17: How does a cost-based optimizer estimate row counts (selectivity)? | Why can outdated statistics cause a bad query plan? | N17: Reading EXPLAIN ANALYZE output fluently is a strong interview signal. | P17: 0 | Q17: =IF(OR(O17="",P17=0),"",O17+CHOOSE(P17,1,3,7,14,30,90,365))
A18: Transactions, Replication & Caching
A19: Not Started | B19: Transactions | C19: ACID guarantees & the transaction log | D19: Advanced | E19: MVCC, WAL | F19: Understand what each ACID guarantee actually protects against. | G19: 2 | H19: CMU 15-445 - Transactions lecture | I19: 'Designing Data-Intensive Applications' Ch.7 (Kleppmann) - widely available lecture notes | J19: postgresql.org/docs/current/tutorial-transactions.html | K19: Reproduce a lost-update anomaly without proper isolation | L19: N/A | M19: What specific anomaly does each isolation level prevent? | Why is 'atomicity' about all-or-nothing, not concurrency? | N19: Kleppmann's DDIA is widely considered the best conceptual resource here. | P19: 0 | Q19: =IF(OR(O19="",P19=0),"",O19+CHOOSE(P19,1,3,7,14,30,90,365))
A20: Not Started | B20: Isolation Levels | C20: Read Committed, Repeatable Read, Serializable | D20: Advanced | E20: Transactions | F20: Understand the concrete anomalies (dirty read, phantom read) each isolation level prevents. | G20: 3 | H20: CMU 15-445 - Isolation Levels lecture | I20: DDIA Ch.7.2 (Kleppmann) | J20: postgresql.org/docs/current/transaction-iso.html | K20: Reproduce a phantom read under Read Committed and fix it with Serializable | L20: N/A | M20: What's a phantom read and which isolation level prevents it? | Why does higher isolation cost more throughput? | N20: Postgres's default is Read Committed, not Serializable — a common surprise. | P20: 0 | Q20: =IF(OR(O20="",P20=0),"",O20+CHOOSE(P20,1,3,7,14,30,90,365))
A21: Not Started | B21: Replication | C21: Streaming replication, synchronous vs async | D21: Advanced | E21: WAL | F21: Understand the durability/latency tradeoff between sync and async replication. | G21: 3 | H21: CMU 15-445 - Replication lecture | I21: DDIA Ch.5 (Kleppmann) | J21: postgresql.org/docs/current/warm-standby.html | K21: Set up Postgres streaming replication between two local instances | L21: N/A | M21: What durability guarantee do you lose with async replication? | How does synchronous replication affect write latency? | N21: Directly relevant to designing HA data stores for production ML systems. | P21: 0 | Q21: =IF(OR(O21="",P21=0),"",O21+CHOOSE(P21,1,3,7,14,30,90,365))
A22: Not Started | B22: Sharding | C22: Horizontal partitioning strategies & shard keys | D22: Advanced | E22: Replication | F22: Choose shard keys that avoid hot spots and support your query patterns. | G22: 3 | H22: CMU 15-445 - Sharding/Partitioning lecture | I22: DDIA Ch.6 (Kleppmann) | J22: N/A | K22: Design a shard-key strategy for a hypothetical multi-tenant workload | L22: N/A | M22: What makes a shard key 'bad' (causing hot spots)? | How do you handle cross-shard joins/transactions? | N22: Common senior system-design question: 'how would you shard this table'. | P22: 0 | Q22: =IF(OR(O22="",P22=0),"",O22+CHOOSE(P22,1,3,7,14,30,90,365))
A23: Not Started | B23: Partitioning | C23: Range/list/hash table partitioning within one DB | D23: Advanced | E23: Sharding | F23: Understand single-node partitioning as distinct from cross-node sharding. | G23: 2 | H23: CMU 15-445 - Partitioning lecture | I23: postgresql.org official partitioning docs | J23: postgresql.org/docs/current/ddl-partitioning.html | K23: Partition a large table by date range in Postgres and compare query performance | L23: N/A | M23: When does partition pruning help query performance? | How is partitioning different from sharding? | N23: Partitioning is a single-node optimization; sharding is a distributed one — a common conflation to clear up. | P23: 0 | Q23: =IF(OR(O23="",P23=0),"",O23+CHOOSE(P23,1,3,7,14,30,90,365))
A24: Not Started | B24: Caching | C24: Cache-aside, write-through, TTL & invalidation | D24: Advanced | E24: Redis fundamentals | F24: Choose the right caching strategy and understand its consistency tradeoffs. | G24: 3 | H24: System Design Interview - Caching Strategies (conceptual talk) | I24: 'Designing Data-Intensive Applications' Ch.3 (cache-adjacent sections) | J24: redis.io/docs/manual/ | K24: Implement cache-aside with Redis in front of a slow DB query | L24: Add write-through caching with TTL-based invalidation to an existing API | M24: What's the tradeoff between cache-aside and write-through? | How do you avoid cache stampede on a popular key's expiry? | N24: Directly usable given your existing Redis experience. | P24: 0 | Q24: =IF(OR(O24="",P24=0),"",O24+CHOOSE(P24,1,3,7,14,30,90,365))

Sheet Mathematics
A1: Mathematics
A2: Linear algebra, probability/information theory, and optimization underlying ML theory and practice.
A3: Sheet Progress — 21 topics total | Q3: =ROUND(COUNTIF(A5:A28,"Completed")/SUMPRODUCT(COUNTIF(A5:A28,{"Completed","In Progress","Not Started","Research","Project","Optional"}))*100,0) -> 0
A4: Status | B4: Topic | C4: Subtopic | D4: Difficulty | E4: Prerequisites | F4: Learning Goal | G4: Est. Hours | H4: Best YouTube Resource | I4: Best Reading | J4: Official Documentation | K4: Coding Exercise | L4: Mini Project | M4: Interview Questions | N4: Notes | O4: Date Completed | P4: Revision Stage | Q4: Revision Date
A5: Linear Algebra
A6: Not Started | B6: Linear Algebra | C6: Vector spaces, basis, rank | D6: Advanced | E6: High-school algebra | F6: Build geometric intuition for vector spaces before the matrix-calculus content below. | G6: 3 | H6: 3Blue1Brown - Essence of Linear Algebra (full playlist) | I6: MIT 18.06 Linear Algebra (Gilbert Strang, free OCW) | J6: N/A | K6: Implement Gram-Schmidt orthogonalization from scratch in NumPy | L6: N/A | M6: What does the rank of a matrix tell you geometrically? | Why does a basis need to be linearly independent? | N6: 3Blue1Brown's playlist is the best geometric-intuition resource that exists for this topic. | P6: 0 | Q6: =IF(OR(O6="",P6=0),"",O6+CHOOSE(P6,1,3,7,14,30,90,365))
A7: Not Started | B7: Matrix Calculus | C7: Gradients of matrix/vector expressions | D7: Advanced | E7: Linear Algebra, Calculus | F7: Differentiate scalar functions of vectors/matrices — the backbone of backprop. | G7: 4 | H7: 3Blue1Brown adjacent - Matrix Calculus for Deep Learning (freeCodeCamp) | I7: 'The Matrix Calculus You Need for Deep Learning' (Parr & Howard, free paper) | J7: N/A | K7: Derive and verify the gradient of a linear layer (Wx+b) by hand and against autograd | L7: N/A | M7: How do you derive the gradient of a matrix-vector product w.r.t. the matrix? | Why does the chain rule generalize to Jacobians for vector functions? | N7: The Parr & Howard paper is written specifically for ML practitioners. | P7: 0 | Q7: =IF(OR(O7="",P7=0),"",O7+CHOOSE(P7,1,3,7,14,30,90,365))
A8: Not Started | B8: Eigenvalues | C8: Eigendecomposition & spectral theorem | D8: Advanced | E8: Linear Algebra | F8: Understand eigenvectors as directions a linear map only scales, not rotates. | G8: 3 | H8: 3Blue1Brown - Eigenvectors and Eigenvalues | I8: MIT 18.06 Lecture 21-22 (Strang, free OCW) | J8: N/A | K8: Compute eigenvalues/eigenvectors of a covariance matrix and verify with NumPy | L8: N/A | M8: Why are eigenvectors of a symmetric matrix always orthogonal? | What does a negative eigenvalue mean geometrically? | N8: Foundation for PCA and understanding Hessian curvature. | P8: 0 | Q8: =IF(OR(O8="",P8=0),"",O8+CHOOSE(P8,1,3,7,14,30,90,365))
A9: Not Started | B9: Eigenvectors | C9: Diagonalization & powers of a matrix | D9: Advanced | E9: Eigenvalues | F9: Use eigendecomposition to compute matrix powers and understand stability. | G9: 2 | H9: 3Blue1Brown - Eigenvectors follow-up | I9: MIT 18.06 Lecture 22 (Strang) | J9: N/A | K9: Compute A^100 via eigendecomposition instead of repeated multiplication | L9: N/A | M9: Why does diagonalization make computing A^n trivial? | What does it mean for a matrix to not be diagonalizable? | N9: Directly relevant to understanding RNN gradient explosion/vanishing via repeated matrix multiplication. | P9: 0 | Q9: =IF(OR(O9="",P9=0),"",O9+CHOOSE(P9,1,3,7,14,30,90,365))
A10: Not Started | B10: SVD | C10: Singular Value Decomposition & low-rank approximation | D10: Advanced | E10: Eigenvalues | F10: Understand SVD as the generalization of eigendecomposition to any matrix. | G10: 4 | H10: 3Blue1Brown adjacent - SVD Visualized (Steve Brunton, free) | I10: MIT 18.06 Lecture 29-30 (Strang, free OCW) | J10: N/A | K10: Compress an image using truncated SVD and measure quality vs rank | L10: Build a low-rank recommender system using SVD | M10: Why does truncating singular values give the best low-rank approximation (Eckart-Young theorem)? | How does SVD relate to PCA? | N10: SVD is the mathematical core of LoRA — directly relevant to LLM fine-tuning. | P10: 0 | Q10: =IF(OR(O10="",P10=0),"",O10+CHOOSE(P10,1,3,7,14,30,90,365))
A11: Not Started | B11: PCA | C11: Principal Component Analysis via covariance eigendecomposition | D11: Advanced | E11: SVD, Eigenvalues, Statistics | F11: Understand PCA as finding the directions of maximum variance in data. | G11: 3 | H11: StatQuest - PCA Step-by-Step | I11: 'Elements of Statistical Learning' Ch.14.5 (free PDF, Hastie/Tibshirani/Friedman) | J11: scikit-learn.org/stable/modules/decomposition.html#pca | K11: Implement PCA from scratch via eigendecomposition of the covariance matrix | L11: Visualize high-dimensional embeddings in 2D with PCA vs t-SNE | M11: Why does PCA maximize variance rather than minimize reconstruction error (they're equivalent, but why?) | How do you choose the number of components to keep? | N11: StatQuest's visual explanations are unusually good for building fast intuition. | P11: 0 | Q11: =IF(OR(O11="",P11=0),"",O11+CHOOSE(P11,1,3,7,14,30,90,365))
A12: Probability, Statistics & Information Theory
A13: Not Started | B13: Probability | C13: Random variables, joint/marginal/conditional distributions | D13: Advanced | E13: High-school math | F13: Build fluency manipulating joint, marginal, and conditional distributions. | G13: 3 | H13: Harvard Stat 110 - Joe Blitzstein (free full course) | I13: 'Introduction to Probability' (Blitzstein & Hwang, free companion) | J13: N/A | K13: Simulate and verify the law of total probability with Monte Carlo sampling | L13: N/A | M13: How does the law of total probability decompose a marginal? | What's the difference between independence and conditional independence? | N13: Stat 110 is widely regarded as the best free probability course available. | P13: 0 | Q13: =IF(OR(O13="",P13=0),"",O13+CHOOSE(P13,1,3,7,14,30,90,365))
A14: Not Started | B14: Bayes | C14: Bayes' theorem, priors, posteriors, conjugate priors | D14: Advanced | E14: Probability | F14: Reason correctly about updating beliefs given new evidence. | G14: 3 | H14: 3Blue1Brown - Bayes theorem visualized | I14: Harvard Stat 110 - Bayes lectures (Blitzstein) | J14: N/A | K14: Implement Bayesian updating for a Beta-Binomial conjugate pair | L14: N/A | M14: Why do conjugate priors make posterior updates closed-form? | What's the difference between a frequentist and Bayesian interpretation of probability? | N14: Directly underlies reward-model calibration discussions in RLHF. | P14: 0 | Q14: =IF(OR(O14="",P14=0),"",O14+CHOOSE(P14,1,3,7,14,30,90,365))
A15: Not Started | B15: Information Theory | C15: Entropy, cross-entropy, KL divergence | D15: Advanced | E15: Probability | F15: Understand entropy as a measure of uncertainty and how loss functions relate to it. | G15: 4 | H15: 3Blue1Brown - But what is entropy? (via Art of the Problem, widely referenced) | I15: 'Elements of Information Theory' Ch.2 (Cover & Thomas) - lecture-note equivalents free online | J15: N/A | K15: Compute entropy/cross-entropy/KL for two toy distributions and verify relationships | L15: N/A | M15: Why is cross-entropy loss equivalent to minimizing KL divergence to the true distribution? | Why is KL divergence not symmetric? | N15: This is the mathematical backbone of essentially every LLM training loss function. | P15: 0 | Q15: =IF(OR(O15="",P15=0),"",O15+CHOOSE(P15,1,3,7,14,30,90,365))
A16: Not Started | B16: Entropy | C16: Shannon entropy & its properties | D16: Advanced | E16: Information Theory | F16: Build intuition for entropy as expected 'surprise' / minimum encoding length. | G16: 2 | H16: Khan Academy adjacent - Information theory basics (Art of the Problem) | I16: 'Elements of Information Theory' Ch.2.1 (Cover & Thomas) | J16: N/A | K16: N/A | L16: N/A | M16: Why is entropy maximized by a uniform distribution? | What is entropy's connection to optimal compression (Shannon's source coding theorem)? | N16: Directly connects to why a well-calibrated model has lower predictive entropy. | P16: 0 | Q16: =IF(OR(O16="",P16=0),"",O16+CHOOSE(P16,1,3,7,14,30,90,365))
A17: Not Started | B17: Cross Entropy | C17: Cross-entropy as a loss function | D17: Advanced | E17: Entropy | F17: Understand why cross-entropy is the standard classification/LM loss. | G17: 2 | H17: StatQuest - Cross Entropy Clearly Explained | I17: 'Deep Learning' book Ch.5.5 (Goodfellow, Bengio, Courville - free online) | J17: pytorch.org/docs/stable/generated/torch.nn.CrossEntropyLoss.html | K17: Implement cross-entropy loss from scratch and verify against PyTorch's | L17: N/A | M17: Why is cross-entropy loss convex for logistic regression but not for deep nets? | How does label smoothing modify the cross-entropy target? | N17: The loss function every LLM pretraining run directly optimizes. | P17: 0 | Q17: =IF(OR(O17="",P17=0),"",O17+CHOOSE(P17,1,3,7,14,30,90,365))
A18: Not Started | B18: KL Divergence | C18: Forward vs reverse KL, mode-seeking vs mode-covering | D18: Advanced | E18: Cross Entropy | F18: Understand the asymmetry of KL divergence and its practical consequences. | G18: 3 | H18: StatQuest - KL Divergence Clearly Explained | I18: 'Pattern Recognition and ML' Ch.10.1 (Bishop, free PDF) | J18: N/A | K18: Visualize forward vs reverse KL fitting a unimodal Gaussian to a bimodal target | L18: N/A | M18: Why does reverse KL tend to be mode-seeking? | Where does KL divergence appear directly in the DPO/RLHF objective? | N18: The KL penalty term is central to both RLHF and DPO objectives. | P18: 0 | Q18: =IF(OR(O18="",P18=0),"",O18+CHOOSE(P18,1,3,7,14,30,90,365))
A19: Not Started | B19: Jensen Shannon | C19: Symmetric, bounded divergence measure | D19: Advanced | E19: KL Divergence | F19: Understand JS divergence as a symmetrized, smoothed alternative to KL. | G19: 2 | H19: StatQuest adjacent - Jensen-Shannon Divergence explained | I19: 'Elements of Information Theory' Ch.2 (Cover & Thomas, JSD extensions) | J19: N/A | K19: Compute JS divergence between two toy distributions and compare to KL | L19: N/A | M19: Why is JS divergence always finite while KL can be infinite? | Where does JSD show up in GAN training objectives? | N19: Originally famous from the GAN paper's theoretical analysis. | P19: 0 | Q19: =IF(OR(O19="",P19=0),"",O19+CHOOSE(P19,1,3,7,14,30,90,365))
A20: Not Started | B20: Statistics | C20: Hypothesis testing, confidence intervals, p-values | D20: Advanced | E20: Probability | F20: Correctly interpret statistical significance when evaluating model results. | G20: 3 | H20: StatQuest - Hypothesis Testing playlist | I20: Harvard Stat 110/111 (Blitzstein, free OCW-equivalent) | J20: N/A | K20: Run a proper significance test comparing two model variants' accuracy | L20: N/A | M20: Why does a p-value not tell you the probability the null hypothesis is true? | How do you correctly size a confidence interval for an eval metric? | N20: Directly relevant to correctly interpreting A/B eval results, not just believing a headline number. | P20: 0 | Q20: =IF(OR(O20="",P20=0),"",O20+CHOOSE(P20,1,3,7,14,30,90,365))
A21: Optimization & Automatic Differentiation
A22: Not Started | B22: Optimization | C22: Convexity, local vs global minima | D22: Advanced | E22: Calculus | F22: Understand what convexity guarantees (and why deep nets don't have it). | G22: 3 | H22: Stanford EE364A - Convex Optimization (Boyd, free full course) | I22: 'Convex Optimization' (Boyd & Vandenberghe, free PDF) | J22: N/A | K22: Visualize a non-convex loss landscape with multiple local minima in 2D | L22: N/A | M22: Why doesn't losing convexity guarantees stop deep nets from training well in practice? | What is a saddle point and why is it more common than local minima in high dimensions? | N22: Boyd's book/course is the canonical free resource for convex optimization. | P22: 0 | Q22: =IF(OR(O22="",P22=0),"",O22+CHOOSE(P22,1,3,7,14,30,90,365))
A23: Not Started | B23: Gradient Descent | C23: Batch, stochastic, mini-batch variants | D23: Advanced | E23: Optimization, Matrix Calculus | F23: Understand the bias-variance-speed tradeoffs across gradient descent variants. | G23: 2 | H23: 3Blue1Brown - Gradient Descent, how neural networks learn | I23: 'Deep Learning' book Ch.8.1-8.3 (Goodfellow et al, free) | J23: pytorch.org/docs/stable/optim.html | K23: Implement mini-batch SGD from scratch and compare convergence to full-batch GD | L23: N/A | M23: Why does mini-batch SGD often generalize better than full-batch gradient descent? | How does learning rate interact with batch size? | N23: Foundation before Adam and other adaptive optimizers below. | P23: 0 | Q23: =IF(OR(O23="",P23=0),"",O23+CHOOSE(P23,1,3,7,14,30,90,365))
A24: Not Started | B24: Adam | C24: Adaptive moment estimation, bias correction | D24: Advanced | E24: Gradient Descent | F24: Understand how Adam combines momentum and per-parameter adaptive learning rates. | G24: 3 | H24: Yannic Kilcher - Adam Optimizer paper walkthrough | I24: Original Adam paper (Kingma & Ba, arXiv, free) | J24: pytorch.org/docs/stable/generated/torch.optim.Adam.html | K24: Implement Adam from scratch and verify convergence matches PyTorch's Adam | L24: N/A | M24: What problem does Adam's bias-correction term solve in early training steps? | Why can Adam generalize worse than SGD+momentum on some tasks? | N24: AdamW (decoupled weight decay) is the actual default for most LLM pretraining. | P24: 0 | Q24: =IF(OR(O24="",P24=0),"",O24+CHOOSE(P24,1,3,7,14,30,90,365))
A25: Not Started | B25: Convex Optimization | C25: Duality, KKT conditions | D25: Expert | E25: Optimization | F25: Understand constrained optimization via Lagrangian duality. | G25: 4 | H25: Stanford EE364A - Duality lecture (Boyd, free) | I25: 'Convex Optimization' Ch.5 (Boyd & Vandenberghe, free PDF) | J25: N/A | K25: Solve a small constrained optimization problem using KKT conditions by hand | L25: N/A | M25: What do the KKT conditions generalize from unconstrained calculus? | Why does strong duality not always hold? | N25: More research-engineer-relevant than day-to-day LLM engineering, but common in advanced-role interviews. | P25: 0 | Q25: =IF(OR(O25="",P25=0),"",O25+CHOOSE(P25,1,3,7,14,30,90,365))
A26: Not Started | B26: Automatic Differentiation | C26: Forward mode vs reverse mode autodiff | D26: Expert | E26: Matrix Calculus | F26: Understand how autograd computes exact gradients via computational graphs. | G26: 4 | H26: MIT 18.S096 adjacent - Autodiff lecture (Alan Edelman, free) | I26: 'Automatic Differentiation in Machine Learning: a Survey' (Baydin et al, free arXiv paper) | J26: pytorch.org/docs/stable/notes/autograd.html | K26: Implement reverse-mode autodiff for a small scalar expression graph from scratch | L26: Build a minimal autograd engine (Karpathy's micrograd style) from scratch | M26: Why is reverse mode preferred for functions with many inputs and one output (like neural net loss)? | How does forward mode differ in when it's more efficient? | N26: Karpathy's 'micrograd' project is the single best hands-on way to internalize this. | P26: 0 | Q26: =IF(OR(O26="",P26=0),"",O26+CHOOSE(P26,1,3,7,14,30,90,365))
A27: Not Started | B27: Jacobians | C27: Jacobian matrices for vector-valued functions | D27: Advanced | E27: Matrix Calculus | F27: Generalize the gradient to vector-valued (not just scalar-valued) functions. | G27: 2 | H27: 3Blue1Brown adjacent - Jacobians for deep learning (Parr & Howard talk) | I27: 'The Matrix Calculus You Need for Deep Learning' Sec.4 (Parr & Howard) | J27: pytorch.org/docs/stable/generated/torch.autograd.functional.jacobian.html | K27: Compute the Jacobian of a small 2-layer MLP with torch.autograd.functional.jacobian | L27: N/A | M27: Why is the Jacobian needed (not just a gradient) for a vector-valued layer output? | How does the chain rule compose Jacobians across layers? | N27: This is literally what backprop computes and multiplies layer by layer. | P27: 0 | Q27: =IF(OR(O27="",P27=0),"",O27+CHOOSE(P27,1,3,7,14,30,90,365))
A28: Not Started | B28: Hessians | C28: Second-order curvature & Newton's method | D28: Expert | E28: Jacobians, Gradient Descent | F28: Understand second-order optimization and why it's rarely used directly at LLM scale. | G28: 3 | H28: Stanford EE364A adjacent - Newton's Method lecture (Boyd) | I28: 'Convex Optimization' Ch.9.5 (Boyd & Vandenberghe) | J28: N/A | K28: Compare Newton's method vs gradient descent convergence speed on a small convex problem | L28: N/A | M28: Why is computing/inverting the Hessian intractable at LLM parameter scale? | What do second-order approximations like K-FAC try to approximate cheaply? | N28: Explains why Adam (a first-order method with adaptive scaling) is the practical default. | P28: 0 | Q28: =IF(OR(O28="",P28=0),"",O28+CHOOSE(P28,1,3,7,14,30,90,365))

Sheet Machine Learning
A1: Machine Learning
A2: Learning theory, tree ensembles, and evaluation/interpretability beyond deep learning.
A3: Sheet Progress — 16 topics total | Q3: =ROUND(COUNTIF(A5:A23,"Completed")/SUMPRODUCT(COUNTIF(A5:A23,{"Completed","In Progress","Not Started","Research","Project","Optional"}))*100,0) -> 0
A4: Status | B4: Topic | C4: Subtopic | D4: Difficulty | E4: Prerequisites | F4: Learning Goal | G4: Est. Hours | H4: Best YouTube Resource | I4: Best Reading | J4: Official Documentation | K4: Coding Exercise | L4: Mini Project | M4: Interview Questions | N4: Notes | O4: Date Completed | P4: Revision Stage | Q4: Revision Date
A5: Learning Theory & Estimation
A6: Not Started | B6: Bias Variance | C6: Bias-variance decomposition of test error | D6: Advanced | E6: Statistics | F6: Decompose generalization error into bias, variance, and irreducible noise. | G6: 3 | H6: StatQuest - Bias and Variance Clearly Explained | I6: 'Elements of Statistical Learning' Ch.7.3 (free PDF, Hastie et al) | J6: scikit-learn.org/stable/modules/learning_curve.html | K6: Plot a learning curve showing bias-dominated vs variance-dominated regimes | L6: N/A | M6: Why can't you minimize bias and variance simultaneously without more data/capacity tradeoffs? | How does regularization shift the bias-variance tradeoff? | N6: Foundation for reasoning about under/overfitting rigorously instead of by vibes. | P6: 0 | Q6: =IF(OR(O6="",P6=0),"",O6+CHOOSE(P6,1,3,7,14,30,90,365))
A7: Not Started | B7: PAC Learning | C7: Probably Approximately Correct learning framework | D7: Expert | E7: Probability | F7: Understand the formal framework for what 'learnable with finite samples' means. | G7: 4 | H7: Caltech CS156 - Learning From Data (Abu-Mostafa, free full course) | I7: 'Understanding Machine Learning' Ch.2-3 (Shalev-Shwartz & Ben-David, free PDF) | J7: N/A | K7: N/A | L7: N/A | M7: What does 'probably approximately correct' formally guarantee? | How does sample complexity scale with hypothesis class size? | N7: Caltech's CS156 is the best free course for rigorous learning theory. | P7: 0 | Q7: =IF(OR(O7="",P7=0),"",O7+CHOOSE(P7,1,3,7,14,30,90,365))
A8: Not Started | B8: VC Dimension | C8: Vapnik-Chervonenkis dimension & model capacity | D8: Expert | E8: PAC Learning | F8: Measure a hypothesis class's capacity to shatter data points. | G8: 3 | H8: Caltech CS156 - VC Dimension lecture (Abu-Mostafa) | I8: 'Understanding Machine Learning' Ch.6 (Shalev-Shwartz & Ben-David, free PDF) | J8: N/A | K8: Compute the VC dimension of simple hypothesis classes (e.g. axis-aligned rectangles) | L8: N/A | M8: Why does VC dimension bound generalization error independent of the true distribution? | How does VC dimension relate to the number of parameters in a model? | N8: Classic theory question at research-focused labs; less common at pure product roles. | P8: 0 | Q8: =IF(OR(O8="",P8=0),"",O8+CHOOSE(P8,1,3,7,14,30,90,365))
A9: Not Started | B9: Maximum Likelihood | C9: MLE as the standard parameter-estimation principle | D9: Advanced | E9: Probability, Statistics | F9: Understand MLE as choosing parameters that make observed data most probable. | G9: 2 | H9: StatQuest - Maximum Likelihood Clearly Explained | I9: 'Deep Learning' book Ch.5.5 (Goodfellow et al, free) | J9: N/A | K9: Derive the MLE solution for a Gaussian's mean/variance by hand | L9: N/A | M9: Why is minimizing cross-entropy loss equivalent to maximizing likelihood under a categorical model? | When is MLE biased (e.g. variance estimation)? | N9: This is precisely the framing behind 'next-token prediction' pretraining objectives. | P9: 0 | Q9: =IF(OR(O9="",P9=0),"",O9+CHOOSE(P9,1,3,7,14,30,90,365))
A10: Not Started | B10: EM Algorithm | C10: Expectation-Maximization for latent variable models | D10: Expert | E10: Maximum Likelihood, Bayes | F10: Understand how EM iteratively estimates parameters when data has latent structure. | G10: 4 | H10: StatQuest - EM Algorithm Clearly Explained | I10: 'Pattern Recognition and ML' Ch.9 (Bishop, free PDF) | J10: N/A | K10: Implement EM for a Gaussian Mixture Model from scratch | L10: Fit a GMM to a real clustering dataset and compare to k-means | M10: Why is EM guaranteed to never decrease the likelihood at each step? | How does EM relate to k-means as a special case? | N10: Less used directly in LLM work but a recurring theoretical-foundations interview topic. | P10: 0 | Q10: =IF(OR(O10="",P10=0),"",O10+CHOOSE(P10,1,3,7,14,30,90,365))
A11: Tree-Based Models & Ensembles
A12: Not Started | B12: Decision Trees | C12: Splitting criteria: Gini, entropy, information gain | D12: Advanced | E12: Information Theory | F12: Understand how a decision tree greedily selects splits. | G12: 2 | H12: StatQuest - Decision Trees Clearly Explained | I12: 'Elements of Statistical Learning' Ch.9.2 (free PDF) | J12: scikit-learn.org/stable/modules/tree.html | K12: Implement a CART decision tree from scratch with Gini impurity splitting | L12: N/A | M12: Why does greedy splitting not guarantee a globally optimal tree? | What's the difference between Gini impurity and entropy as split criteria? | N12: StatQuest builds excellent intuition before touching the math formally. | P12: 0 | Q12: =IF(OR(O12="",P12=0),"",O12+CHOOSE(P12,1,3,7,14,30,90,365))
A13: Not Started | B13: Random Forest | C13: Bagging & feature subsampling for variance reduction | D13: Advanced | E13: Decision Trees | F13: Understand how bagging + random feature subsets reduce a tree ensemble's variance. | G13: 2 | H13: StatQuest - Random Forests Clearly Explained | I13: Breiman's original Random Forests paper (free, Machine Learning journal archive) | J13: scikit-learn.org/stable/modules/ensemble.html#forest | K13: Compare a single decision tree's variance to a random forest's on noisy data | L13: N/A | M13: Why does bagging reduce variance but not bias? | Why does Random Forest also randomize feature subsets, not just bootstrap samples? | N13: Good baseline model to reach for before defaulting to gradient boosting. | P13: 0 | Q13: =IF(OR(O13="",P13=0),"",O13+CHOOSE(P13,1,3,7,14,30,90,365))
A14: Not Started | B14: XGBoost Internals | C14: Gradient boosting, second-order Taylor approximation | D14: Expert | E14: Decision Trees, Matrix Calculus | F14: Understand how XGBoost fits trees to the gradient AND curvature of the loss. | G14: 4 | H14: StatQuest - Gradient Boost & XGBoost playlist | I14: Original XGBoost paper (Chen & Guestrin, free arXiv) | J14: xgboost.readthedocs.io/en/stable/tutorials/model.html | K14: Train XGBoost on a tabular dataset and inspect feature importances vs SHAP values | L14: Build an end-to-end tabular pipeline: feature engineering + XGBoost + calibration | M14: Why does XGBoost use a second-order (Newton-like) approximation instead of just gradients? | How does XGBoost's regularization term penalize tree complexity? | N14: Still the strongest baseline for most tabular data problems in industry. | P14: 0 | Q14: =IF(OR(O14="",P14=0),"",O14+CHOOSE(P14,1,3,7,14,30,90,365))
A15: Not Started | B15: LightGBM | C15: Leaf-wise growth & histogram-based splitting | D15: Advanced | E15: XGBoost Internals | F15: Understand LightGBM's speed advantages over XGBoost at scale. | G15: 2 | H15: LightGBM official talk/paper walkthrough | I15: Original LightGBM paper (Ke et al, free NeurIPS paper) | J15: lightgbm.readthedocs.io/en/latest/Features.html | K15: Benchmark LightGBM vs XGBoost training time on a large tabular dataset | L15: N/A | M15: Why does leaf-wise growth converge faster but risk overfitting more than level-wise? | How does histogram-based splitting speed up training? | N15: Preferred over XGBoost when training speed on large tabular data matters most. | P15: 0 | Q15: =IF(OR(O15="",P15=0),"",O15+CHOOSE(P15,1,3,7,14,30,90,365))
A16: Not Started | B16: CatBoost | C16: Ordered boosting & native categorical handling | D16: Advanced | E16: XGBoost Internals | F16: Understand how CatBoost avoids target leakage from naive categorical encoding. | G16: 2 | H16: CatBoost official - How CatBoost works (official talk) | I16: Original CatBoost paper (Prokhorenkova et al, free NeurIPS paper) | J16: catboost.ai/docs/concepts/algorithm-main-stages.html | K16: Compare CatBoost's native categorical handling to one-hot encoding + XGBoost | L16: N/A | M16: What is target leakage in naive categorical target-encoding and how does ordered boosting avoid it? | When would you reach for CatBoost over XGBoost? | N16: Best default when your tabular data has many high-cardinality categorical features. | P16: 0 | Q16: =IF(OR(O16="",P16=0),"",O16+CHOOSE(P16,1,3,7,14,30,90,365))
A17: Evaluation, Features & Interpretability
A18: Not Started | B18: Calibration | C18: Reliability diagrams, Platt scaling, temperature scaling | D18: Advanced | E18: Probability, Cross Entropy | F18: Ensure a model's predicted probabilities match real-world frequencies. | G18: 3 | H18: Google - Model Calibration explained (official ML crash course) | I18: 'On Calibration of Modern Neural Networks' (Guo et al, free arXiv) | J18: scikit-learn.org/stable/modules/calibration.html | K18: Plot a reliability diagram for an overconfident classifier and fix it with temperature scaling | L18: N/A | M18: Why do modern deep nets tend to be overconfident despite high accuracy? | How does temperature scaling recalibrate softmax outputs cheaply? | N18: Directly relevant to LLM confidence/uncertainty and reward-model calibration. | P18: 0 | Q18: =IF(OR(O18="",P18=0),"",O18+CHOOSE(P18,1,3,7,14,30,90,365))
A19: Not Started | B19: Metrics | C19: Precision/recall/F1, ROC-AUC, PR-AUC tradeoffs | D19: Advanced | E19: Statistics | F19: Choose the right metric for imbalanced or asymmetric-cost problems. | G19: 2 | H19: StatQuest - ROC and AUC Clearly Explained | I19: 'Elements of Statistical Learning' Ch.9.2.5 (free PDF) | J19: scikit-learn.org/stable/modules/model_evaluation.html | K19: Compute and compare ROC-AUC vs PR-AUC on a highly imbalanced dataset | L19: N/A | M19: Why is PR-AUC often more informative than ROC-AUC on imbalanced data? | What does an F1 score hide that precision and recall separately reveal? | N19: The 'why not just use accuracy' framing is a very common interview probe. | P19: 0 | Q19: =IF(OR(O19="",P19=0),"",O19+CHOOSE(P19,1,3,7,14,30,90,365))
A20: Not Started | B20: Feature Engineering | C20: Encoding, scaling, interaction features | D20: Advanced | E20: Statistics | F20: Systematically transform raw data into model-ready, informative features. | G20: 2 | H20: Kaggle Learn - Feature Engineering (free micro-course) | I20: 'Feature Engineering for Machine Learning' selected chapters (Zheng & Casari) | J20: scikit-learn.org/stable/modules/preprocessing.html | K20: Engineer interaction and time-based features for a tabular forecasting task | L20: N/A | M20: Why does target encoding risk leakage without proper cross-validation folds? | When does feature scaling matter vs not (tree models vs linear/NN)? | N20: Still highly relevant even in an LLM-centric role for any tabular/metadata side-systems. | P20: 0 | Q20: =IF(OR(O20="",P20=0),"",O20+CHOOSE(P20,1,3,7,14,30,90,365))
A21: Not Started | B21: Model Selection | C21: Cross-validation, nested CV, hyperparameter search | D21: Advanced | E21: Statistics | F21: Select models/hyperparameters without leaking test-set information. | G21: 2 | H21: StatQuest - Cross Validation Clearly Explained | I21: 'Elements of Statistical Learning' Ch.7.10 (free PDF) | J21: scikit-learn.org/stable/modules/cross_validation.html | K21: Implement nested cross-validation for unbiased hyperparameter selection | L21: N/A | M21: Why does using the same CV folds for both model selection and evaluation leak information? | What does nested CV fix? | N21: A common 'find the bug in this ML pipeline' interview scenario centers on this leakage. | P21: 0 | Q21: =IF(OR(O21="",P21=0),"",O21+CHOOSE(P21,1,3,7,14,30,90,365))
A22: Not Started | B22: Interpretability | C22: SHAP values & feature attribution | D22: Advanced | E22: Game theory basics (Shapley values) | F22: Attribute a model's prediction to individual input features rigorously. | G22: 3 | H22: StatQuest - SHAP Values Clearly Explained | I22: Original SHAP paper (Lundberg & Lee, free NeurIPS paper) | J22: shap.readthedocs.io/en/latest/ | K22: Compute SHAP values for an XGBoost model and compare to built-in feature importance | L22: N/A | M22: Why are SHAP values theoretically grounded (Shapley values from game theory) while default feature importance isn't? | What's a limitation of SHAP for highly correlated features? | N22: Directly useful whenever a stakeholder asks 'why did the model predict this'. | P22: 0 | Q22: =IF(OR(O22="",P22=0),"",O22+CHOOSE(P22,1,3,7,14,30,90,365))
A23: Not Started | B23: Explainability | C23: LIME, counterfactual explanations, saliency maps | D23: Advanced | E23: Interpretability | F23: Compare local surrogate-model explanation techniques to attribution methods. | G23: 2 | H23: StatQuest adjacent - LIME explained (official conference talk) | I23: Original LIME paper (Ribeiro et al, free arXiv) | J23: N/A | K23: Generate a LIME explanation for a single prediction and compare to SHAP for the same instance | L23: N/A | M23: How does LIME's local surrogate-model approach differ conceptually from SHAP's game-theoretic approach? | When do saliency maps mislead more than they inform? | N23: Good breadth topic; SHAP is more commonly used in production than LIME today. | P23: 0 | Q23: =IF(OR(O23="",P23=0),"",O23+CHOOSE(P23,1,3,7,14,30,90,365))

Sheet Deep Learning
A1: Deep Learning
A2: Backprop through modern Transformer architectures, normalization, and generative models.
A3: Sheet Progress — 16 topics total | Q3: =ROUND(COUNTIF(A5:A23,"Completed")/SUMPRODUCT(COUNTIF(A5:A23,{"Completed","In Progress","Not Started","Research","Project","Optional"}))*100,0) -> 0
A4: Status | B4: Topic | C4: Subtopic | D4: Difficulty | E4: Prerequisites | F4: Learning Goal | G4: Est. Hours | H4: Best YouTube Resource | I4: Best Reading | J4: Official Documentation | K4: Coding Exercise | L4: Mini Project | M4: Interview Questions | N4: Notes | O4: Date Completed | P4: Revision Stage | Q4: Revision Date
A5: Backpropagation & Core Architectures
A6: Not Started | B6: Backpropagation | C6: Chain rule applied through a computational graph | D6: Advanced | E6: Matrix Calculus, Automatic Differentiation | F6: Derive backprop from first principles, not just call .backward(). | G6: 4 | H6: Andrej Karpathy - Building micrograd (Neural Networks: Zero to Hero) | I6: 'Deep Learning' book Ch.6.5 (Goodfellow, Bengio, Courville, free online) | J6: pytorch.org/docs/stable/notes/autograd.html | K6: Implement backprop for a 2-layer MLP with pure NumPy, no autograd | L6: N/A | M6: Why does backprop reuse forward-pass activations instead of recomputing them? | What causes vanishing gradients in deep/recurrent nets? | N6: Karpathy's micrograd series is the definitive from-scratch resource. | P6: 0 | Q6: =IF(OR(O6="",P6=0),"",O6+CHOOSE(P6,1,3,7,14,30,90,365))
A7: Not Started | B7: Gradient Flow | C7: Vanishing/exploding gradients & mitigations | D7: Advanced | E7: Backpropagation | F7: Diagnose and fix unstable gradient magnitudes across deep networks. | G7: 3 | H7: Andrej Karpathy - Building makemore Part 3 (BatchNorm/gradient flow) | I7: 'Deep Learning' book Ch.8.2.5 (Goodfellow et al) | J7: pytorch.org/docs/stable/notes/autograd.html | K7: Plot gradient norms per layer for a deep MLP with/without normalization | L7: N/A | M7: Why does residual connection help gradient flow in very deep networks? | How does gradient clipping prevent exploding gradients? | N7: Directly explains why ResNets and Transformers both lean heavily on skip connections. | P7: 0 | Q7: =IF(OR(O7="",P7=0),"",O7+CHOOSE(P7,1,3,7,14,30,90,365))
A8: Not Started | B8: CNN | C8: Convolution, pooling, receptive fields | D8: Advanced | E8: Linear Algebra | F8: Understand convolutional layers as learned, spatially-shared filters. | G8: 3 | H8: Stanford CS231n - Convolutional Neural Networks lecture (free, Karpathy/Li) | I8: CS231n course notes (free, cs231n.github.io) | J8: pytorch.org/docs/stable/generated/torch.nn.Conv2d.html | K8: Implement a 2D convolution from scratch with NumPy and verify against PyTorch | L8: N/A | M8: How does weight sharing in convolutions reduce parameters vs a fully-connected layer? | How does receptive field grow with network depth? | N8: CS231n remains one of the best free deep learning courses ever produced. | P8: 0 | Q8: =IF(OR(O8="",P8=0),"",O8+CHOOSE(P8,1,3,7,14,30,90,365))
A9: Not Started | B9: Residual Networks | C9: Skip connections & identity mappings | D9: Advanced | E9: CNN, Gradient Flow | F9: Understand why residual connections enabled training much deeper networks. | G9: 2 | H9: Yannic Kilcher - ResNet paper walkthrough | I9: Original ResNet paper (He et al, free arXiv) | J9: pytorch.org/vision/stable/models.html#classification | K9: Train a plain deep CNN vs a ResNet of the same depth and compare convergence | L9: N/A | M9: Why does an identity skip connection make it easier to learn than an unreferenced mapping? | How do residual connections show up in Transformer blocks? | N9: The residual idea directly carries into every modern Transformer block. | P9: 0 | Q9: =IF(OR(O9="",P9=0),"",O9+CHOOSE(P9,1,3,7,14,30,90,365))
A10: Transformers & Attention
A11: Not Started | B11: Transformers | C11: Encoder-decoder architecture, full forward pass | D11: Advanced | E11: Backpropagation, Linear Algebra | F11: Trace a full Transformer forward pass end to end. | G11: 5 | H11: Andrej Karpathy - Let's build GPT from scratch | I11: 'The Illustrated Transformer' (Jay Alammar, free blog) | J11: pytorch.org/docs/stable/generated/torch.nn.Transformer.html | K11: Implement a minimal decoder-only Transformer (nanoGPT-style) from scratch | L11: Train a small character-level GPT on a toy dataset | M11: Why does the original Transformer use both self-attention and feed-forward sublayers? | What role do layer norm and residuals play at each sublayer? | N11: Karpathy's 'Let's build GPT' + Jay Alammar's illustrated posts are the definitive combo. | P11: 0 | Q11: =IF(OR(O11="",P11=0),"",O11+CHOOSE(P11,1,3,7,14,30,90,365))
A12: Not Started | B12: Attention | C12: Scaled dot-product attention & multi-head attention | D12: Advanced | E12: Matrix Calculus, Transformers | F12: Derive scaled dot-product attention and understand why scaling by sqrt(d_k) matters. | G12: 4 | H12: Andrej Karpathy - GPT from scratch (attention section) | I12: 'The Illustrated Transformer' (Jay Alammar, free blog) | J12: N/A | K12: Implement multi-head self-attention from scratch and match PyTorch's output | L12: N/A | M12: Why divide by sqrt(d_k) before the softmax in attention? | What does each attention head learn differently in practice? | N12: This single mechanism is the core building block of every modern LLM. | P12: 0 | Q12: =IF(OR(O12="",P12=0),"",O12+CHOOSE(P12,1,3,7,14,30,90,365))
A13: Not Started | B13: RoPE | C13: Rotary Positional Embeddings | D13: Expert | E13: Attention, Linear Algebra | F13: Understand how RoPE encodes relative position via rotation in embedding space. | G13: 4 | H13: Yannic Kilcher / EleutherAI adjacent - RoPE explained talk | I13: Original RoFormer paper (Su et al, free arXiv) | J13: N/A | K13: Implement RoPE from scratch and verify relative-position invariance | L13: N/A | M13: Why does RoPE naturally encode relative rather than absolute position? | Why does RoPE extrapolate to longer contexts better than learned absolute embeddings? | N13: The current default positional scheme in Llama, Mistral, Qwen, and most modern open LLMs. | P13: 0 | Q13: =IF(OR(O13="",P13=0),"",O13+CHOOSE(P13,1,3,7,14,30,90,365))
A14: Not Started | B14: ALiBi | C14: Attention with Linear Biases for length extrapolation | D14: Advanced | E14: Attention | F14: Understand ALiBi's simpler alternative to RoPE for length generalization. | G14: 2 | H14: Yannic Kilcher - ALiBi paper walkthrough | I14: Original ALiBi paper (Press et al, free arXiv) | J14: N/A | K14: Implement ALiBi's linear bias and compare extrapolation to a no-position baseline | L14: N/A | M14: How does ALiBi bias attention scores instead of modifying embeddings? | Why does ALiBi extrapolate well to unseen sequence lengths? | N14: Useful contrast case to RoPE for a 'compare positional encoding schemes' interview question. | P14: 0 | Q14: =IF(OR(O14="",P14=0),"",O14+CHOOSE(P14,1,3,7,14,30,90,365))
A15: Not Started | B15: SwiGLU | C15: Gated linear unit activation variant | D15: Advanced | E15: Backpropagation | F15: Understand why SwiGLU-style gated activations outperform plain ReLU/GELU FFNs in LLMs. | G15: 2 | H15: Yannic Kilcher adjacent - GLU Variants paper walkthrough | I15: 'GLU Variants Improve Transformer' paper (Shazeer, free arXiv) | J15: N/A | K15: Implement a SwiGLU feed-forward block and compare to a standard ReLU MLP block | L15: N/A | M15: What does the gating mechanism in SwiGLU add over a plain activation? | Why did Llama/PaLM adopt SwiGLU over ReLU/GELU? | N15: A small but consistently-used architectural detail across most modern LLMs. | P15: 0 | Q15: =IF(OR(O15="",P15=0),"",O15+CHOOSE(P15,1,3,7,14,30,90,365))
A16: Not Started | B16: FlashAttention | C16: IO-aware exact attention via tiling | D16: Expert | E16: Attention, CUDA basics | F16: Understand how FlashAttention avoids materializing the full attention matrix in HBM. | G16: 5 | H16: Tri Dao - FlashAttention paper talk (official) | I16: Original FlashAttention paper (Dao et al, free arXiv) | J16: github.com/Dao-AILab/flash-attention | K16: Read the FlashAttention CUDA kernel and annotate its tiling strategy | L16: N/A | M16: Why is FlashAttention exact (not an approximation) yet still faster? | How does tiling reduce HBM reads/writes specifically? | N16: One of the highest-leverage papers to deeply understand for an NVIDIA/inference-focused role. | P16: 0 | Q16: =IF(OR(O16="",P16=0),"",O16+CHOOSE(P16,1,3,7,14,30,90,365))
A17: Not Started | B17: MoE | C17: Mixture of Experts, sparse routing, load balancing | D17: Expert | E17: Transformers | F17: Understand how sparse expert routing scales parameter count without scaling compute proportionally. | G17: 4 | H17: Yannic Kilcher - Switch Transformer / MoE paper walkthrough | I17: 'Switch Transformers' paper (Fedus et al, free arXiv) | J17: N/A | K17: Implement a toy top-1 MoE router and observe expert load imbalance | L17: N/A | M17: Why is expert load-balancing loss necessary during MoE training? | What's the tradeoff MoE makes between parameter count and active compute per token? | N17: Directly relevant to Mixtral, DeepSeek-MoE, and Grok's architecture choices. | P17: 0 | Q17: =IF(OR(O17="",P17=0),"",O17+CHOOSE(P17,1,3,7,14,30,90,365))
A18: Normalization, Loss & Generative Models
A19: Not Started | B19: Normalization | C19: BatchNorm, LayerNorm, RMSNorm | D19: Advanced | E19: Gradient Flow | F19: Understand why and where each normalization variant is applied. | G19: 3 | H19: Andrej Karpathy - makemore Part 3 (BatchNorm deep-dive) | I19: Original LayerNorm paper (Ba et al, free arXiv) | J19: pytorch.org/docs/stable/generated/torch.nn.LayerNorm.html | K19: Implement LayerNorm and RMSNorm from scratch and compare stability during training | L19: N/A | M19: Why do Transformers use LayerNorm/RMSNorm instead of BatchNorm? | What compute does RMSNorm save over LayerNorm? | N19: RMSNorm is now the default in Llama-family models for its lower compute cost. | P19: 0 | Q19: =IF(OR(O19="",P19=0),"",O19+CHOOSE(P19,1,3,7,14,30,90,365))
A20: Not Started | B20: Loss Functions | C20: Cross-entropy, contrastive, and ranking losses | D20: Advanced | E20: Cross Entropy | F20: Match the loss function to the training objective (classification vs. representation learning vs. ranking). | G20: 3 | H20: Yannic Kilcher - Contrastive Loss / SimCLR paper walkthrough | I20: 'Deep Learning' book Ch.6.2 (Goodfellow et al, free) | J20: pytorch.org/docs/stable/nn.html#loss-functions | K20: Implement InfoNCE contrastive loss from scratch for a small embedding task | L20: N/A | M20: Why does contrastive loss need negative samples while cross-entropy doesn't? | How does temperature affect contrastive loss sharpness? | N20: InfoNCE-style losses underlie most modern embedding-model training (relevant to RAG). | P20: 0 | Q20: =IF(OR(O20="",P20=0),"",O20+CHOOSE(P20,1,3,7,14,30,90,365))
A21: Not Started | B21: Diffusion | C21: Forward/reverse diffusion, denoising score matching | D21: Expert | E21: Probability, Optimization | F21: Understand diffusion models as learning to reverse a gradual noising process. | G21: 5 | H21: Outlier / Yannic Kilcher - Diffusion Models explained from scratch | I21: 'Denoising Diffusion Probabilistic Models' paper (Ho et al, free arXiv) | J21: huggingface.co/docs/diffusers/en/index | K21: Implement a minimal DDPM on a toy 2D dataset and visualize the reverse process | L21: N/A | M21: Why is the reverse process trained to predict noise rather than the clean image directly? | How does the noise schedule affect sample quality/speed tradeoffs? | N21: Less central to text-only LLM roles but increasingly relevant to multimodal generative work. | P21: 0 | Q21: =IF(OR(O21="",P21=0),"",O21+CHOOSE(P21,1,3,7,14,30,90,365))
A22: Not Started | B22: Vision Transformers | C22: Patch embeddings & ViT architecture | D22: Advanced | E22: Transformers, CNN | F22: Understand how images are tokenized into patches for a standard Transformer. | G22: 3 | H22: Yannic Kilcher - ViT paper walkthrough (An Image is Worth 16x16 Words) | I22: Original ViT paper (Dosovitskiy et al, free arXiv) | J22: pytorch.org/vision/stable/models.html#classification | K22: Implement patch embedding + a small ViT and train on a toy image dataset | L22: N/A | M22: Why do ViTs need far more data than CNNs to match performance (lack of inductive bias)? | How is a 2D image patch flattened into a Transformer token? | N22: The architectural bridge between CNN-era vision and today's multimodal LLMs. | P22: 0 | Q22: =IF(OR(O22="",P22=0),"",O22+CHOOSE(P22,1,3,7,14,30,90,365))
A23: Not Started | B23: Multimodal Models | C23: Vision-language fusion: cross-attention vs. shared embedding space | D23: Expert | E23: Vision Transformers, Attention | F23: Understand the main architectural strategies for fusing text and image modalities. | G23: 4 | H23: Yannic Kilcher - CLIP paper walkthrough | I23: Original CLIP paper (Radford et al, free arXiv) | J23: huggingface.co/docs/transformers/en/model_doc/clip | K23: Use a pretrained CLIP model to compute image-text similarity for a small dataset | L23: Build a simple image-text retrieval demo using CLIP embeddings | M23: How does CLIP's contrastive pretraining align image and text embeddings without paired labels? | What's the difference between early fusion (cross-attention) and late fusion (shared embedding space)? | N23: CLIP-style contrastive pretraining underlies most modern multimodal LLM vision encoders. | P23: 0 | Q23: =IF(OR(O23="",P23=0),"",O23+CHOOSE(P23,1,3,7,14,30,90,365))

Sheet LLM Engineering
A1: LLM Engineering
A2: Tokenization through inference serving — the highest-priority sheet for your target roles.
A3: Sheet Progress — 29 topics total | Q3: =ROUND(COUNTIF(A5:A37,"Completed")/SUMPRODUCT(COUNTIF(A5:A37,{"Completed","In Progress","Not Started","Research","Project","Optional"}))*100,0) -> 0
A4: Status | B4: Topic | C4: Subtopic | D4: Difficulty | E4: Prerequisites | F4: Learning Goal | G4: Est. Hours | H4: Best YouTube Resource | I4: Best Reading | J4: Official Documentation | K4: Coding Exercise | L4: Mini Project | M4: Interview Questions | N4: Notes | O4: Date Completed | P4: Revision Stage | Q4: Revision Date
A5: Tokenization
A6: Not Started | B6: Tokenizers | C6: Subword tokenization overview & vocabulary tradeoffs | D6: Advanced | E6: Deep Learning fundamentals | F6: Understand why subword tokenization balances vocabulary size against sequence length. | G6: 2 | H6: Andrej Karpathy - Let's build the GPT Tokenizer | I6: Hugging Face NLP Course - Tokenizers chapter (free) | J6: huggingface.co/docs/transformers/en/tokenizer_summary | K6: Compare token counts for the same text across GPT/Llama/Claude-style tokenizers | L6: N/A | M6: Why not just tokenize at the word or character level? | How does vocabulary size affect embedding table size vs sequence length? | N6: Karpathy's tokenizer video is the single best from-scratch walkthrough available. | P6: 0 | Q6: =IF(OR(O6="",P6=0),"",O6+CHOOSE(P6,1,3,7,14,30,90,365))
A7: Not Started | B7: BPE | C7: Byte-Pair Encoding merge algorithm | D7: Advanced | E7: Tokenizers | F7: Implement the BPE merge algorithm that builds a subword vocabulary from raw text. | G7: 3 | H7: Andrej Karpathy - Let's build the GPT Tokenizer (BPE section) | I7: Hugging Face NLP Course - Byte-Pair Encoding tokenization (free) | J7: huggingface.co/docs/transformers/en/tokenizer_summary#bytepair-encoding-bpe | K7: Implement byte-level BPE from scratch on a small corpus (minbpe-style) | L7: Train a custom BPE tokenizer on domain-specific text and compare compression ratio | M7: Why does GPT-2 use byte-level BPE instead of Unicode-character-level BPE? | How do merge rules get applied at inference/encoding time? | N7: This is exactly what Karpathy's minbpe repo implements end to end. | P7: 0 | Q7: =IF(OR(O7="",P7=0),"",O7+CHOOSE(P7,1,3,7,14,30,90,365))
A8: Not Started | B8: SentencePiece | C8: Language-agnostic tokenization without pre-tokenization | D8: Advanced | E8: BPE | F8: Understand SentencePiece's whitespace-as-symbol approach for language-agnostic tokenization. | G8: 2 | H8: Hugging Face - SentencePiece explainer (official course video) | I8: SentencePiece official documentation/paper (Kudo & Richardson, free) | J8: github.com/google/sentencepiece | K8: Train a SentencePiece unigram-model tokenizer on a small multilingual corpus | L8: N/A | M8: Why does SentencePiece treat whitespace as a regular symbol? | What's the difference between SentencePiece's BPE and unigram modes? | N8: Used by Llama, T5, and many multilingual models specifically for language-agnostic handling. | P8: 0 | Q8: =IF(OR(O8="",P8=0),"",O8+CHOOSE(P8,1,3,7,14,30,90,365))
A9: Not Started | B9: WordPiece | C9: Likelihood-based subword merging (BERT's tokenizer) | D9: Advanced | E9: BPE | F9: Understand how WordPiece's merge criterion differs from BPE's frequency-based merges. | G9: 2 | H9: Hugging Face - WordPiece explainer (official course video) | I9: Hugging Face NLP Course - WordPiece tokenization (free) | J9: huggingface.co/docs/transformers/en/tokenizer_summary#wordpiece | K9: Compare a word's BPE vs WordPiece tokenization side by side | L9: N/A | M9: How does WordPiece's likelihood-based merge score differ from BPE's raw frequency count? | Why does BERT specifically use WordPiece? | N9: Mostly relevant for understanding legacy encoder models like BERT. | P9: 0 | Q9: =IF(OR(O9="",P9=0),"",O9+CHOOSE(P9,1,3,7,14,30,90,365))
A10: Transformer Internals & Inference Optimization
A11: Not Started | B11: Transformer Internals | C11: KV Cache mechanics & memory growth | D11: Advanced | E11: Attention | F11: Understand why caching keys/values avoids recomputing attention for past tokens. | G11: 3 | H11: Andrej Karpathy - GPT from scratch (inference/KV cache adjacent) | I11: Hugging Face - 'A Guide to Efficient LLM Inference' blog (free) | J11: huggingface.co/docs/transformers/en/llm_tutorial_optimization | K11: Implement KV caching in a minimal decoder and measure the generation speedup | L11: N/A | M11: Why does KV cache memory grow linearly with sequence length AND batch size? | How does KV cache size relate to the number of layers and heads? | N11: KV cache size is the primary memory bottleneck for long-context serving. | P11: 0 | Q11: =IF(OR(O11="",P11=0),"",O11+CHOOSE(P11,1,3,7,14,30,90,365))
A12: Not Started | B12: PagedAttention | C12: Virtual-memory-style paging for the KV cache | D12: Expert | E12: Transformer Internals, OS Virtual Memory | F12: Understand how vLLM applies OS paging concepts to eliminate KV cache fragmentation. | G12: 4 | H12: vLLM team - PagedAttention paper talk (official) | I12: Original vLLM/PagedAttention paper (Kwon et al, free arXiv) | J12: docs.vllm.ai/en/latest/design/paged_attention.html | K12: Read vLLM's PagedAttention kernel source and map it to your OS paging knowledge | L12: N/A | M12: How does PagedAttention borrow directly from OS virtual memory paging? | Why does non-contiguous KV cache storage reduce memory waste? | N12: This is the single biggest inference-serving innovation of the last few years — study it deeply. | P12: 0 | Q12: =IF(OR(O12="",P12=0),"",O12+CHOOSE(P12,1,3,7,14,30,90,365))
A13: Not Started | B13: Continuous Batching | C13: Iteration-level scheduling for dynamic batch composition | D13: Expert | E13: PagedAttention | F13: Understand how continuous batching keeps GPU utilization high with variable-length requests. | G13: 3 | H13: vLLM/Anyscale - Continuous Batching explained (official blog talk) | I13: Anyscale - 'How continuous batching enables 23x throughput' (free blog) | J13: docs.vllm.ai/en/latest/ | K13: Simulate static vs continuous batching throughput on a synthetic request stream | L13: N/A | M13: Why does static batching waste GPU cycles on short-finished sequences? | How does continuous batching decide when to admit a new request mid-batch? | N13: Directly explains the throughput gap between naive and production-grade serving stacks. | P13: 0 | Q13: =IF(OR(O13="",P13=0),"",O13+CHOOSE(P13,1,3,7,14,30,90,365))
A14: Not Started | B14: Speculative Decoding | C14: Draft-model verification for faster autoregressive generation | D14: Expert | E14: Transformer Internals | F14: Understand how a small draft model speeds up generation from a larger target model. | G14: 4 | H14: Yannic Kilcher - Speculative Decoding paper walkthrough | I14: 'Fast Inference from Transformers via Speculative Decoding' (Leviathan et al, free arXiv) | J14: huggingface.co/docs/transformers/en/llm_tutorial_optimization#speculative-decoding | K14: Implement a toy speculative decoding loop with a small/large model pair | L14: N/A | M14: Why does speculative decoding preserve the exact output distribution of the target model? | What determines the achievable speedup (draft model acceptance rate)? | N14: A major lever for reducing latency without changing the served model's quality. | P14: 0 | Q14: =IF(OR(O14="",P14=0),"",O14+CHOOSE(P14,1,3,7,14,30,90,365))
A15: Not Started | B15: Quantization | C15: INT8/INT4 quantization, GPTQ, AWQ | D15: Expert | E15: Linear Algebra, Numerical precision | F15: Understand how reducing weight precision trades a small quality cost for large memory/speed wins. | G15: 4 | H15: Hugging Face - Quantization explained (official course video) | I15: 'GPTQ' paper (Frantar et al, free arXiv) and 'AWQ' paper (Lin et al, free arXiv) | J15: huggingface.co/docs/transformers/en/quantization/overview | K15: Quantize an open model to INT4 with a library like AutoGPTQ and measure quality/speed tradeoff | L15: N/A | M15: Why does AWQ protect a small subset of 'salient' weights at higher precision? | How does GPTQ use layer-wise error compensation during quantization? | N15: Directly determines what hardware footprint a model can be served on. | P15: 0 | Q15: =IF(OR(O15="",P15=0),"",O15+CHOOSE(P15,1,3,7,14,30,90,365))
A16: Fine-Tuning & Alignment
A17: Not Started | B17: LoRA | C17: Low-Rank Adaptation of pretrained weights | D17: Advanced | E17: SVD, Linear Algebra | F17: Understand how LoRA freezes base weights and learns a low-rank update instead. | G17: 3 | H17: Hugging Face - LoRA explained (official PEFT course video) | I17: Original LoRA paper (Hu et al, free arXiv) | J17: huggingface.co/docs/peft/en/conceptual_guides/lora | K17: Fine-tune a small open model with LoRA on a custom dataset using PEFT | L17: N/A | M17: Why does a low-rank update matter memory-wise vs full fine-tuning? | How do you choose the LoRA rank (r) and which layers to adapt? | N17: The SVD topic in the Mathematics sheet is the direct mathematical foundation here. | P17: 0 | Q17: =IF(OR(O17="",P17=0),"",O17+CHOOSE(P17,1,3,7,14,30,90,365))
A18: Not Started | B18: QLoRA | C18: 4-bit quantized base model + LoRA adapters | D18: Expert | E18: LoRA, Quantization | F18: Understand how QLoRA combines quantization and LoRA to fine-tune huge models on limited hardware. | G18: 3 | H18: Hugging Face - QLoRA explained (official course video) | I18: Original QLoRA paper (Dettmers et al, free arXiv) | J18: huggingface.co/docs/peft/en/developer_guides/quantization | K18: Fine-tune a 7B+ parameter model with QLoRA on a single consumer GPU | L18: N/A | M18: What does QLoRA's 4-bit NormalFloat (NF4) data type optimize for vs standard INT4? | How does paged optimizer state avoid OOM during QLoRA training? | N18: This is what made fine-tuning large open models accessible outside big labs. | P18: 0 | Q18: =IF(OR(O18="",P18=0),"",O18+CHOOSE(P18,1,3,7,14,30,90,365))
A19: Not Started | B19: PEFT | C19: Parameter-Efficient Fine-Tuning landscape (LoRA, prefix-tuning, adapters) | D19: Advanced | E19: LoRA | F19: Compare the major PEFT strategies and when to choose each. | G19: 3 | H19: Hugging Face - PEFT methods overview (official course video) | I19: Hugging Face PEFT documentation - conceptual guides | J19: huggingface.co/docs/peft/en/index | K19: Fine-tune the same task with LoRA vs prefix-tuning and compare parameter count/quality | L19: N/A | M19: When would prefix-tuning be preferred over LoRA? | Why do PEFT methods generally reduce catastrophic forgetting vs full fine-tuning? | N19: Good breadth topic showing you know the full toolbox, not just LoRA. | P19: 0 | Q19: =IF(OR(O19="",P19=0),"",O19+CHOOSE(P19,1,3,7,14,30,90,365))
A20: Not Started | B20: SFT | C20: Supervised Fine-Tuning on instruction data | D20: Advanced | E20: Cross Entropy, Transformers | F20: Understand how SFT adapts a pretrained base model to follow instructions. | G20: 3 | H20: Hugging Face - SFT explained (official TRL course video) | I20: Hugging Face TRL documentation - SFTTrainer guide (free) | J20: huggingface.co/docs/trl/en/sft_trainer | K20: Run SFT on an open base model using Hugging Face's TRL library | L20: Build an end-to-end SFT pipeline: data curation, training, eval | M20: Why does SFT data quality matter more than quantity beyond a certain point? | How is the loss masked so only completion tokens (not prompt tokens) are trained on? | N20: The first stage of essentially every modern post-training pipeline. | P20: 0 | Q20: =IF(OR(O20="",P20=0),"",O20+CHOOSE(P20,1,3,7,14,30,90,365))
A21: Not Started | B21: RLHF | C21: Reinforcement Learning from Human Feedback pipeline | D21: Expert | E21: SFT, Reward Models | F21: Understand the 3-stage RLHF pipeline: SFT, reward modeling, RL optimization (PPO). | G21: 5 | H21: Hugging Face - RLHF explained (official course video) | I21: 'Training language models to follow instructions with human feedback' (InstructGPT paper, Ouyang et al, free arXiv) | J21: huggingface.co/docs/trl/en/ppo_trainer | K21: Walk through Hugging Face TRL's PPO trainer on a toy reward function | L21: N/A | M21: Why is a KL penalty against the SFT policy included in the RLHF objective? | What makes PPO more stable than naive policy gradient for this setting? | N21: The InstructGPT paper is essential, foundational reading for this whole section. | P21: 0 | Q21: =IF(OR(O21="",P21=0),"",O21+CHOOSE(P21,1,3,7,14,30,90,365))
A22: Not Started | B22: DPO | C22: Direct Preference Optimization (RL-free alignment) | D22: Expert | E22: RLHF, KL Divergence | F22: Understand how DPO reformulates RLHF's objective as a simple classification loss. | G22: 4 | H22: Yannic Kilcher - DPO paper walkthrough | I22: Original DPO paper (Rafailov et al, free arXiv) | J22: huggingface.co/docs/trl/en/dpo_trainer | K22: Fine-tune a model with DPO on a preference dataset using Hugging Face TRL | L22: Compare SFT-only vs SFT+DPO outputs on a held-out eval set | M22: How does DPO avoid training an explicit reward model at all? | Why is DPO more stable to train than PPO-based RLHF in practice? | N22: DPO's simplicity has made it the default choice for many open-source alignment pipelines. | P22: 0 | Q22: =IF(OR(O22="",P22=0),"",O22+CHOOSE(P22,1,3,7,14,30,90,365))
A23: Not Started | B23: GRPO | C23: Group Relative Policy Optimization | D23: Expert | E23: DPO, RLHF | F23: Understand GRPO's critic-free approach to RL fine-tuning popularized by DeepSeek. | G23: 4 | H23: Yannic Kilcher / community - GRPO & DeepSeekMath paper walkthrough | I23: 'DeepSeekMath' paper, GRPO section (Shao et al, free arXiv) | J23: huggingface.co/docs/trl/en/grpo_trainer | K23: Read TRL's GRPOTrainer source and compare its loss to PPO's | L23: N/A | M23: Why does GRPO avoid training a separate value/critic network? | How does group-relative advantage estimation replace a learned baseline? | N23: Directly relevant to recent reasoning-model training pipelines (DeepSeek-R1 style). | P23: 0 | Q23: =IF(OR(O23="",P23=0),"",O23+CHOOSE(P23,1,3,7,14,30,90,365))
A24: Not Started | B24: Reward Models | C24: Bradley-Terry preference modeling | D24: Advanced | E24: Bayes, Cross Entropy | F24: Understand how pairwise human preferences are converted into a scalar reward signal. | G24: 3 | H24: Hugging Face - Reward Modeling explained (official course video) | I24: InstructGPT paper, reward-model section (Ouyang et al, free arXiv) | J24: huggingface.co/docs/trl/en/reward_trainer | K24: Train a reward model on a preference dataset and inspect its score distribution | L24: N/A | M24: Why is the Bradley-Terry model a natural fit for pairwise preference data? | What causes reward-model overoptimization (reward hacking) during downstream RL? | N24: Reward hacking is a top-tier alignment interview discussion topic. | P24: 0 | Q24: =IF(OR(O24="",P24=0),"",O24+CHOOSE(P24,1,3,7,14,30,90,365))
A25: Prompting, Evaluation & Serving
A26: Not Started | B26: Prompt Optimization | C26: Few-shot design, chain-of-thought, structured output | D26: Advanced | E26: LLM API fluency | F26: Systematically improve prompt quality rather than relying on trial and error. | G26: 2 | H26: DeepLearning.AI - Prompt Engineering for Developers (free short course) | I26: 'Prompt Engineering Guide' (promptingguide.ai, free) | J26: platform.openai.com/docs/guides/prompt-engineering | K26: A/B test 3 prompting strategies on the same task and measure eval-score deltas | L26: N/A | M26: Why does chain-of-thought prompting help more on some task types than others? | How do you make LLM output reliably parseable (structured output / function-calling schemas)? | N26: Directly usable given your existing LangChain/agents background. | P26: 0 | Q26: =IF(OR(O26="",P26=0),"",O26+CHOOSE(P26,1,3,7,14,30,90,365))
A27: Not Started | B27: Evaluation | C27: LLM-as-judge, benchmark design, eval contamination | D27: Advanced | E27: Statistics | F27: Design trustworthy evaluations that avoid common LLM-eval pitfalls. | G27: 4 | H27: Hugging Face - LLM Evaluation explained (official course video) | I27: 'Judging LLM-as-a-Judge' paper (Zheng et al, free arXiv) | J27: huggingface.co/docs/lighteval/en/index | K27: Build a small LLM-as-judge eval harness and check its agreement with human labels | L27: Build a regression-test eval suite for a prompt/pipeline you maintain | M27: What biases does LLM-as-judge scoring introduce (e.g. verbosity/position bias)? | How do you detect and prevent benchmark/eval-set contamination in pretraining data? | N27: Weak evaluation is one of the most common real-world failure points in production LLM systems. | P27: 0 | Q27: =IF(OR(O27="",P27=0),"",O27+CHOOSE(P27,1,3,7,14,30,90,365))
A28: Not Started | B28: Agents | C28: ReAct pattern, planning, self-correction loops | D28: Advanced | E28: LLM APIs, LangChain | F28: Understand the core reasoning-acting loop underlying most agent frameworks. | G28: 3 | H28: DeepLearning.AI - AI Agents in LangGraph (free short course) | I28: Original ReAct paper (Yao et al, free arXiv) | J28: python.langchain.com/docs/concepts/agents/ | K28: Build a ReAct-style agent from scratch (no framework) that uses 2 tools | L28: Build a multi-step research agent with self-correction/reflection | M28: Why does interleaving reasoning and acting outperform reasoning-only or acting-only approaches? | How do you prevent an agent from looping indefinitely? | N28: Given your background, this is a strong area to go deep rather than wide. | P28: 0 | Q28: =IF(OR(O28="",P28=0),"",O28+CHOOSE(P28,1,3,7,14,30,90,365))
A29: Not Started | B29: Tool Calling | C29: Function-calling schemas & structured tool invocation | D29: Advanced | E29: Agents | F29: Understand how models are trained/prompted to emit structured, parseable tool calls. | G29: 2 | H29: OpenAI/Anthropic - Function calling explainer (official docs walkthroughs) | I29: Anthropic - Tool use documentation (free) | J29: docs.anthropic.com/en/docs/agents-and-tools/tool-use/overview | K29: Implement a multi-tool agent loop handling tool_use/tool_result turns manually (no SDK helper) | L29: N/A | M29: Why do models need explicit schemas rather than free-text tool descriptions? | How do you handle a model calling a tool with invalid arguments? | N29: Directly maps onto your MCP investigation interest. | P29: 0 | Q29: =IF(OR(O29="",P29=0),"",O29+CHOOSE(P29,1,3,7,14,30,90,365))
A30: Not Started | B30: Memory | C30: Short-term context vs long-term memory architectures for agents | D30: Advanced | E30: RAG, Vector Search | F30: Design memory systems that let agents persist and retrieve information across sessions. | G30: 3 | H30: DeepLearning.AI - Building agentic memory systems (free short course content) | I30: LangChain - Memory concepts documentation (free) | J30: python.langchain.com/docs/concepts/memory/ | K30: Build a simple long-term memory store for an agent using a vector DB + summarization | L30: N/A | M30: What's the tradeoff between raw conversation history and summarized memory? | How do you decide what's worth persisting to long-term memory vs discarding? | N30: A fast-evolving area — worth revisiting resources periodically. | P30: 0 | Q30: =IF(OR(O30="",P30=0),"",O30+CHOOSE(P30,1,3,7,14,30,90,365))
A31: Not Started | B31: MCP | C31: Model Context Protocol for tool/data connectivity | D31: Advanced | E31: Tool Calling, RPC | F31: Understand MCP's client-server model for standardizing how models access tools/data. | G31: 3 | H31: Anthropic - Introducing MCP (official announcement walkthrough) | I31: Anthropic - Model Context Protocol documentation (free) | J31: modelcontextprotocol.io/introduction | K31: Build a minimal MCP server exposing one custom tool and connect a client to it | L31: Wrap one of your existing internal scripts/tools as an MCP server | M31: How does MCP standardize what previously required bespoke integrations per tool? | What's the difference between an MCP 'resource' and a 'tool'? | N31: Given your specific interest in this area, worth deep hands-on practice, not just reading. | P31: 0 | Q31: =IF(OR(O31="",P31=0),"",O31+CHOOSE(P31,1,3,7,14,30,90,365))
A32: Not Started | B32: RAG | C32: Retrieval-augmented generation pipeline design | D32: Advanced | E32: Vector Search, Embeddings | F32: Design a RAG pipeline's retrieval, ranking, and context-injection stages end to end. | G32: 3 | H32: DeepLearning.AI - Building and Evaluating Advanced RAG (free short course) | I32: Original RAG paper (Lewis et al, free arXiv) | J32: python.langchain.com/docs/concepts/rag/ | K32: Build a RAG pipeline with chunking, embedding, retrieval, and re-ranking | L32: Build a RAG system over your own resume/portfolio content and evaluate answer faithfulness | M32: Why does chunk size/overlap significantly affect retrieval quality? | What does a re-ranker add over raw embedding-similarity retrieval? | N32: Given your RAG background, focus this sheet's effort on the harder eval/re-ranking topics. | P32: 0 | Q32: =IF(OR(O32="",P32=0),"",O32+CHOOSE(P32,1,3,7,14,30,90,365))
A33: Not Started | B33: Vector Search | C33: ANN search algorithms & index tuning | D33: Advanced | E33: Vector Databases (see Databases sheet) | F33: Tune vector index parameters for the recall/latency tradeoff your application needs. | G33: 2 | H33: Pinecone - Vector Search 101 (official learning series) | I33: Pinecone Learning Center - ANN algorithms overview | J33: pinecone.io/learn/vector-search-basics/ | K33: Benchmark recall@k vs latency across different HNSW ef_search settings | L33: N/A | M33: How does increasing ef_search trade latency for recall in HNSW? | When would exact (brute-force) search still beat ANN at small scale? | N33: Complements the Vector Databases row in the Databases sheet — study together. | P33: 0 | Q33: =IF(OR(O33="",P33=0),"",O33+CHOOSE(P33,1,3,7,14,30,90,365))
A34: Not Started | B34: Embeddings | C34: Dense embedding models & contrastive training | D34: Advanced | E34: Loss Functions (Deep Learning sheet) | F34: Understand how embedding models are trained to place similar items close in vector space. | G34: 3 | H34: Hugging Face - Sentence Embeddings explained (official course video) | I34: 'Sentence-BERT' paper (Reimers & Gurevych, free arXiv) | J34: huggingface.co/docs/sentence-transformers/en/index | K34: Fine-tune a small embedding model on domain-specific pairs with sentence-transformers | L34: N/A | M34: Why does Sentence-BERT's siamese network structure enable fast similarity search? | How does hard-negative mining improve embedding quality? | N34: Directly determines RAG retrieval quality — often more impactful than the LLM choice itself. | P34: 0 | Q34: =IF(OR(O34="",P34=0),"",O34+CHOOSE(P34,1,3,7,14,30,90,365))
A35: Not Started | B35: Inference Optimization | C35: Batching, KV cache reuse, prompt caching strategies | D35: Expert | E35: PagedAttention, Continuous Batching | F35: Combine the serving-optimization techniques above into a coherent deployment strategy. | G35: 3 | H35: vLLM team - Production LLM Serving talk (official) | I35: Hugging Face - 'A Guide to Efficient LLM Inference' (free blog) | J35: docs.vllm.ai/en/latest/ | K35: Benchmark end-to-end throughput/latency of a self-hosted model under increasing concurrent load | L35: N/A | M35: How does prompt/prefix caching reduce redundant compute for repeated system prompts? | What's the throughput-vs-latency tradeoff of larger batch sizes? | N35: This row ties together everything else in this section into a deployable system. | P35: 0 | Q35: =IF(OR(O35="",P35=0),"",O35+CHOOSE(P35,1,3,7,14,30,90,365))
A36: Not Started | B36: vLLM | C36: Production serving engine architecture | D36: Advanced | E36: PagedAttention, Continuous Batching | F36: Understand vLLM's architecture well enough to deploy and tune it in production. | G36: 3 | H36: vLLM team - vLLM architecture deep dive (official talk) | I36: vLLM official documentation (free) | J36: docs.vllm.ai/en/latest/ | K36: Deploy an open model with vLLM and load-test it with concurrent requests | L36: Stand up a vLLM-served model behind a FastAPI gateway with request queuing | M36: What tunable parameters most affect vLLM's throughput vs latency tradeoff? | How does vLLM decide the KV cache block size? | N36: Directly usable with your existing FastAPI/Docker infrastructure background. | P36: 0 | Q36: =IF(OR(O36="",P36=0),"",O36+CHOOSE(P36,1,3,7,14,30,90,365))
A37: Not Started | B37: TensorRT-LLM | C37: NVIDIA's compiled inference engine | D37: Expert | E37: CUDA basics, vLLM concepts | F37: Understand how TensorRT-LLM's ahead-of-time compilation trades flexibility for raw speed. | G37: 4 | H37: NVIDIA - TensorRT-LLM overview (official GTC talk) | I37: NVIDIA TensorRT-LLM official documentation (free) | J37: github.com/NVIDIA/TensorRT-LLM | K37: Compile and benchmark a small open model with TensorRT-LLM vs vLLM on the same hardware | L37: N/A | M37: Why does ahead-of-time kernel compilation give TensorRT-LLM an edge over more flexible runtimes? | What's the tradeoff of TensorRT-LLM's longer build/compile step? | N37: High-value, NVIDIA-specific knowledge directly relevant to your target companies. | P37: 0 | Q37: =IF(OR(O37="",P37=0),"",O37+CHOOSE(P37,1,3,7,14,30,90,365))

Sheet CUDA & GPU Programming
A1: CUDA & GPU Programming
A2: GPU architecture, memory hierarchy, and modern kernel-authoring tools (Triton).
A3: Sheet Progress — 15 topics total | Q3: =ROUND(COUNTIF(A5:A22,"Completed")/SUMPRODUCT(COUNTIF(A5:A22,{"Completed","In Progress","Not Started","Research","Project","Optional"}))*100,0) -> 0
A4: Status | B4: Topic | C4: Subtopic | D4: Difficulty | E4: Prerequisites | F4: Learning Goal | G4: Est. Hours | H4: Best YouTube Resource | I4: Best Reading | J4: Official Documentation | K4: Coding Exercise | L4: Mini Project | M4: Interview Questions | N4: Notes | O4: Date Completed | P4: Revision Stage | Q4: Revision Date
A5: GPU Architecture & Programming Model
A6: Not Started | B6: GPU Architecture | C6: SMs, warps, CUDA cores vs Tensor Cores | D6: Advanced | E6: Computer architecture basics | F6: Understand the hierarchy from GPU -> Streaming Multiprocessor -> warp -> thread. | G6: 4 | H6: NVIDIA - CUDA architecture overview (official GTC talk) | I6: 'Programming Massively Parallel Processors' Ch.4 (Kirk & Hwu) - selected free chapters | J6: docs.nvidia.com/cuda/cuda-c-programming-guide/index.html#hardware-implementation | K6: Query your GPU's SM count/warp size with a small CUDA device-query program | L6: N/A | M6: Why does a GPU favor thousands of simple cores over a few complex ones? | What's the relationship between an SM and the warps it schedules? | N6: NVIDIA's own CUDA C Programming Guide is the definitive free reference for this whole sheet. | P6: 0 | Q6: =IF(OR(O6="",P6=0),"",O6+CHOOSE(P6,1,3,7,14,30,90,365))
A7: Not Started | B7: CUDA Programming | C7: Kernels, grids, blocks, threads | D7: Advanced | E7: GPU Architecture, C/C++ | F7: Write and launch a basic CUDA kernel, understanding the grid/block/thread hierarchy. | G7: 4 | H7: freeCodeCamp - CUDA Programming Course (full free course) | I7: NVIDIA CUDA C Programming Guide Ch.2-3 (free) | J7: docs.nvidia.com/cuda/cuda-c-programming-guide/ | K7: Write a CUDA kernel for element-wise vector addition and benchmark vs CPU NumPy | L7: Implement a tiled matrix multiplication CUDA kernel | M7: How do you choose block size and grid size for a given problem? | What determines whether a kernel launch is compute- or memory-bound? | N7: freeCodeCamp's course is a genuinely excellent, free, hands-on introduction. | P7: 0 | Q7: =IF(OR(O7="",P7=0),"",O7+CHOOSE(P7,1,3,7,14,30,90,365))
A8: Not Started | B8: PTX | C8: Parallel Thread Execution intermediate representation | D8: Expert | E8: CUDA Programming | F8: Understand PTX as CUDA's portable intermediate assembly-like representation. | G8: 3 | H8: NVIDIA - PTX ISA overview (official GTC talk) | I8: NVIDIA PTX ISA reference documentation (free) | J8: docs.nvidia.com/cuda/parallel-thread-execution/ | K8: Inspect the PTX output of a simple CUDA kernel with nvcc -ptx | L8: N/A | M8: Why does CUDA compile to PTX before SASS (device-specific machine code)? | How does PTX enable forward compatibility across GPU generations? | N8: Understanding PTX matters when writing Triton kernels or debugging compiler output. | P8: 0 | Q8: =IF(OR(O8="",P8=0),"",O8+CHOOSE(P8,1,3,7,14,30,90,365))
A9: Not Started | B9: Tensor Cores | C9: Mixed-precision matrix-multiply-accumulate units | D9: Expert | E9: GPU Architecture, Linear Algebra | F9: Understand how Tensor Cores accelerate the matmuls that dominate deep learning compute. | G9: 4 | H9: NVIDIA - Tensor Core Programming (official GTC talk) | I9: NVIDIA Tensor Core programming guide (free) | J9: docs.nvidia.com/cuda/cuda-c-programming-guide/#warp-matrix-functions | K9: Compare FP32 vs TF32/FP16 Tensor Core matmul throughput on your GPU | L9: N/A | M9: Why do Tensor Cores require specific matrix tile shapes to reach peak throughput? | What precision tradeoffs come with TF32 vs FP16 vs BF16 Tensor Core paths? | N9: Directly explains why mixed-precision training gives large real-world speedups. | P9: 0 | Q9: =IF(OR(O9="",P9=0),"",O9+CHOOSE(P9,1,3,7,14,30,90,365))
A10: Memory Hierarchy & Scheduling
A11: Not Started | B11: Shared Memory | C11: On-chip scratchpad memory & bank conflicts | D11: Expert | E11: CUDA Programming | F11: Use shared memory to avoid repeated global-memory round trips within a block. | G11: 4 | H11: NVIDIA - CUDA Shared Memory optimization (official GTC talk) | I11: NVIDIA CUDA Best Practices Guide Ch.9 (free) | J11: docs.nvidia.com/cuda/cuda-c-best-practices-guide/index.html#shared-memory | K11: Rewrite a naive matmul kernel to use shared-memory tiling and benchmark the speedup | L11: N/A | M11: What causes a shared-memory bank conflict and how do you avoid it? | Why is shared memory an order of magnitude faster than global memory? | N11: Tiled matmul with shared memory is the canonical CUDA optimization exercise. | P11: 0 | Q11: =IF(OR(O11="",P11=0),"",O11+CHOOSE(P11,1,3,7,14,30,90,365))
A12: Not Started | B12: Warp Scheduling | C12: Warp divergence & scheduler occupancy | D12: Expert | E12: CUDA Programming, GPU Architecture | F12: Understand how branch divergence within a warp serializes execution. | G12: 3 | H12: NVIDIA - Warp-level programming (official GTC talk) | I12: NVIDIA CUDA Best Practices Guide Ch.10 (free) | J12: docs.nvidia.com/cuda/cuda-c-programming-guide/#simt-architecture | K12: Write a kernel with intentional warp divergence and measure the slowdown | L12: N/A | M12: Why does an if/else branch inside a warp cause serialized execution of both paths? | How do warp-level primitives (__shfl_sync) avoid shared memory for small reductions? | N12: Divergence is one of the most common silent-performance-killers in naive CUDA code. | P12: 0 | Q12: =IF(OR(O12="",P12=0),"",O12+CHOOSE(P12,1,3,7,14,30,90,365))
A13: Not Started | B13: Memory Coalescing | C13: Aligned, contiguous global-memory access patterns | D13: Expert | E13: GPU Architecture | F13: Structure memory access patterns so a warp's loads merge into few transactions. | G13: 3 | H13: NVIDIA - Global Memory coalescing (official GTC talk) | I13: NVIDIA CUDA Best Practices Guide Ch.9.2 (free) | J13: docs.nvidia.com/cuda/cuda-c-best-practices-guide/index.html#coalesced-access-to-global-memory | K13: Compare a coalesced vs strided-access kernel's memory throughput | L13: N/A | M13: What makes a memory access pattern 'coalesced' from a warp's perspective? | Why does column-major vs row-major matrix layout affect coalescing? | N13: This single concept explains a large fraction of real-world CUDA kernel slowdowns. | P13: 0 | Q13: =IF(OR(O13="",P13=0),"",O13+CHOOSE(P13,1,3,7,14,30,90,365))
A14: Not Started | B14: Occupancy | C14: Balancing registers, shared memory, and thread count | D14: Expert | E14: Warp Scheduling, Shared Memory | F14: Tune kernel resource usage to maximize the number of resident warps per SM. | G14: 3 | H14: NVIDIA - Occupancy Calculator & tuning (official GTC talk) | I14: NVIDIA CUDA Occupancy Calculator documentation (free) | J14: docs.nvidia.com/cuda/cuda-occupancy-calculator/index.html | K14: Use the CUDA occupancy calculator to tune a kernel's block size for max occupancy | L14: N/A | M14: Why doesn't maximum occupancy always mean maximum performance? | What resource (registers, shared memory, threads) is usually the limiting factor? | N14: High occupancy is necessary but not sufficient — a nuance that separates strong candidates. | P14: 0 | Q14: =IF(OR(O14="",P14=0),"",O14+CHOOSE(P14,1,3,7,14,30,90,365))
A15: Streams, Fusion & Modern Tooling
A16: Not Started | B16: Streams | C16: Overlapping compute and data transfer | D16: Advanced | E16: CUDA Programming | F16: Use CUDA streams to overlap kernel execution with host-device memory transfers. | G16: 3 | H16: NVIDIA - CUDA Streams & Concurrency (official GTC talk) | I16: NVIDIA CUDA C Programming Guide Ch.3.2.5 (free) | J16: docs.nvidia.com/cuda/cuda-c-programming-guide/#asynchronous-concurrent-execution | K16: Overlap a memcpy and kernel execution using two CUDA streams and measure the win | L16: N/A | M16: Why does overlapping transfer and compute require pinned host memory? | How many concurrent streams actually help before hardware limits saturate? | N16: Directly relevant to hiding PCIe transfer latency in a training/inference pipeline. | P16: 0 | Q16: =IF(OR(O16="",P16=0),"",O16+CHOOSE(P16,1,3,7,14,30,90,365))
A17: Not Started | B17: Kernel Fusion | C17: Fusing multiple ops into a single kernel launch | D17: Expert | E17: CUDA Programming, Streams | F17: Understand how fusing ops reduces kernel-launch overhead and memory round trips. | G17: 3 | H17: NVIDIA/PyTorch - torch.compile & kernel fusion (official talk) | I17: PyTorch 2.0 - torch.compile technical overview (free blog) | J17: pytorch.org/docs/stable/torch.compiler.html | K17: Compare unfused vs fused elementwise op throughput using torch.compile | L17: N/A | M17: Why does fusing elementwise ops reduce memory bandwidth pressure specifically? | How does torch.compile decide what to fuse automatically? | N17: This is exactly what torch.compile (via Triton/Inductor) automates under the hood. | P17: 0 | Q17: =IF(OR(O17="",P17=0),"",O17+CHOOSE(P17,1,3,7,14,30,90,365))
A18: Not Started | B18: CUDA Graphs | C18: Capturing and replaying kernel launch sequences | D18: Expert | E18: Streams, Kernel Fusion | F18: Understand how CUDA graphs eliminate per-kernel launch overhead for repeated workloads. | G18: 3 | H18: NVIDIA - CUDA Graphs deep dive (official GTC talk) | I18: NVIDIA CUDA C Programming Guide Ch.3.2.9 (free) | J18: docs.nvidia.com/cuda/cuda-c-programming-guide/#cuda-graphs | K18: Capture a small multi-kernel sequence as a CUDA graph and benchmark replay vs re-launch | L18: N/A | M18: Why does launch overhead matter more for many-small-kernel workloads (like LLM inference)? | What's captured in a CUDA graph vs re-executed each replay? | N18: Increasingly important for reducing CPU-side launch overhead in LLM inference loops. | P18: 0 | Q18: =IF(OR(O18="",P18=0),"",O18+CHOOSE(P18,1,3,7,14,30,90,365))
A19: Not Started | B19: Triton | C19: Python-level GPU kernel authoring | D19: Expert | E19: CUDA Programming basics, Python | F19: Write custom GPU kernels in Triton without hand-writing CUDA C++. | G19: 4 | H19: OpenAI - Triton official tutorial series (free) | I19: Triton official documentation & tutorials (free) | J19: triton-lang.org/main/index.html | K19: Write a fused softmax kernel in Triton and benchmark against PyTorch's native op | L19: Write a custom fused attention kernel in Triton | M19: Why does Triton let you reach near-hand-tuned-CUDA performance with far less code? | How does Triton's block-level programming model differ from raw CUDA's thread-level model? | N19: The pragmatic modern path to custom kernels without deep raw-CUDA expertise. | P19: 0 | Q19: =IF(OR(O19="",P19=0),"",O19+CHOOSE(P19,1,3,7,14,30,90,365))
A20: Not Started | B20: Nsight | C20: NVIDIA's profiling & debugging toolset | D20: Advanced | E20: CUDA Programming | F20: Use Nsight Systems/Compute to profile and debug real CUDA kernels. | G20: 3 | H20: NVIDIA - Nsight Systems & Compute tutorial (official GTC talk) | I20: NVIDIA Nsight Systems/Compute documentation (free) | J20: developer.nvidia.com/nsight-systems | K20: Profile a CUDA kernel with Nsight Compute and identify its limiting resource | L20: N/A | M20: How do you distinguish a memory-bound from a compute-bound kernel in Nsight Compute? | What does Nsight Systems show that Nsight Compute doesn't (timeline vs per-kernel)? | N20: The professional-grade equivalent of perf/flamegraphs, but for GPU code. | P20: 0 | Q20: =IF(OR(O20="",P20=0),"",O20+CHOOSE(P20,1,3,7,14,30,90,365))
A21: Not Started | B21: Profiling | C21: Roofline model & bottleneck identification | D21: Expert | E21: Nsight, Occupancy | F21: Use the roofline model to determine whether a kernel is compute- or memory-bound. | G21: 3 | H21: NVIDIA - Roofline analysis with Nsight Compute (official GTC talk) | I21: NVIDIA roofline model application notes (free) | J21: docs.nvidia.com/nsight-compute/NsightCompute/index.html#roofline-charts | K21: Plot a kernel's achieved performance against the roofline model for your GPU | L21: N/A | M21: How do you compute a kernel's arithmetic intensity for the roofline model? | Why does a memory-bound kernel not benefit from more compute (Tensor Cores)? | N21: Ties GPU architecture, memory coalescing, and occupancy together into one diagnostic framework. | P21: 0 | Q21: =IF(OR(O21="",P21=0),"",O21+CHOOSE(P21,1,3,7,14,30,90,365))
A22: Not Started | B22: Performance Optimization | C22: End-to-end CUDA kernel optimization workflow | D22: Expert | E22: All CUDA topics above | F22: Apply a systematic optimization workflow: profile, identify bottleneck, fix, repeat. | G22: 3 | H22: NVIDIA - GPU Performance Optimization workflow (official GTC talk) | I22: NVIDIA CUDA Best Practices Guide Ch.1-2 (free, workflow overview) | J22: docs.nvidia.com/cuda/cuda-c-best-practices-guide/ | K22: Take a naive kernel through 3+ optimization passes, benchmarking each step | L22: Optimize a real attention or matmul kernel from naive to near-peak throughput | M22: What's the right order to check bottlenecks (occupancy, coalescing, divergence, etc)? | How do you know when a kernel is 'good enough' to stop optimizing? | N22: This row is the capstone exercise for the whole CUDA sheet. | P22: 0 | Q22: =IF(OR(O22="",P22=0),"",O22+CHOOSE(P22,1,3,7,14,30,90,365))

Sheet Distributed Systems
A1: Distributed Systems
A2: Consensus, streaming infra, and the specific parallelism strategies behind large-model training.
A3: Sheet Progress — 22 topics total | Q3: =ROUND(COUNTIF(A5:A29,"Completed")/SUMPRODUCT(COUNTIF(A5:A29,{"Completed","In Progress","Not Started","Research","Project","Optional"}))*100,0) -> 0
A4: Status | B4: Topic | C4: Subtopic | D4: Difficulty | E4: Prerequisites | F4: Learning Goal | G4: Est. Hours | H4: Best YouTube Resource | I4: Best Reading | J4: Official Documentation | K4: Coding Exercise | L4: Mini Project | M4: Interview Questions | N4: Notes | O4: Date Completed | P4: Revision Stage | Q4: Revision Date
A5: Consensus & Fundamentals
A6: Not Started | B6: CAP | C6: Consistency, Availability, Partition tolerance tradeoff | D6: Advanced | E6: Distributed systems fundamentals | F6: Understand what CAP actually constrains (and commonly misunderstood nuances). | G6: 2 | H6: MIT 6.824 - Distributed Systems (Robert Morris, free full course) | I6: 'Designing Data-Intensive Applications' Ch.9 (Kleppmann) | J6: N/A | K6: N/A | L6: N/A | M6: Why is CAP really about behavior during a partition, not a permanent 3-way tradeoff? | What is PACELC and what does it add to CAP? | N6: MIT 6.824 is the gold-standard free distributed systems course. | P6: 0 | Q6: =IF(OR(O6="",P6=0),"",O6+CHOOSE(P6,1,3,7,14,30,90,365))
A7: Not Started | B7: Raft | C7: Leader election & log replication consensus | D7: Expert | E7: CAP | F7: Understand Raft's mechanism for maintaining a consistent replicated log despite failures. | G7: 5 | H7: MIT 6.824 - Raft lectures (Robert Morris, free) | I7: 'In Search of an Understandable Consensus Algorithm' (Raft paper, Ongaro & Ousterhout, free) | J7: raft.github.io | K7: Implement leader election for a simplified Raft cluster in Python | L7: Implement a toy Raft-based replicated key-value store | M7: How does Raft guarantee log entries, once committed, are never lost? | What happens during a Raft leader election with a split vote? | N7: raft.github.io has an excellent interactive visualization of the algorithm. | P7: 0 | Q7: =IF(OR(O7="",P7=0),"",O7+CHOOSE(P7,1,3,7,14,30,90,365))
A8: Not Started | B8: Paxos | C8: Classic consensus protocol & Multi-Paxos | D8: Expert | E8: Raft | F8: Understand Paxos as the theoretical precursor to Raft, and why Raft is more understandable. | G8: 4 | H8: MIT 6.824 - Paxos lecture (Robert Morris, free) | I8: 'Paxos Made Simple' (Lamport, free paper) | J8: N/A | K8: N/A | L8: N/A | M8: Why is Paxos notoriously hard to implement correctly compared to Raft? | What problem does Multi-Paxos solve over single-decree Paxos? | N8: Understanding both Paxos and Raft signals real consensus-protocol depth. | P8: 0 | Q8: =IF(OR(O8="",P8=0),"",O8+CHOOSE(P8,1,3,7,14,30,90,365))
A9: Streaming, Data & Orchestration
A10: Not Started | B10: Kafka | C10: Log-based pub/sub, partitions, consumer groups | D10: Advanced | E10: Distributed systems fundamentals | F10: Understand Kafka's append-only log model and how partitioning enables parallelism. | G10: 4 | H10: Confluent - Kafka Internals (official free course) | I10: Kafka official documentation - Design section (free) | J10: kafka.apache.org/documentation/#design | K10: Produce/consume messages across multiple partitions and observe consumer-group rebalancing | L10: Build an event-driven pipeline using Kafka between two services | M10: Why does partition count set the upper bound on consumer parallelism? | How does Kafka guarantee ordering within a partition but not across partitions? | N10: Confluent's free courses are the best vendor-produced deep dive available. | P10: 0 | Q10: =IF(OR(O10="",P10=0),"",O10+CHOOSE(P10,1,3,7,14,30,90,365))
A11: Not Started | B11: Redis | C11: Data structures, persistence (RDB/AOF), pub/sub | D11: Advanced | E11: Caching concepts | F11: Go beyond basic caching to Redis's persistence and pub/sub capabilities. | G11: 3 | H11: Redis official - Redis University RU101 (free course) | I11: Redis official documentation (free) | J11: redis.io/docs/latest/ | K11: Compare RDB snapshotting vs AOF durability tradeoffs experimentally | L11: N/A | M11: What's the durability/performance tradeoff between RDB and AOF persistence? | How does Redis pub/sub differ from a durable queue like Kafka? | N11: Given your existing Redis experience, focus here on persistence/durability nuances you may not have used yet. | P11: 0 | Q11: =IF(OR(O11="",P11=0),"",O11+CHOOSE(P11,1,3,7,14,30,90,365))
A12: Not Started | B12: Ray | C12: Distributed Python for ML workloads, actors & tasks | D12: Advanced | E12: Multiprocessing (Python sheet) | F12: Understand Ray's actor/task abstractions for distributed Python compute. | G12: 3 | H12: Anyscale - Ray Core official crash course (free) | I12: Ray official documentation - Ray Core concepts (free) | J12: docs.ray.io/en/latest/ray-core/walkthrough.html | K12: Parallelize a data-preprocessing pipeline across a local Ray cluster | L12: Build a distributed hyperparameter sweep using Ray Tune | M12: When would you use a Ray actor instead of a stateless task? | How does Ray's scheduler place tasks across a cluster? | N12: Ray is increasingly the default for distributed LLM training/serving orchestration in Python. | P12: 0 | Q12: =IF(OR(O12="",P12=0),"",O12+CHOOSE(P12,1,3,7,14,30,90,365))
A13: Not Started | B13: Spark | C13: RDDs/DataFrames, lazy evaluation, shuffle | D13: Advanced | E13: Distributed systems fundamentals | F13: Understand Spark's lazy execution model and why shuffles are expensive. | G13: 3 | H13: Databricks - Apache Spark official crash course (free) | I13: Spark official documentation - RDD Programming Guide (free) | J13: spark.apache.org/docs/latest/rdd-programming-guide.html | K13: Profile a Spark job's stages and identify a shuffle-heavy bottleneck | L13: N/A | M13: Why is a shuffle the most expensive operation in a Spark job? | What does Spark's lazy evaluation (DAG of transformations) optimize for? | N13: Relevant to large-scale pretraining-data preprocessing pipelines. | P13: 0 | Q13: =IF(OR(O13="",P13=0),"",O13+CHOOSE(P13,1,3,7,14,30,90,365))
A14: Not Started | B14: Flink | C14: Stream processing with exactly-once semantics | D14: Expert | E14: Kafka | F14: Understand how Flink achieves exactly-once processing guarantees via checkpointing. | G14: 3 | H14: Ververica (Flink creators) - Flink official crash course (free) | I14: Flink official documentation - Concepts (free) | J14: nightlies.apache.org/flink/flink-docs-stable/docs/concepts/overview/ | K14: N/A | L14: N/A | M14: How does Flink's checkpointing (Chandy-Lamport-based) enable exactly-once semantics? | When would you choose Flink over Spark Streaming? | N14: Less commonly needed day-to-day but a strong 'real-time systems depth' signal. | P14: 0 | Q14: =IF(OR(O14="",P14=0),"",O14+CHOOSE(P14,1,3,7,14,30,90,365))
A15: Not Started | B15: Kubernetes | C15: Pods, deployments, autoscaling, scheduling | D15: Advanced | E15: Docker | F15: Understand how Kubernetes schedules and manages containerized workloads at scale. | G15: 4 | H15: TechWorld with Nana - Kubernetes crash course (free) | I15: Kubernetes official documentation - Concepts (free) | J15: kubernetes.io/docs/concepts/ | K15: Deploy a containerized service to a local Kubernetes cluster (kind/minikube) with autoscaling | L15: Deploy a model-serving container behind a Kubernetes HPA (horizontal pod autoscaler) | M15: How does the Kubernetes scheduler decide which node runs a pod? | What triggers a horizontal pod autoscaler to scale up/down? | N15: Given your Docker background, this is the natural next layer up. | P15: 0 | Q15: =IF(OR(O15="",P15=0),"",O15+CHOOSE(P15,1,3,7,14,30,90,365))
A16: Not Started | B16: Docker | C16: Multi-stage builds, layer caching, networking | D16: Advanced | E16: Containers fundamentals | F16: Go beyond basic Docker usage into build efficiency and networking internals. | G16: 2 | H16: TechWorld with Nana - Docker deep dive (free) | I16: Docker official documentation - Build guide (free) | J16: docs.docker.com/build/building/best-practices/ | K16: Optimize a slow Docker build using multi-stage builds and layer-cache ordering | L16: N/A | M16: Why does layer order in a Dockerfile affect build cache efficiency? | How does a multi-stage build reduce final image size? | N16: Quick refresher sheet since this is already a known strength for you. | P16: 0 | Q16: =IF(OR(O16="",P16=0),"",O16+CHOOSE(P16,1,3,7,14,30,90,365))
A17: Not Started | B17: Service Mesh | C17: Sidecar pattern, traffic management, mTLS | D17: Expert | E17: Envoy (Networking sheet), Kubernetes | F17: Understand what a service mesh adds on top of raw Kubernetes networking. | G17: 3 | H17: Istio official - Service Mesh explained (official talk) | I17: Istio official documentation - Concepts (free) | J17: istio.io/latest/docs/concepts/what-is-istio/ | K17: N/A | L17: N/A | M17: What does a service mesh provide that Kubernetes networking alone doesn't (mTLS, retries, observability)? | Why is the sidecar pattern used instead of a shared library? | N17: Builds directly on the Envoy row in the Networking sheet. | P17: 0 | Q17: =IF(OR(O17="",P17=0),"",O17+CHOOSE(P17,1,3,7,14,30,90,365))
A18: Not Started | B18: Microservices | C18: Decomposition boundaries & distributed-system tradeoffs | D18: Advanced | E18: Service Mesh, RPC | F18: Understand when microservices' operational cost is worth their decoupling benefit. | G18: 2 | H18: MIT 6.824 adjacent - Microservices tradeoffs talk (conference talks) | I18: 'Designing Data-Intensive Applications' Ch.4 (schema evolution, service boundaries) | J18: N/A | K18: N/A | L18: N/A | M18: What operational costs does splitting a monolith into microservices introduce? | How do you choose service boundaries (by data ownership vs by team)? | N18: A common 'when would you NOT use microservices' senior-level question. | P18: 0 | Q18: =IF(OR(O18="",P18=0),"",O18+CHOOSE(P18,1,3,7,14,30,90,365))
A19: Distributed Training & Checkpointing
A20: Not Started | B20: Distributed Training | C20: Why single-GPU training doesn't scale to modern LLM sizes | D20: Advanced | E20: Deep Learning fundamentals | F20: Understand the memory and compute limits that force distributed training strategies. | G20: 3 | H20: Hugging Face - Efficient Training on Multiple GPUs (official course video) | I20: Hugging Face documentation - Model Parallelism guide (free) | J20: huggingface.co/docs/transformers/en/perf_train_gpu_many | K20: Estimate the GPU memory required to train a 7B parameter model with Adam | L20: N/A | M20: Why does the optimizer state (not just weights) dominate memory for Adam-trained models? | At what model size does a single GPU's memory become the binding constraint? | N20: Sets up the specific parallelism strategies covered in the rows below. | P20: 0 | Q20: =IF(OR(O20="",P20=0),"",O20+CHOOSE(P20,1,3,7,14,30,90,365))
A21: Not Started | B21: Tensor Parallelism | C21: Splitting individual layers/matmuls across GPUs | D21: Expert | E21: Distributed Training, Linear Algebra | F21: Understand how a single matmul is split across GPUs within a layer. | G21: 4 | H21: Hugging Face - Tensor Parallelism explained (official course video) | I21: Megatron-LM paper (Shoeybi et al, free arXiv) | J21: huggingface.co/docs/transformers/en/perf_train_gpu_many#tensor-parallelism | K21: Trace through how a column-parallel then row-parallel matmul pair avoids an extra communication step | L21: N/A | M21: Why does Megatron-style tensor parallelism pair column-parallel and row-parallel layers? | What communication pattern (all-reduce) does tensor parallelism require per layer? | N21: Directly explains Megatron-LM's core design used to train many large models. | P21: 0 | Q21: =IF(OR(O21="",P21=0),"",O21+CHOOSE(P21,1,3,7,14,30,90,365))
A22: Not Started | B22: Pipeline Parallelism | C22: Splitting layers across GPUs & pipeline bubbles | D22: Expert | E22: Distributed Training | F22: Understand how splitting a model by layer across GPUs introduces pipeline bubbles. | G22: 4 | H22: Hugging Face - Pipeline Parallelism explained (official course video) | I22: GPipe paper (Huang et al, free arXiv) | J22: huggingface.co/docs/transformers/en/perf_train_gpu_many#pipeline-parallelism | K22: Simulate pipeline bubble overhead for different micro-batch counts | L22: N/A | M22: What causes a 'pipeline bubble' and how does micro-batching reduce it? | Why must activation memory be kept for the entire pipeline depth? | N22: The bubble-overhead math here is a common quantitative interview question. | P22: 0 | Q22: =IF(OR(O22="",P22=0),"",O22+CHOOSE(P22,1,3,7,14,30,90,365))
A23: Not Started | B23: Data Parallelism | C23: Replicated model, sharded data, gradient all-reduce | D23: Advanced | E23: Distributed Training | F23: Understand the simplest and most common form of distributed training. | G23: 2 | H23: Hugging Face - Data Parallelism explained (official course video) | I23: PyTorch DDP official documentation (free) | J23: pytorch.org/tutorials/intermediate/ddp_tutorial.html | K23: Train a small model with PyTorch DistributedDataParallel across 2+ simulated workers | L23: N/A | M23: Why does data parallelism require an all-reduce of gradients every step? | What limits data parallelism's scaling (communication bandwidth)? | N23: The baseline everyone starts with before reaching for tensor/pipeline parallelism. | P23: 0 | Q23: =IF(OR(O23="",P23=0),"",O23+CHOOSE(P23,1,3,7,14,30,90,365))
A24: Not Started | B24: FSDP | C24: Fully Sharded Data Parallel — sharding optimizer/gradients/weights | D24: Expert | E24: Data Parallelism, ZeRO | F24: Understand how FSDP shards model state across GPUs to fit larger models than DDP allows. | G24: 4 | H24: PyTorch - FSDP official deep dive (official talk) | I24: PyTorch FSDP official documentation (free) | J24: pytorch.org/docs/stable/fsdp.html | K24: Train a model with PyTorch FSDP and compare peak memory usage to plain DDP | L24: N/A | M24: What does FSDP shard that plain DDP doesn't (optimizer state, gradients, weights)? | How does FSDP's all-gather-before-compute pattern trade communication for memory? | N24: PyTorch's native answer to DeepSpeed's ZeRO, directly comparable to it. | P24: 0 | Q24: =IF(OR(O24="",P24=0),"",O24+CHOOSE(P24,1,3,7,14,30,90,365))
